Workbook
Name all_brassica: 'PROXY def''ns'!$I$4:$I$20
Name all_fish: 'PROXY def''ns'!$F$98:$F$104
Name almond: 'PROXY def''ns'!$F$73:$F$74
Name apple: 'PROXY def''ns'!$F$55:$F$56
Name apricot: 'PROXY def''ns'!$F$61:$F$62
Name artichoke_globe: 'PROXY def''ns'!$F$90:$F$91
Name asparagus: 'PROXY def''ns'!$F$86:$F$87
Name banana: 'PROXY def''ns'!$F$92:$F$93
Name bean_dry: 'PROXY def''ns'!$F$26:$F$27
Name bean_snap_succulent: 'PROXY def''ns'!$F$22:$F$23
Name beer: 'PROXY def''ns'!$F$125:$F$126
Name berry: 'PROXY def''ns'!$B$4:$B$13
Name brass_grns_E: 'Pivot Table_CED'!$T$11
Name brass_grns_GHG: 'Pivot Table_CED'!$U$11
Name brassica: 'PROXY def''ns'!$B$22:$B$27
Name brassica_greens: 'PROXY def''ns'!$B$28:$B$35
Name brassica_roots: 'PROXY def''ns'!$B$36:$B$40
Name broccoli: 'PROXY def''ns'!$F$17:$F$18
Name carrot: 'PROXY def''ns'!$F$4:$F$5
Name cassava: 'PROXY def''ns'!$F$6:$F$7
Name celery: 'PROXY def''ns'!$F$88:$F$89
Name cherry: 'PROXY def''ns'!$F$59:$F$60
Name Chicken: 'PROXY def''ns'!$F$118:$F$119
Name choc_coffee_tea: 'PROXY def''ns'!$I$110:$I$117
Name citrus: 'PROXY def''ns'!$B$41:$B$52
Name clover_seed: 'PROXY def''ns'!$B$15:$B$16
Name coconut_meat: 'PROXY def''ns'!$F$75:$F$76
Name coconut_oil: 'PROXY def''ns'!$I$65:$I$66
Name corn_flour: 'PROXY def''ns'!$F$121:$F$122
Name corn_starch: 'PROXY def''ns'!$F$123:$F$124
Name cucumber: 'PROXY def''ns'!$F$45:$F$46
Name cucurbits: 'PROXY def''ns'!$I$122:$I$132
Name dried_herbs: 'PROXY def''ns'!$B$53:$B$55
Name endive: 'PROXY def''ns'!$F$13:$F$14
Name Escarole: 'PROXY def''ns'!$F$111:$F$112
Name flours: 'PROXY def''ns'!$I$68:$I$73
Name Fluid_milk_cow: 'PROXY def''ns'!$I$119:$I$120
Name Food_Form: '[1]List Names'!$C$3:$C$8
Name Food_Type: '[1]List Names'!$B$3:$B$16
Name FoodForm: #REF!
Name FoodTypes: #REF!
Name fresh_herbs: 'PROXY def''ns'!$B$56:$B$65
Name ginger: 'PROXY def''ns'!$F$11:$F$12
Name grains: 'PROXY def''ns'!$B$66:$B$77
Name grape: 'PROXY def''ns'!$F$69:$F$70
Name grape_raisin: 'PROXY def''ns'!$F$67:$F$68
Name greens: 'PROXY def''ns'!$B$78:$B$88
Name honey: 'PROXY def''ns'!$F$109:$F$110
Name legume_seed: 'PROXY def''ns'!$I$23:$I$32
Name lentil_seed: 'PROXY def''ns'!$F$28:$F$29
Name Maple_syrup: 'PROXY def''ns'!$F$115:$F$116
Name melon: 'PROXY def''ns'!$F$40:$F$43
Name nightshades: 'PROXY def''ns'!$F$34:$F$37
Name nonruminant_meat: 'PROXY def''ns'!$F$139:$F$144
Name nut: 'PROXY def''ns'!$B$89:$B$101
Name oat_flour: 'PROXY def''ns'!$F$127:$F$128
Name oils: 'PROXY def''ns'!$B$148:$B$161
Name oilseed_oil: 'PROXY def''ns'!$B$140:$B$146
Name onion_bulb: 'PROXY def''ns'!$F$15:$F$16
Name orange: 'PROXY def''ns'!$F$53:$F$54

Sheet DESCRIPTION
A2: Welcome to dataFIELD version 1.0 - (database of Food Impacts on the Environment for Linking to Diets)
B3: This version links greenhouse gas emissions (GHGE) and cumulative energy demand (CED) associated with PRODUCTION of food commodities to the 2005-2010 FCID commodity codes. | S3: http://fcid.foodrisk.org/
B4: FCID commodity codes can then be used to link to NHANES datasets.
A5: The methods used to compile this database are described in the journal article:
B6: Heller MC, Willits-Smith A, Meyer R, Keoleian GA, Rose D (2018) Greenhouse gas emissions and energy use associated with production of individual self-selected U.S. diets. Environ Res Lett 13
B7: https://doi.org/10.1088/1748-9326/aab0ac
A8: *MODIFICATIONS TO THIS WORKBOOK ARE AT YOUR OWN RISK. The modifier is responsible for assuring that functionality is maintained. No efforts have been made to "lock" or otherwise protect necessary functionality.
A10: Workbook Contents
A11: below are brief descriptions of the sheets in this workbook. For more complete descriptions and suggestions for use, see the accompanying document:
B13: FCID Linkages | C13: contains final (utlized) impact factors. Assigns impact factors to FCID commodities, assigns proxies, and executes necessary mass conversions
B14: literature entries | C14: raw data entries logged in literature review, including metadata, references
B15: Pivot Table_GHG | C15: GHGE data from "literature entries" sheet aggregated by specific food type and boundary condition (farm gate vs. processor gate)
B16: Pivot Table_CED | C16: CED data from "literature entries" sheet aggregated by specific food type and boundary condition (farm gate vs. processor gate)
B17: PROXY def'ns | C17: contains proxy definitions used to fill FICD commodities without direct matches.
B18: MassConv | C18: compilation of mass conversions used to account for inedible portions, etc. The source of the conversion factor used for each FCID entry is defined in column "I" of the FCID Linkages sheet

Sheet FCID linkages
F1: UTILIZED IMPACT FACTORS | J1: farm gate (=1) | K1: PROXY DEFINITION | L1: ENERGY USE MJ/kg | P1: GHG Emissions (kg CO2eq/kg) | T1: additional processing inputs for select foods | W1: VARIANCE CALCULATIONS
E2: number of times specific commodity appears in FCID recipe files | F2: CED | G2: GHG | L2: PROXY? | P2: PROXY? | T2: Energy (MJ) | U2: GHG (kgCO2eq) | W2: Energy Use (MJ/kg) | AB2: GHGE
A3: FCID_Code | B3: FCID_Desc | C3: Weight_Basis_ as defined by FCID | D3: Comments (from FCID) | E3: N_Cases | F3: MJ / kg | G3: CO2 eq / kg | H3: weight Conversion Factor | I3: conversion factor source | J3: or processor gate (=2)? | M3: # of datapoints | N3: N-average | O3: Std. Dev | Q3: # of datapoints | R3: N-average | S3: Std. Dev | W3: basis | X3: n | Y3: proxy group mean | Z3: SD (group or indiv food) | AA3: scaled SD (group SD*food mean/group mean) | AB3: basis | AC3: n | AD3: proxy group mean | AE3: SD (group or indiv food) | AF3: scaled SD (group SD*food mean/group mean)
A4: 101050000 | B4: Beet, garden, roots | C4: weight of roots; juice | E4: 659 | F4: =N4*H4+T4 -> 1.221 | G4: =R4*H4+U4 -> 0.19425 | H4: 1.11 | I4: AgHB | J4: 1 | L4: =IF(ISERROR(GETPIVOTDATA(IF($J4=1,"Count of ACTIVE CED, FARM GATE (MJ/kg)","Count of CED, processor gate (MJ/kg)"),'Pivot Table_CED'!$A$3,"SUB TYPE",$B4)),"PROXY",IF(GETPIVOTDATA(IF($J4=1,"Count of ACTIVE CED, FARM GATE (MJ/kg)","Count of CED, processor gate (MJ/kg)"),'Pivot Table_CED'!$A$3,"SUB TYPE",$B4)=0,"PROXY","DB value")) -> DB value | M4: =IF($L4="PROXY",DCOUNT('literature entries'!$D:$AI,IF($J4=1,"ACTIVE CED, FARM GATE (MJ/kg)","CED, processor gate (MJ/kg)"),INDIRECT($K4)),GETPIVOTDATA(IF($J4=1,"Count of ACTIVE CED, FARM GATE (MJ/kg)","Count of CED, processor gate (MJ/kg)"),'Pivot Table_CED'!$A$3,"SUB TYPE",$B4)) -> 1 | N4: =IF($L4="PROXY",DAVERAGE('literature entries'!$D:$AI,IF($J4=1,"ACTIVE CED, FARM GATE (MJ/kg)","CED, processor gate (MJ/kg)"),INDIRECT($K4)),GETPIVOTDATA(IF($J4=1,"Average of ACTIVE CED, FARM GATE (MJ/kg)","Average of CED, processor gate (MJ/kg)"),'Pivot Table_CED'!$A$3,"SUB TYPE",$B4)) -> 1.1 | O4: =IF($L4="PROXY",DSTDEV('literature entries'!D:AF,IF($J4=1,"ACTIVE CED, FARM GATE (MJ/kg)","CED, processor gate (MJ/kg)"),INDIRECT($K4)),GETPIVOTDATA(IF($J4=1,"StdDev of ACTIVE CED, FARM GATE (MJ/kg)","StdDev of CED, processor gate (MJ/kg)"),'Pivot Table_CED'!$A$3,"SUB TYPE",$B4)) -> 0 | P4: =IF(ISERROR(GETPIVOTDATA(IF($J4=1,"Count of ACTIVE GHGE, FARM GATE (kg CO2e/kg)","Count of GHGE, processor gate (kg CO2e/kg)"),'Pivot Table_GHG'!$A$3,"SUB TYPE",$B4)),"PROXY",IF(GETPIVOTDATA(IF($J4=1,"Count of ACTIVE GHGE, FARM GATE (kg CO2e/kg)","Count of GHGE, processor gate (kg CO2e/kg)"),'Pivot Table_GHG'!$A$3,"SUB TYPE",$B4)=0,"PROXY","DB value")) -> DB value | Q4: =IF($P4="PROXY",DCOUNT('literature entries'!$D:$AI,IF($J4=1,"ACTIVE GHGE, FARM GATE (kg CO2e/kg)","GHGE, processor gate (kg CO2e/kg)"),INDIRECT($K4)),GETPIVOTDATA(IF($J4=1,"ACTIVE GHGE, FARM GATE (kg CO2e/kg)","Count of GHGE, processor gate (kg CO2e/kg)"),'Pivot Table_GHG'!$A$3,"SUB TYPE",$B4)) -> 2 | R4: =IF($P4="PROXY",DAVERAGE('literature entries'!$D:$AI,IF($J4=1,"ACTIVE GHGE, FARM GATE (kg CO2e/kg)","GHGE, processor gate (kg CO2e/kg)"),INDIRECT($K4)),GETPIVOTDATA(IF($J4=1,"Average of ACTIVE GHGE, FARM GATE (kg CO2e/kg)","Average of GHGE, processor gate (kg CO2e/kg)"),'Pivot Table_GHG'!$A$3,"SUB TYPE",$B4)) -> 0.175 | S4: =IF($P4="PROXY",DSTDEV('literature entries'!$D:$AI,IF($J4=1,"ACTIVE GHGE, FARM GATE (kg CO2e/kg)","GHGE, processor gate (kg CO2e/kg)"),INDIRECT($K4)),GETPIVOTDATA(IF($J4=1,"StdDev of ACTIVE GHGE, FARM GATE (kg CO2e/kg)","StdDev of GHGE, processor gate (kg CO2e/kg)"),'Pivot Table_GHG'!$A$3,"SUB TYPE",$B4)) -> 0.091923882 | W4: roots | X4: =IF($W4="DIRECT",M4,DCOUNT('literature entries'!$D:$AI,IF($J4=1,"ACTIVE CED, FARM GATE (MJ/kg)","CED, processor gate (MJ/kg)"),INDIRECT($W4))) -> 14 | Y4: =IF($W4="DIRECT","",DAVERAGE('literature entries'!$D:$AI,IF($J4=1,"ACTIVE CED, FARM GATE (MJ/kg)","CED, processor gate (MJ/kg)"),INDIRECT($W4))) -> 1.4220714 | Z4: =IF($W4="DIRECT",$O4,DSTDEV('literature entries'!$D:$AI,IF($J4=1,"ACTIVE CED, FARM GATE (MJ/kg)","CED, processor gate (MJ/kg)"),INDIRECT($W4))) -> 0.57442044 | AA4: =IF($W4="DIRECT",$O4,$Z4/$Y4*$N4) -> 0.44432542 | AB4: roots | AC4: =IF($AB4="DIRECT",Q4,DCOUNT('literature entries'!$D:$AI,IF($J4=1,"ACTIVE GHGE, FARM GATE (kg CO2e/kg)","GHGE, processor gate (kg CO2e/kg)"),INDIRECT($AB4))) -> 25 | AD4: =IF($AB4="DIRECT","",DAVERAGE('literature entries'!$D:$AI,IF($J4=1,"ACTIVE GHGE, FARM GATE (kg CO2e/kg)","GHGE, processor gate (kg CO2e/kg)"),INDIRECT($AB4))) -> 0.2134 | AE4: =IF($AB4="DIRECT",$S4,DSTDEV('literature entries'!$D:$AI,IF($J4=1,"ACTIVE GHGE, FARM GATE (kg CO2e/kg)","GHGE, processor gate (kg CO2e/kg)"),INDIRECT($AB4))) -> 0.17992035 | AF4: =IF($AB4="DIRECT",$S4,$AE4/$AD4*$R4) -> 0.14754481
A5: 101052000 | B5: Beet, sugar | C5: dry weight of sugar (sucrose) | D5: Sucrose is a disaccharide obtained from sugar cane and sugar beet. | E5: 49979 | F5: =N5*H5+T5 -> 4.5742357 | G5: =R5*H5+U5 -> 0.39078306 | H5: 1 | I5: FICRCD | J5: 2 | L5: =IF(ISERROR(GETPIVOTDATA(IF($J5=1,"Count of ACTIVE CED, FARM GATE (MJ/kg)","Count of CED, processor gate (MJ/kg)"),'Pivot Table_CED'!$A$3,"SUB TYPE",$B5)),"PROXY",IF(GETPIVOTDATA(IF($J5=1,"Count of ACTIVE CED, FARM GATE (MJ/kg)","Count of CED, processor gate (MJ/kg)"),'Pivot Table_CED'!$A$3,"SUB TYPE",$B5)=0,"PROXY","DB value")) -> DB value | M5: =IF($L5="PROXY",DCOUNT('literature entries'!$D:$AI,IF($J5=1,"ACTIVE CED, FARM GATE (MJ/kg)","CED, processor gate (MJ/kg)"),INDIRECT($K5)),GETPIVOTDATA(IF($J5=1,"Count of ACTIVE CED, FARM GATE (MJ/kg)","Count of CED, processor gate (MJ/kg)"),'Pivot Table_CED'!$A$3,"SUB TYPE",$B5)) -> 4 | N5: =IF($L5="PROXY",DAVERAGE('literature entries'!$D:$AI,IF($J5=1,"ACTIVE CED, FARM GATE (MJ/kg)","CED, processor gate (MJ/kg)"),INDIRECT($K5)),GETPIVOTDATA(IF($J5=1,"Average of ACTIVE CED, FARM GATE (MJ/kg)","Average of CED, processor gate (MJ/kg)"),'Pivot Table_CED'!$A$3,"SUB TYPE",$B5)) -> 4.5742357 | O5: =IF($L5="PROXY",DSTDEV('literature entries'!D:AI,IF($J5=1,"ACTIVE CED, FARM GATE (MJ/kg)","CED, processor gate (MJ/kg)"),INDIRECT($K5)),GETPIVOTDATA(IF($J5=1,"StdDev of ACTIVE CED, FARM GATE (MJ/kg)","StdDev of CED, processor gate (MJ/kg)"),'Pivot Table_CED'!$A$3,"SUB TYPE",$B5)) -> 0.63688081 | P5: =IF(ISERROR(GETPIVOTDATA(IF($J5=1,"Count of ACTIVE GHGE, FARM GATE (kg CO2e/kg)","Count of GHGE, processor gate (kg CO2e/kg)"),'Pivot Table_GHG'!$A$3,"SUB TYPE",$B5)),"PROXY",IF(GETPIVOTDATA(IF($J5=1,"Count of ACTIVE GHGE, FARM GATE (kg CO2e/kg)","Count of GHGE, processor gate (kg CO2e/kg)"),'Pivot Table_GHG'!$A$3,"SUB TYPE",$B5)=0,"PROXY","DB value")) -> DB value | Q5: =IF($P5="PROXY",DCOUNT('literature entries'!$D:$AI,IF($J5=1,"ACTIVE GHGE, FARM GATE (kg CO2e/kg)","GHGE, processor gate (kg CO2e/kg)"),INDIRECT($K5)),GETPIVOTDATA(IF($J5=1,"ACTIVE GHGE, FARM GATE (kg CO2e/kg)","Count of GHGE, processor gate (kg CO2e/kg)"),'Pivot Table_GHG'!$A$3,"SUB TYPE",$B5)) -> 4 | R5: =IF($P5="PROXY",DAVERAGE('literature entries'!$D:$AI,IF($J5=1,"ACTIVE GHGE, FARM GATE (kg CO2e/kg)","GHGE, processor gate (kg CO2e/kg)"),INDIRECT($K5)),GETPIVOTDATA(IF($J5=1,"Average of ACTIVE GHGE, FARM GATE (kg CO2e/kg)","Average of GHGE, processor gate (kg CO2e/kg)"),'Pivot Table_GHG'!$A$3,"SUB TYPE",$B5)) -> 0.39078306 | S5: =IF($P5="PROXY",DSTDEV('literature entries'!$D:$AI,IF($J5=1,"ACTIVE GHGE, FARM GATE (kg CO2e/kg)","GHGE, processor gate (kg CO2e/kg)"),INDIRECT($K5)),GETPIVOTDATA(IF($J5=1,"StdDev of ACTIVE GHGE, FARM GATE (kg CO2e/kg)","StdDev of GHGE, processor gate (kg CO2e/kg)"),'Pivot Table_GHG'!$A$3,"SUB TYPE",$B5)) -> 0.076284475 | W5: sweeteners | X5: =IF($W5="DIRECT",M5,DCOUNT('literature entries'!$D:$AI,IF($J5=1,"ACTIVE CED, FARM GATE (MJ/kg)","CED, processor gate (MJ/kg)"),INDIRECT($W5))) -> 14 | Y5: =IF($W5="DIRECT","",DAVERAGE('literature entries'!$D:$AI,IF($J5=1,"ACTIVE CED, FARM GATE (MJ/kg)","CED, processor gate (MJ/kg)"),INDIRECT($W5))) -> 8.8453456 | Z5: =IF($W5="DIRECT",$O5,DSTDEV('literature entries'!$D:$AI,IF($J5=1,"ACTIVE CED, FARM GATE (MJ/kg)","CED, processor gate (MJ/kg)"),INDIRECT($W5))) -> 17.468328 | AA5: =IF($W5="DIRECT",$O5,$Z5/$Y5*$N5) -> 9.0334799 | AB5: sweeteners | AC5: =IF($AB5="DIRECT",Q5,DCOUNT('literature entries'!$D:$AI,IF($J5=1,"ACTIVE GHGE, FARM GATE (kg CO2e/kg)","GHGE, processor gate (kg CO2e/kg)"),INDIRECT($AB5))) -> 13 | AD5: =IF($AB5="DIRECT","",DAVERAGE('literature entries'!$D:$AI,IF($J5=1,"ACTIVE GHGE, FARM GATE (kg CO2e/kg)","GHGE, processor gate (kg CO2e/kg)"),INDIRECT($AB5))) -> 1.0611859 | AE5: =IF($AB5="DIRECT",$S5,DSTDEV('literature entries'!$D:$AI,IF($J5=1,"ACTIVE GHGE, FARM GATE (kg CO2e/kg)","GHGE, processor gate (kg CO2e/kg)"),INDIRECT($AB5))) -> 1.8055997 | AF5: =IF($AB5="DIRECT",$S5,$AE5/$AD5*$R5) -> 0.66491438
A6: 101053000 | B6: Beet, sugar, molasses | C6: weight of molasses | E6: 7656 | F6: =N6*H6+T6 -> 3.47585 | G6: =R6*H6+U6 -> 0.2875925 | H6: 1 | I6: FICRCD | J6: 2 | L6: =IF(ISERROR(GETPIVOTDATA(IF($J6=1,"Count of ACTIVE CED, FARM GATE (MJ/kg)","Count of CED, processor gate (MJ/kg)"),'Pivot Table_CED'!$A$3,"SUB TYPE",$B6)),"PROXY",IF(GETPIVOTDATA(IF($J6=1,"Count of ACTIVE CED, FARM GATE (MJ/kg)","Count of CED, processor gate (MJ/kg)"),'Pivot Table_CED'!$A$3,"SUB TYPE",$B6)=0,"PROXY","DB value")) -> DB value | M6: =IF($L6="PROXY",DCOUNT('literature entries'!$D:$AI,IF($J6=1,"ACTIVE CED, FARM GATE (MJ/kg)","CED, processor gate (MJ/kg)"),INDIRECT($K6)),GETPIVOTDATA(IF($J6=1,"Count of ACTIVE CED, FARM GATE (MJ/kg)","Count of CED, processor gate (MJ/kg)"),'Pivot Table_CED'!$A$3,"SUB TYPE",$B6)) -> 4 | N6: =IF($L6="PROXY",DAVERAGE('literature entries'!$D:$AI,IF($J6=1,"ACTIVE CED, FARM GATE (MJ/kg)","CED, processor gate (MJ/kg)"),INDIRECT($K6)),GETPIVOTDATA(IF($J6=1,"Average of ACTIVE CED, FARM GATE (MJ/kg)","Average of CED, processor gate (MJ/kg)"),'Pivot Table_CED'!$A$3,"SUB TYPE",$B6)) -> 3.47585 | O6: =IF($L6="PROXY",DSTDEV('literature entries'!D:AI,IF($J6=1,"ACTIVE CED, FARM GATE (MJ/kg)","CED, processor gate (MJ/kg)"),INDIRECT($K6)),GETPIVOTDATA(IF($J6=1,"StdDev of ACTIVE CED, FARM GATE (MJ/kg)","StdDev of CED, processor gate (MJ/kg)"),'Pivot Table_CED'!$A$3,"SUB TYPE",$B6)) -> 0.3775474 | P6: =IF(ISERROR(GETPIVOTDATA(IF($J6=1,"Count of ACTIVE GHGE, FARM GATE (kg CO2e/kg)","Count of GHGE, processor gate (kg CO2e/kg)"),'Pivot Table_GHG'!$A$3,"SUB TYPE",$B6)),"PROXY",IF(GETPIVOTDATA(IF($J6=1,"Count of ACTIVE GHGE, FARM GATE (kg CO2e/kg)","Count of GHGE, processor gate (kg CO2e/kg)"),'Pivot Table_GHG'!$A$3,"SUB TYPE",$B6)=0,"PROXY","DB value")) -> DB value | Q6: =IF($P6="PROXY",DCOUNT('literature entries'!$D:$AI,IF($J6=1,"ACTIVE GHGE, FARM GATE (kg CO2e/kg)","GHGE, processor gate (kg CO2e/kg)"),INDIRECT($K6)),GETPIVOTDATA(IF($J6=1,"ACTIVE GHGE, FARM GATE (kg CO2e/kg)","Count of GHGE, processor gate (kg CO2e/kg)"),'Pivot Table_GHG'!$A$3,"SUB TYPE",$B6)) -> 4 | R6: =IF($P6="PROXY",DAVERAGE('literature entries'!$D:$AI,IF($J6=1,"ACTIVE GHGE, FARM GATE (kg CO2e/kg)","GHGE, processor gate (kg CO2e/kg)"),INDIRECT($K6)),GETPIVOTDATA(IF($J6=1,"Average of ACTIVE GHGE, FARM GATE (kg CO2e/kg)","Average of GHGE, processor gate (kg CO2e/kg)"),'Pivot Table_GHG'!$A$3,"SUB TYPE",$B6)) -> 0.2875925 | S6: =IF($P6="PROXY",DSTDEV('literature entries'!$D:$AI,IF($J6=1,"ACTIVE GHGE, FARM GATE (kg CO2e/kg)","GHGE, processor gate (kg CO2e/kg)"),INDIRECT($K6)),GETPIVOTDATA(IF($J6=1,"StdDev of ACTIVE GHGE, FARM GATE (kg CO2e/kg)","StdDev of GHGE, processor gate (kg CO2e/kg)"),'Pivot Table_GHG'!$A$3,"SUB TYPE",$B6)) -> 0.047032512 | W6: sweeteners | X6: =IF($W6="DIRECT",M6,DCOUNT('literature entries'!$D:$AI,IF($J6=1,"ACTIVE CED, FARM GATE (MJ/kg)","CED, processor gate (MJ/kg)"),INDIRECT($W6))) -> 14 | Y6: =IF($W6="DIRECT","",DAVERAGE('literature entries'!$D:$AI,IF($J6=1,"ACTIVE CED, FARM GATE (MJ/kg)","CED, processor gate (MJ/kg)"),INDIRECT($W6))) -> 8.8453456 | Z6: =IF($W6="DIRECT",$O6,DSTDEV('literature entries'!$D:$AI,IF($J6=1,"ACTIVE CED, FARM GATE (MJ/kg)","CED, processor gate (MJ/kg)"),INDIRECT($W6))) -> 17.468328 | AA6: =IF($W6="DIRECT",$O6,$Z6/$Y6*$N6) -> 6.8643208 | AB6: sweeteners | AC6: =IF($AB6="DIRECT",Q6,DCOUNT('literature entries'!$D:$AI,IF($J6=1,"ACTIVE GHGE, FARM GATE (kg CO2e/kg)","GHGE, processor gate (kg CO2e/kg)"),INDIRECT($AB6))) -> 13 | AD6: =IF($AB6="DIRECT","",DAVERAGE('literature entries'!$D:$AI,IF($J6=1,"ACTIVE GHGE, FARM GATE (kg CO2e/kg)","GHGE, processor gate (kg CO2e/kg)"),INDIRECT($AB6))) -> 1.0611859 | AE6: =IF($AB6="DIRECT",$S6,DSTDEV('literature entries'!$D:$AI,IF($J6=1,"ACTIVE GHGE, FARM GATE (kg CO2e/kg)","GHGE, processor gate (kg CO2e/kg)"),INDIRECT($AB6))) -> 1.8055997 | AF6: =IF($AB6="DIRECT",$S6,$AE6/$AD6*$R6) -> 0.48933644
A7: 101067000 | B7: Burdock | C7: weight of roots | E7: 2 | F7: =N7*H7+T7 -> 1.891355 | G7: =R7*H7+U7 -> 0.283822 | H7: 1.33 | I7: NNDSR28 | J7: 1 | K7: roots | L7: =IF(ISERROR(GETPIVOTDATA(IF($J7=1,"Count of ACTIVE CED, FARM GATE (MJ/kg)","Count of CED, processor gate (MJ/kg)"),'Pivot Table_CED'!$A$3,"SUB TYPE",$B7)),"PROXY",IF(GETPIVOTDATA(IF($J7=1,"Count of ACTIVE CED, FARM GATE (MJ/kg)","Count of CED, processor gate (MJ/kg)"),'Pivot Table_CED'!$A$3,"SUB TYPE",$B7)=0,"PROXY","DB value")) -> PROXY | M7: =IF($L7="PROXY",DCOUNT('literature entries'!$D:$AI,IF($J7=1,"ACTIVE CED, FARM GATE (MJ/kg)","CED, processor gate (MJ/kg)"),INDIRECT($K7)),GETPIVOTDATA(IF($J7=1,"Count of ACTIVE CED, FARM GATE (MJ/kg)","Count of CED, processor gate (MJ/kg)"),'Pivot Table_CED'!$A$3,"SUB TYPE",$B7)) -> 14 | N7: =IF($L7="PROXY",DAVERAGE('literature entries'!$D:$AI,IF($J7=1,"ACTIVE CED, FARM GATE (MJ/kg)","CED, processor gate (MJ/kg)"),INDIRECT($K7)),GETPIVOTDATA(IF($J7=1,"Average of ACTIVE CED, FARM GATE (MJ/kg)","Average of CED, processor gate (MJ/kg)"),'Pivot Table_CED'!$A$3,"SUB TYPE",$B7)) -> 1.4220714 | O7: =IF($L7="PROXY",DSTDEV('literature entries'!D:AI,IF($J7=1,"ACTIVE CED, FARM GATE (MJ/kg)","CED, processor gate (MJ/kg)"),INDIRECT($K7)),GETPIVOTDATA(IF($J7=1,"StdDev of ACTIVE CED, FARM GATE (MJ/kg)","StdDev of CED, processor gate (MJ/kg)"),'Pivot Table_CED'!$A$3,"SUB TYPE",$B7)) -> 0.57442044 | P7: =IF(ISERROR(GETPIVOTDATA(IF($J7=1,"Count of ACTIVE GHGE, FARM GATE (kg CO2e/kg)","Count of GHGE, processor gate (kg CO2e/kg)"),'Pivot Table_GHG'!$A$3,"SUB TYPE",$B7)),"PROXY",IF(GETPIVOTDATA(IF($J7=1,"Count of ACTIVE GHGE, FARM GATE (kg CO2e/kg)","Count of GHGE, processor gate (kg CO2e/kg)"),'Pivot Table_GHG'!$A$3,"SUB TYPE",$B7)=0,"PROXY","DB value")) -> PROXY | Q7: =IF($P7="PROXY",DCOUNT('literature entries'!$D:$AI,IF($J7=1,"ACTIVE GHGE, FARM GATE (kg CO2e/kg)","GHGE, processor gate (kg CO2e/kg)"),INDIRECT($K7)),GETPIVOTDATA(IF($J7=1,"ACTIVE GHGE, FARM GATE (kg CO2e/kg)","Count of GHGE, processor gate (kg CO2e/kg)"),'Pivot Table_GHG'!$A$3,"SUB TYPE",$B7)) -> 25 | R7: =IF($P7="PROXY",DAVERAGE('literature entries'!$D:$AI,IF($J7=1,"ACTIVE GHGE, FARM GATE (kg CO2e/kg)","GHGE, processor gate (kg CO2e/kg)"),INDIRECT($K7)),GETPIVOTDATA(IF($J7=1,"Average of ACTIVE GHGE, FARM GATE (kg CO2e/kg)","Average of GHGE, processor gate (kg CO2e/kg)"),'Pivot Table_GHG'!$A$3,"SUB TYPE",$B7)) -> 0.2134 | S7: =IF($P7="PROXY",DSTDEV('literature entries'!$D:$AI,IF($J7=1,"ACTIVE GHGE, FARM GATE (kg CO2e/kg)","GHGE, processor gate (kg CO2e/kg)"),INDIRECT($K7)),GETPIVOTDATA(IF($J7=1,"StdDev of ACTIVE GHGE, FARM GATE (kg CO2e/kg)","StdDev of GHGE, processor gate (kg CO2e/kg)"),'Pivot Table_GHG'!$A$3,"SUB TYPE",$B7)) -> 0.17992035 | W7: =IF(L7="PROXY",IF(M7>=5,K7,"need group"),IF(M7>=5,"DIRECT","need group")) -> roots | X7: =IF($W7="DIRECT",M7,DCOUNT('literature entries'!$D:$AI,IF($J7=1,"ACTIVE CED, FARM GATE (MJ/kg)","CED, processor gate (MJ/kg)"),INDIRECT($W7))) -> 14 | Y7: =IF($W7="DIRECT","",DAVERAGE('literature entries'!$D:$AI,IF($J7=1,"ACTIVE CED, FARM GATE (MJ/kg)","CED, processor gate (MJ/kg)"),INDIRECT($W7))) -> 1.4220714 | Z7: =IF($W7="DIRECT",$O7,DSTDEV('literature entries'!$D:$AI,IF($J7=1,"ACTIVE CED, FARM GATE (MJ/kg)","CED, processor gate (MJ/kg)"),INDIRECT($W7))) -> 0.57442044 | AA7: =IF($W7="DIRECT",$O7,$Z7/$Y7*$N7) -> 0.57442044 | AB7: =IF(P7="PROXY",IF(Q7>=5,K7,"need group"),IF(Q7>=5,"DIRECT","need group")) -> roots | AC7: =IF($AB7="DIRECT",Q7,DCOUNT('literature entries'!$D:$AI,IF($J7=1,"ACTIVE GHGE, FARM GATE (kg CO2e/kg)","GHGE, processor gate (kg CO2e/kg)"),INDIRECT($AB7))) -> 25 | AD7: =IF($AB7="DIRECT","",DAVERAGE('literature entries'!$D:$AI,IF($J7=1,"ACTIVE GHGE, FARM GATE (kg CO2e/kg)","GHGE, processor gate (kg CO2e/kg)"),INDIRECT($AB7))) -> 0.2134 | AE7: =IF($AB7="DIRECT",$S7,DSTDEV('literature entries'!$D:$AI,IF($J7=1,"ACTIVE GHGE, FARM GATE (kg CO2e/kg)","GHGE, processor gate (kg CO2e/kg)"),INDIRECT($AB7))) -> 0.17992035 | AF7: =IF($AB7="DIRECT",$S7,$AE7/$AD7*$R7) -> 0.17992035
A8: 101078000 | B8: Carrot | C8: weight of roots, with or without peel, excluding tops | E8: 14222 | F8: =N8*H8+T8 -> 1.325856 | G8: =R8*H8+U8 -> 0.091616 | H8: 1.12 | I8: FICRCD | J8: 1 | L8: =IF(ISERROR(GETPIVOTDATA(IF($J8=1,"Count of ACTIVE CED, FARM GATE (MJ/kg)","Count of CED, processor gate (MJ/kg)"),'Pivot Table_CED'!$A$3,"SUB TYPE",$B8)),"PROXY",IF(GETPIVOTDATA(IF($J8=1,"Count of ACTIVE CED, FARM GATE (MJ/kg)","Count of CED, processor gate (MJ/kg)"),'Pivot Table_CED'!$A$3,"SUB TYPE",$B8)=0,"PROXY","DB value")) -> DB value | M8: =IF($L8="PROXY",DCOUNT('literature entries'!$D:$AI,IF($J8=1,"ACTIVE CED, FARM GATE (MJ/kg)","CED, processor gate (MJ/kg)"),INDIRECT($K8)),GETPIVOTDATA(IF($J8=1,"Count of ACTIVE CED, FARM GATE (MJ/kg)","Count of CED, processor gate (MJ/kg)"),'Pivot Table_CED'!$A$3,"SUB TYPE",$B8)) -> 5 | N8: =IF($L8="PROXY",DAVERAGE('literature entries'!$D:$AI,IF($J8=1,"ACTIVE CED, FARM GATE (MJ/kg)","CED, processor gate (MJ/kg)"),INDIRECT($K8)),GETPIVOTDATA(IF($J8=1,"Average of ACTIVE CED, FARM GATE (MJ/kg)","Average of CED, processor gate (MJ/kg)"),'Pivot Table_CED'!$A$3,"SUB TYPE",$B8)) -> 1.1838 | O8: =IF($L8="PROXY",DSTDEV('literature entries'!D:AI,IF($J8=1,"ACTIVE CED, FARM GATE (MJ/kg)","CED, processor gate (MJ/kg)"),INDIRECT($K8)),GETPIVOTDATA(IF($J8=1,"StdDev of ACTIVE CED, FARM GATE (MJ/kg)","StdDev of CED, processor gate (MJ/kg)"),'Pivot Table_CED'!$A$3,"SUB TYPE",$B8)) -> 0.63805815 | P8: =IF(ISERROR(GETPIVOTDATA(IF($J8=1,"Count of ACTIVE GHGE, FARM GATE (kg CO2e/kg)","Count of GHGE, processor gate (kg CO2e/kg)"),'Pivot Table_GHG'!$A$3,"SUB TYPE",$B8)),"PROXY",IF(GETPIVOTDATA(IF($J8=1,"Count of ACTIVE GHGE, FARM GATE (kg CO2e/kg)","Count of GHGE, processor gate (kg CO2e/kg)"),'Pivot Table_GHG'!$A$3,"SUB TYPE",$B8)=0,"PROXY","DB value")) -> DB value | Q8: =IF($P8="PROXY",DCOUNT('literature entries'!$D:$AI,IF($J8=1,"ACTIVE GHGE, FARM GATE (kg CO2e/kg)","GHGE, processor gate (kg CO2e/kg)"),INDIRECT($K8)),GETPIVOTDATA(IF($J8=1,"ACTIVE GHGE, FARM GATE (kg CO2e/kg)","Count of GHGE, processor gate (kg CO2e/kg)"),'Pivot Table_GHG'!$A$3,"SUB TYPE",$B8)) -> 5 | R8: =IF($P8="PROXY",DAVERAGE('literature entries'!$D:$AI,IF($J8=1,"ACTIVE GHGE, FARM GATE (kg CO2e/kg)","GHGE, processor gate (kg CO2e/kg)"),INDIRECT($K8)),GETPIVOTDATA(IF($J8=1,"Average of ACTIVE GHGE, FARM GATE (kg CO2e/kg)","Average of GHGE, processor gate (kg CO2e/kg)"),'Pivot Table_GHG'!$A$3,"SUB TYPE",$B8)) -> 0.0818 | S8: =IF($P8="PROXY",DSTDEV('literature entries'!$D:$AI,IF($J8=1,"ACTIVE GHGE, FARM GATE (kg CO2e/kg)","GHGE, processor gate (kg CO2e/kg)"),INDIRECT($K8)),GETPIVOTDATA(IF($J8=1,"StdDev of ACTIVE GHGE, FARM GATE (kg CO2e/kg)","StdDev of GHGE, processor gate (kg CO2e/kg)"),'Pivot Table_GHG'!$A$3,"SUB TYPE",$B8)) -> 0.051982689 | W8: =IF(L8="PROXY",IF(M8>=5,K8,"need group"),IF(M8>=5,"DIRECT","need group")) -> DIRECT | X8: =IF($W8="DIRECT",M8,DCOUNT('literature entries'!$D:$AI,IF($J8=1,"ACTIVE CED, FARM GATE (MJ/kg)","CED, processor gate (MJ/kg)"),INDIRECT($W8))) -> 5 | Y8: =IF($W8="DIRECT","",DAVERAGE('literature entries'!$D:$AI,IF($J8=1,"ACTIVE CED, FARM GATE (MJ/kg)","CED, processor gate (MJ/kg)"),INDIRECT($W8))) | Z8: =IF($W8="DIRECT",$O8,DSTDEV('literature entries'!$D:$AI,IF($J8=1,"ACTIVE CED, FARM GATE (MJ/kg)","CED, processor gate (MJ/kg)"),INDIRECT($W8))) -> 0.63805815 | AA8: =IF($W8="DIRECT",$O8,$Z8/$Y8*$N8) -> 0.63805815 | AB8: =IF(P8="PROXY",IF(Q8>=5,K8,"need group"),IF(Q8>=5,"DIRECT","need group")) -> DIRECT | AC8: =IF($AB8="DIRECT",Q8,DCOUNT('literature entries'!$D:$AI,IF($J8=1,"ACTIVE GHGE, FARM GATE (kg CO2e/kg)","GHGE, processor gate (kg CO2e/kg)"),INDIRECT($AB8))) -> 5 | AD8: =IF($AB8="DIRECT","",DAVERAGE('literature entries'!$D:$AI,IF($J8=1,"ACTIVE GHGE, FARM GATE (kg CO2e/kg)","GHGE, processor gate (kg CO2e/kg)"),INDIRECT($AB8))) | AE8: =IF($AB8="DIRECT",$S8,DSTDEV('literature entries'!$D:$AI,IF($J8=1,"ACTIVE GHGE, FARM GATE (kg CO2e/kg)","GHGE, processor gate (kg CO2e/kg)"),INDIRECT($AB8))) -> 0.051982689 | AF8: =IF($AB8="DIRECT",$S8,$AE8/$AD8*$R8) -> 0.051982689
A9: 101079000 | B9: Carrot, juice | C9: weight of juice at single strength (or standard dilution) | E9: 630 | F9: =N9*H9+T9 -> 6.607856 | G9: =R9*H9+U9 -> 1.0706951 | H9: 1.12 | I9: FICRCD | J9: 1 | K9: carrot | L9: =IF(ISERROR(GETPIVOTDATA(IF($J9=1,"Count of ACTIVE CED, FARM GATE (MJ/kg)","Count of CED, processor gate (MJ/kg)"),'Pivot Table_CED'!$A$3,"SUB TYPE",$B9)),"PROXY",IF(GETPIVOTDATA(IF($J9=1,"Count of ACTIVE CED, FARM GATE (MJ/kg)","Count of CED, processor gate (MJ/kg)"),'Pivot Table_CED'!$A$3,"SUB TYPE",$B9)=0,"PROXY","DB value")) -> PROXY | M9: =IF($L9="PROXY",DCOUNT('literature entries'!$D:$AI,IF($J9=1,"ACTIVE CED, FARM GATE (MJ/kg)","CED, processor gate (MJ/kg)"),INDIRECT($K9)),GETPIVOTDATA(IF($J9=1,"Count of ACTIVE CED, FARM GATE (MJ/kg)","Count of CED, processor gate (MJ/kg)"),'Pivot Table_CED'!$A$3,"SUB TYPE",$B9)) -> 5 | N9: =IF($L9="PROXY",DAVERAGE('literature entries'!$D:$AI,IF($J9=1,"ACTIVE CED, FARM GATE (MJ/kg)","CED, processor gate (MJ/kg)"),INDIRECT($K9)),GETPIVOTDATA(IF($J9=1,"Average of ACTIVE CED, FARM GATE (MJ/kg)","Average of CED, processor gate (MJ/kg)"),'Pivot Table_CED'!$A$3,"SUB TYPE",$B9)) -> 1.1838 | O9: =IF($L9="PROXY",DSTDEV('literature entries'!D:AI,IF($J9=1,"ACTIVE CED, FARM GATE (MJ/kg)","CED, processor gate (MJ/kg)"),INDIRECT($K9)),GETPIVOTDATA(IF($J9=1,"StdDev of ACTIVE CED, FARM GATE (MJ/kg)","StdDev of CED, processor gate (MJ/kg)"),'Pivot Table_CED'!$A$3,"SUB TYPE",$B9)) -> 0.63805815 | P9: =IF(ISERROR(GETPIVOTDATA(IF($J9=1,"Count of ACTIVE GHGE, FARM GATE (kg CO2e/kg)","Count of GHGE, processor gate (kg CO2e/kg)"),'Pivot Table_GHG'!$A$3,"SUB TYPE",$B9)),"PROXY",IF(GETPIVOTDATA(IF($J9=1,"Count of ACTIVE GHGE, FARM GATE (kg CO2e/kg)","Count of GHGE, processor gate (kg CO2e/kg)"),'Pivot Table_GHG'!$A$3,"SUB TYPE",$B9)=0,"PROXY","DB value")) -> PROXY | Q9: =IF($P9="PROXY",DCOUNT('literature entries'!$D:$AI,IF($J9=1,"ACTIVE GHGE, FARM GATE (kg CO2e/kg)","GHGE, processor gate (kg CO2e/kg)"),INDIRECT($K9)),GETPIVOTDATA(IF($J9=1,"ACTIVE GHGE, FARM GATE (kg CO2e/kg)","Count of GHGE, processor gate (kg CO2e/kg)"),'Pivot Table_GHG'!$A$3,"SUB TYPE",$B9)) -> 5 | R9: =IF($P9="PROXY",DAVERAGE('literature entries'!$D:$AI,IF($J9=1,"ACTIVE GHGE, FARM GATE (kg CO2e/kg)","GHGE, processor gate (kg CO2e/kg)"),INDIRECT($K9)),GETPIVOTDATA(IF($J9=1,"Average of ACTIVE GHGE, FARM GATE (kg CO2e/kg)","Average of GHGE, processor gate (kg CO2e/kg)"),'Pivot Table_GHG'!$A$3,"SUB TYPE",$B9)) -> 0.0818 | S9: =IF($P9="PROXY",DSTDEV('literature entries'!$D:$AI,IF($J9=1,"ACTIVE GHGE, FARM GATE (kg CO2e/kg)","GHGE, processor gate (kg CO2e/kg)"),INDIRECT($K9)),GETPIVOTDATA(IF($J9=1,"StdDev of ACTIVE GHGE, FARM GATE (kg CO2e/kg)","StdDev of GHGE, processor gate (kg CO2e/kg)"),'Pivot Table_GHG'!$A$3,"SUB TYPE",$B9)) -> 0.051982689 | T9: 5.282 | U9: 0.97907913 | W9: roots | X9: =IF($W9="DIRECT",M9,DCOUNT('literature entries'!$D:$AI,IF($J9=1,"ACTIVE CED, FARM GATE (MJ/kg)","CED, processor gate (MJ/kg)"),INDIRECT($W9))) -> 14 | Y9: =IF($W9="DIRECT","",DAVERAGE('literature entries'!$D:$AI,IF($J9=1,"ACTIVE CED, FARM GATE (MJ/kg)","CED, processor gate (MJ/kg)"),INDIRECT($W9))) -> 1.4220714 | Z9: =IF($W9="DIRECT",$O9,DSTDEV('literature entries'!$D:$AI,IF($J9=1,"ACTIVE CED, FARM GATE (MJ/kg)","CED, processor gate (MJ/kg)"),INDIRECT($W9))) -> 0.57442044 | AA9: =IF($W9="DIRECT",$O9,$Z9/$Y9*$N9) -> 0.47817494 | AB9: roots | AC9: =IF($AB9="DIRECT",Q9,DCOUNT('literature entries'!$D:$AI,IF($J9=1,"ACTIVE GHGE, FARM GATE (kg CO2e/kg)","GHGE, processor gate (kg CO2e/kg)"),INDIRECT($AB9))) -> 25 | AD9: =IF($AB9="DIRECT","",DAVERAGE('literature entries'!$D:$AI,IF($J9=1,"ACTIVE GHGE, FARM GATE (kg CO2e/kg)","GHGE, processor gate (kg CO2e/kg)"),INDIRECT($AB9))) -> 0.2134 | AE9: =IF($AB9="DIRECT",$S9,DSTDEV('literature entries'!$D:$AI,IF($J9=1,"ACTIVE GHGE, FARM GATE (kg CO2e/kg)","GHGE, processor gate (kg CO2e/kg)"),INDIRECT($AB9))) -> 0.17992035 | AF9: =IF($AB9="DIRECT",$S9,$AE9/$AD9*$R9) -> 0.068966658
A10: 101100000 | B10: Chicory, roots | C10: weight of roots | E10: 75 | F10: =N10*H10+T10 -> 0.1544 | G10: =R10*H10+U10 -> 0.050446 | H10: 1 | I10: None | J10: 1 | L10: =IF(ISERROR(GETPIVOTDATA(IF($J10=1,"Count of ACTIVE CED, FARM GATE (MJ/kg)","Count of CED, processor gate (MJ/kg)"),'Pivot Table_CED'!$A$3,"SUB TYPE",$B10)),"PROXY",IF(GETPIVOTDATA(IF($J10=1,"Count of ACTIVE CED, FARM GATE (MJ/kg)","Count of CED, processor gate (MJ/kg)"),'Pivot Table_CED'!$A$3,"SUB TYPE",$B10)=0,"PROXY","DB value")) -> DB value | M10: =IF($L10="PROXY",DCOUNT('literature entries'!$D:$AI,IF($J10=1,"ACTIVE CED, FARM GATE (MJ/kg)","CED, processor gate (MJ/kg)"),INDIRECT($K10)),GETPIVOTDATA(IF($J10=1,"Count of ACTIVE CED, FARM GATE (MJ/kg)","Count of CED, processor gate (MJ/kg)"),'Pivot Table_CED'!$A$3,"SUB TYPE",$B10)) -> 2 | N10: =IF($L10="PROXY",DAVERAGE('literature entries'!$D:$AI,IF($J10=1,"ACTIVE CED, FARM GATE (MJ/kg)","CED, processor gate (MJ/kg)"),INDIRECT($K10)),GETPIVOTDATA(IF($J10=1,"Average of ACTIVE CED, FARM GATE (MJ/kg)","Average of CED, processor gate (MJ/kg)"),'Pivot Table_CED'!$A$3,"SUB TYPE",$B10)) -> 0.1544 | O10: =IF($L10="PROXY",DSTDEV('literature entries'!D:AI,IF($J10=1,"ACTIVE CED, FARM GATE (MJ/kg)","CED, processor gate (MJ/kg)"),INDIRECT($K10)),GETPIVOTDATA(IF($J10=1,"StdDev of ACTIVE CED, FARM GATE (MJ/kg)","StdDev of CED, processor gate (MJ/kg)"),'Pivot Table_CED'!$A$3,"SUB TYPE",$B10)) -> 0.01357645 | P10: =IF(ISERROR(GETPIVOTDATA(IF($J10=1,"Count of ACTIVE GHGE, FARM GATE (kg CO2e/kg)","Count of GHGE, processor gate (kg CO2e/kg)"),'Pivot Table_GHG'!$A$3,"SUB TYPE",$B10)),"PROXY",IF(GETPIVOTDATA(IF($J10=1,"Count of ACTIVE GHGE, FARM GATE (kg CO2e/kg)","Count of GHGE, processor gate (kg CO2e/kg)"),'Pivot Table_GHG'!$A$3,"SUB TYPE",$B10)=0,"PROXY","DB value")) -> DB value | Q10: =IF($P10="PROXY",DCOUNT('literature entries'!$D:$AI,IF($J10=1,"ACTIVE GHGE, FARM GATE (kg CO2e/kg)","GHGE, processor gate (kg CO2e/kg)"),INDIRECT($K10)),GETPIVOTDATA(IF($J10=1,"ACTIVE GHGE, FARM GATE (kg CO2e/kg)","Count of GHGE, processor gate (kg CO2e/kg)"),'Pivot Table_GHG'!$A$3,"SUB TYPE",$B10)) -> 2 | R10: =IF($P10="PROXY",DAVERAGE('literature entries'!$D:$AI,IF($J10=1,"ACTIVE GHGE, FARM GATE (kg CO2e/kg)","GHGE, processor gate (kg CO2e/kg)"),INDIRECT($K10)),GETPIVOTDATA(IF($J10=1,"Average of ACTIVE GHGE, FARM GATE (kg CO2e/kg)","Average of GHGE, processor gate (kg CO2e/kg)"),'Pivot Table_GHG'!$A$3,"SUB TYPE",$B10)) -> 0.050446 | S10: =IF($P10="PROXY",DSTDEV('literature entries'!$D:$AI,IF($J10=1,"ACTIVE GHGE, FARM GATE (kg CO2e/kg)","GHGE, processor gate (kg CO2e/kg)"),INDIRECT($K10)),GETPIVOTDATA(IF($J10=1,"StdDev of ACTIVE GHGE, FARM GATE (kg CO2e/kg)","StdDev of GHGE, processor gate (kg CO2e/kg)"),'Pivot Table_GHG'!$A$3,"SUB TYPE",$B10)) -> 0.0090240967 | W10: roots | X10: =IF($W10="DIRECT",M10,DCOUNT('literature entries'!$D:$AI,IF($J10=1,"ACTIVE CED, FARM GATE (MJ/kg)","CED, processor gate (MJ/kg)"),INDIRECT($W10))) -> 14 | Y10: =IF($W10="DIRECT","",DAVERAGE('literature entries'!$D:$AI,IF($J10=1,"ACTIVE CED, FARM GATE (MJ/kg)","CED, processor gate (MJ/kg)"),INDIRECT($W10))) -> 1.4220714 | Z10: =IF($W10="DIRECT",$O10,DSTDEV('literature entries'!$D:$AI,IF($J10=1,"ACTIVE CED, FARM GATE (MJ/kg)","CED, processor gate (MJ/kg)"),INDIRECT($W10))) -> 0.57442044 | AA10: =IF($W10="DIRECT",$O10,$Z10/$Y10*$N10) -> 0.062367131 | AB10: roots | AC10: =IF($AB10="DIRECT",Q10,DCOUNT('literature entries'!$D:$AI,IF($J10=1,"ACTIVE GHGE, FARM GATE (kg CO2e/kg)","GHGE, processor gate (kg CO2e/kg)"),INDIRECT($AB10))) -> 25 | AD10: =IF($AB10="DIRECT","",DAVERAGE('literature entries'!$D:$AI,IF($J10=1,"ACTIVE GHGE, FARM GATE (kg CO2e/kg)","GHGE, processor gate (kg CO2e/kg)"),INDIRECT($AB10))) -> 0.2134 | AE10: =IF($AB10="DIRECT",$S10,DSTDEV('literature entries'!$D:$AI,IF($J10=1,"ACTIVE GHGE, FARM GATE (kg CO2e/kg)","GHGE, processor gate (kg CO2e/kg)"),INDIRECT($AB10))) -> 0.17992035 | AF10: =IF($AB10="DIRECT",$S10,$AE10/$AD10*$R10) -> 0.042531688
A11: 101168000 | B11: Ginseng, dried | C11: dry weight of roots | E11: 1 | F11: =N11*H11+T11 -> 0 | G11: =R11*H11+U11 -> 0.87 | H11: 1 | I11: None | J11: 1 | K11: spices | L11: =IF(ISERROR(GETPIVOTDATA(IF($J11=1,"Count of ACTIVE CED, FARM GATE (MJ/kg)","Count of CED, processor gate (MJ/kg)"),'Pivot Table_CED'!$A$3,"SUB TYPE",$B11)),"PROXY",IF(GETPIVOTDATA(IF($J11=1,"Count of ACTIVE CED, FARM GATE (MJ/kg)","Count of CED, processor gate (MJ/kg)"),'Pivot Table_CED'!$A$3,"SUB TYPE",$B11)=0,"PROXY","DB value")) -> PROXY | M11: =IF($L11="PROXY",DCOUNT('literature entries'!$D:$AI,IF($J11=1,"ACTIVE CED, FARM GATE (MJ/kg)","CED, processor gate (MJ/kg)"),INDIRECT($K11)),GETPIVOTDATA(IF($J11=1,"Count of ACTIVE CED, FARM GATE (MJ/kg)","Count of CED, processor gate (MJ/kg)"),'Pivot Table_CED'!$A$3,"SUB TYPE",$B11)) -> 1 | N11: =IF($L11="PROXY",DAVERAGE('literature entries'!$D:$AI,IF($J11=1,"ACTIVE CED, FARM GATE (MJ/kg)","CED, processor gate (MJ/kg)"),INDIRECT($K11)),GETPIVOTDATA(IF($J11=1,"Average of ACTIVE CED, FARM GATE (MJ/kg)","Average of CED, processor gate (MJ/kg)"),'Pivot Table_CED'!$A$3,"SUB TYPE",$B11)) -> 0 | O11: =IF($L11="PROXY",DSTDEV('literature entries'!D:AI,IF($J11=1,"ACTIVE CED, FARM GATE (MJ/kg)","CED, processor gate (MJ/kg)"),INDIRECT($K11)),GETPIVOTDATA(IF($J11=1,"StdDev of ACTIVE CED, FARM GATE (MJ/kg)","StdDev of CED, processor gate (MJ/kg)"),'Pivot Table_CED'!$A$3,"SUB TYPE",$B11)) -> #DIV/0! | P11: =IF(ISERROR(GETPIVOTDATA(IF($J11=1,"Count of ACTIVE GHGE, FARM GATE (kg CO2e/kg)","Count of GHGE, processor gate (kg CO2e/kg)"),'Pivot Table_GHG'!$A$3,"SUB TYPE",$B11)),"PROXY",IF(GETPIVOTDATA(IF($J11=1,"Count of ACTIVE GHGE, FARM GATE (kg CO2e/kg)","Count of GHGE, processor gate (kg CO2e/kg)"),'Pivot Table_GHG'!$A$3,"SUB TYPE",$B11)=0,"PROXY","DB value")) -> PROXY | Q11: =IF($P11="PROXY",DCOUNT('literature entries'!$D:$AI,IF($J11=1,"ACTIVE GHGE, FARM GATE (kg CO2e/kg)","GHGE, processor gate (kg CO2e/kg)"),INDIRECT($K11)),GETPIVOTDATA(IF($J11=1,"ACTIVE GHGE, FARM GATE (kg CO2e/kg)","Count of GHGE, processor gate (kg CO2e/kg)"),'Pivot Table_GHG'!$A$3,"SUB TYPE",$B11)) -> 2 | R11: =IF($P11="PROXY",DAVERAGE('literature entries'!$D:$AI,IF($J11=1,"ACTIVE GHGE, FARM GATE (kg CO2e/kg)","GHGE, processor gate (kg CO2e/kg)"),INDIRECT($K11)),GETPIVOTDATA(IF($J11=1,"Average of ACTIVE GHGE, FARM GATE (kg CO2e/kg)","Average of GHGE, processor gate (kg CO2e/kg)"),'Pivot Table_GHG'!$A$3,"SUB TYPE",$B11)) -> 0.87 | S11: =IF($P11="PROXY",DSTDEV('literature entries'!$D:$AI,IF($J11=1,"ACTIVE GHGE, FARM GATE (kg CO2e/kg)","GHGE, processor gate (kg CO2e/kg)"),INDIRECT($K11)),GETPIVOTDATA(IF($J11=1,"StdDev of ACTIVE GHGE, FARM GATE (kg CO2e/kg)","StdDev of GHGE, processor gate (kg CO2e/kg)"),'Pivot Table_GHG'!$A$3,"SUB TYPE",$B11)) -> 0 | W11: no var | Z11: 0 | AA11: 0 | AB11: no var | AE11: 0 | AF11: 0
A12: 101190000 | B12: Horseradish | C12: weight of root, ground | E12: 364 | F12: =N12*H12+T12 -> 1.4220714 | G12: =R12*H12+U12 -> 0.2134 | H12: 1 | I12: None | J12: 1 | K12: roots | L12: =IF(ISERROR(GETPIVOTDATA(IF($J12=1,"Count of ACTIVE CED, FARM GATE (MJ/kg)","Count of CED, processor gate (MJ/kg)"),'Pivot Table_CED'!$A$3,"SUB TYPE",$B12)),"PROXY",IF(GETPIVOTDATA(IF($J12=1,"Count of ACTIVE CED, FARM GATE (MJ/kg)","Count of CED, processor gate (MJ/kg)"),'Pivot Table_CED'!$A$3,"SUB TYPE",$B12)=0,"PROXY","DB value")) -> PROXY | M12: =IF($L12="PROXY",DCOUNT('literature entries'!$D:$AI,IF($J12=1,"ACTIVE CED, FARM GATE (MJ/kg)","CED, processor gate (MJ/kg)"),INDIRECT($K12)),GETPIVOTDATA(IF($J12=1,"Count of ACTIVE CED, FARM GATE (MJ/kg)","Count of CED, processor gate (MJ/kg)"),'Pivot Table_CED'!$A$3,"SUB TYPE",$B12)) -> 14 | N12: =IF($L12="PROXY",DAVERAGE('literature entries'!$D:$AI,IF($J12=1,"ACTIVE CED, FARM GATE (MJ/kg)","CED, processor gate (MJ/kg)"),INDIRECT($K12)),GETPIVOTDATA(IF($J12=1,"Average of ACTIVE CED, FARM GATE (MJ/kg)","Average of CED, processor gate (MJ/kg)"),'Pivot Table_CED'!$A$3,"SUB TYPE",$B12)) -> 1.4220714 | O12: =IF($L12="PROXY",DSTDEV('literature entries'!D:AI,IF($J12=1,"ACTIVE CED, FARM GATE (MJ/kg)","CED, processor gate (MJ/kg)"),INDIRECT($K12)),GETPIVOTDATA(IF($J12=1,"StdDev of ACTIVE CED, FARM GATE (MJ/kg)","StdDev of CED, processor gate (MJ/kg)"),'Pivot Table_CED'!$A$3,"SUB TYPE",$B12)) -> 0.57442044 | P12: =IF(ISERROR(GETPIVOTDATA(IF($J12=1,"Count of ACTIVE GHGE, FARM GATE (kg CO2e/kg)","Count of GHGE, processor gate (kg CO2e/kg)"),'Pivot Table_GHG'!$A$3,"SUB TYPE",$B12)),"PROXY",IF(GETPIVOTDATA(IF($J12=1,"Count of ACTIVE GHGE, FARM GATE (kg CO2e/kg)","Count of GHGE, processor gate (kg CO2e/kg)"),'Pivot Table_GHG'!$A$3,"SUB TYPE",$B12)=0,"PROXY","DB value")) -> PROXY | Q12: =IF($P12="PROXY",DCOUNT('literature entries'!$D:$AI,IF($J12=1,"ACTIVE GHGE, FARM GATE (kg CO2e/kg)","GHGE, processor gate (kg CO2e/kg)"),INDIRECT($K12)),GETPIVOTDATA(IF($J12=1,"ACTIVE GHGE, FARM GATE (kg CO2e/kg)","Count of GHGE, processor gate (kg CO2e/kg)"),'Pivot Table_GHG'!$A$3,"SUB TYPE",$B12)) -> 25 | R12: =IF($P12="PROXY",DAVERAGE('literature entries'!$D:$AI,IF($J12=1,"ACTIVE GHGE, FARM GATE (kg CO2e/kg)","GHGE, processor gate (kg CO2e/kg)"),INDIRECT($K12)),GETPIVOTDATA(IF($J12=1,"Average of ACTIVE GHGE, FARM GATE (kg CO2e/kg)","Average of GHGE, processor gate (kg CO2e/kg)"),'Pivot Table_GHG'!$A$3,"SUB TYPE",$B12)) -> 0.2134 | S12: =IF($P12="PROXY",DSTDEV('literature entries'!$D:$AI,IF($J12=1,"ACTIVE GHGE, FARM GATE (kg CO2e/kg)","GHGE, processor gate (kg CO2e/kg)"),INDIRECT($K12)),GETPIVOTDATA(IF($J12=1,"StdDev of ACTIVE GHGE, FARM GATE (kg CO2e/kg)","StdDev of GHGE, processor gate (kg CO2e/kg)"),'Pivot Table_GHG'!$A$3,"SUB TYPE",$B12)) -> 0.17992035 | W12: =IF(L12="PROXY",IF(M12>=5,K12,"need group"),IF(M12>=5,"DIRECT","need group")) -> roots | X12: =IF($W12="DIRECT",M12,DCOUNT('literature entries'!$D:$AI,IF($J12=1,"ACTIVE CED, FARM GATE (MJ/kg)","CED, processor gate (MJ/kg)"),INDIRECT($W12))) -> 14 | Y12: =IF($W12="DIRECT","",DAVERAGE('literature entries'!$D:$AI,IF($J12=1,"ACTIVE CED, FARM GATE (MJ/kg)","CED, processor gate (MJ/kg)"),INDIRECT($W12))) -> 1.4220714 | Z12: =IF($W12="DIRECT",$O12,DSTDEV('literature entries'!$D:$AI,IF($J12=1,"ACTIVE CED, FARM GATE (MJ/kg)","CED, processor gate (MJ/kg)"),INDIRECT($W12))) -> 0.57442044 | AA12: =IF($W12="DIRECT",$O12,$Z12/$Y12*$N12) -> 0.57442044 | AB12: =IF(P12="PROXY",IF(Q12>=5,K12,"need group"),IF(Q12>=5,"DIRECT","need group")) -> roots | AC12: =IF($AB12="DIRECT",Q12,DCOUNT('literature entries'!$D:$AI,IF($J12=1,"ACTIVE GHGE, FARM GATE (kg CO2e/kg)","GHGE, processor gate (kg CO2e/kg)"),INDIRECT($AB12))) -> 25 | AD12: =IF($AB12="DIRECT","",DAVERAGE('literature entries'!$D:$AI,IF($J12=1,"ACTIVE GHGE, FARM GATE (kg CO2e/kg)","GHGE, processor gate (kg CO2e/kg)"),INDIRECT($AB12))) -> 0.2134 | AE12: =IF($AB12="DIRECT",$S12,DSTDEV('literature entries'!$D:$AI,IF($J12=1,"ACTIVE GHGE, FARM GATE (kg CO2e/kg)","GHGE, processor gate (kg CO2e/kg)"),INDIRECT($AB12))) -> 0.17992035 | AF12: =IF($AB12="DIRECT",$S12,$AE12/$AD12*$R12) -> 0.17992035
A13: 101251000 | B13: Parsnip | C13: weight of roots with or without peel | E13: 54 | F13: =N13*H13+T13 -> 1.6211614 | G13: =R13*H13+U13 -> 0.243276 | H13: 1.14 | I13: FICRCD | J13: 1 | K13: roots | L13: =IF(ISERROR(GETPIVOTDATA(IF($J13=1,"Count of ACTIVE CED, FARM GATE (MJ/kg)","Count of CED, processor gate (MJ/kg)"),'Pivot Table_CED'!$A$3,"SUB TYPE",$B13)),"PROXY",IF(GETPIVOTDATA(IF($J13=1,"Count of ACTIVE CED, FARM GATE (MJ/kg)","Count of CED, processor gate (MJ/kg)"),'Pivot Table_CED'!$A$3,"SUB TYPE",$B13)=0,"PROXY","DB value")) -> PROXY | M13: =IF($L13="PROXY",DCOUNT('literature entries'!$D:$AI,IF($J13=1,"ACTIVE CED, FARM GATE (MJ/kg)","CED, processor gate (MJ/kg)"),INDIRECT($K13)),GETPIVOTDATA(IF($J13=1,"Count of ACTIVE CED, FARM GATE (MJ/kg)","Count of CED, processor gate (MJ/kg)"),'Pivot Table_CED'!$A$3,"SUB TYPE",$B13)) -> 14 | N13: =IF($L13="PROXY",DAVERAGE('literature entries'!$D:$AI,IF($J13=1,"ACTIVE CED, FARM GATE (MJ/kg)","CED, processor gate (MJ/kg)"),INDIRECT($K13)),GETPIVOTDATA(IF($J13=1,"Average of ACTIVE CED, FARM GATE (MJ/kg)","Average of CED, processor gate (MJ/kg)"),'Pivot Table_CED'!$A$3,"SUB TYPE",$B13)) -> 1.4220714 | O13: =IF($L13="PROXY",DSTDEV('literature entries'!D:AI,IF($J13=1,"ACTIVE CED, FARM GATE (MJ/kg)","CED, processor gate (MJ/kg)"),INDIRECT($K13)),GETPIVOTDATA(IF($J13=1,"StdDev of ACTIVE CED, FARM GATE (MJ/kg)","StdDev of CED, processor gate (MJ/kg)"),'Pivot Table_CED'!$A$3,"SUB TYPE",$B13)) -> 0.57442044 | P13: =IF(ISERROR(GETPIVOTDATA(IF($J13=1,"Count of ACTIVE GHGE, FARM GATE (kg CO2e/kg)","Count of GHGE, processor gate (kg CO2e/kg)"),'Pivot Table_GHG'!$A$3,"SUB TYPE",$B13)),"PROXY",IF(GETPIVOTDATA(IF($J13=1,"Count of ACTIVE GHGE, FARM GATE (kg CO2e/kg)","Count of GHGE, processor gate (kg CO2e/kg)"),'Pivot Table_GHG'!$A$3,"SUB TYPE",$B13)=0,"PROXY","DB value")) -> PROXY | Q13: =IF($P13="PROXY",DCOUNT('literature entries'!$D:$AI,IF($J13=1,"ACTIVE GHGE, FARM GATE (kg CO2e/kg)","GHGE, processor gate (kg CO2e/kg)"),INDIRECT($K13)),GETPIVOTDATA(IF($J13=1,"ACTIVE GHGE, FARM GATE (kg CO2e/kg)","Count of GHGE, processor gate (kg CO2e/kg)"),'Pivot Table_GHG'!$A$3,"SUB TYPE",$B13)) -> 25 | R13: =IF($P13="PROXY",DAVERAGE('literature entries'!$D:$AI,IF($J13=1,"ACTIVE GHGE, FARM GATE (kg CO2e/kg)","GHGE, processor gate (kg CO2e/kg)"),INDIRECT($K13)),GETPIVOTDATA(IF($J13=1,"Average of ACTIVE GHGE, FARM GATE (kg CO2e/kg)","Average of GHGE, processor gate (kg CO2e/kg)"),'Pivot Table_GHG'!$A$3,"SUB TYPE",$B13)) -> 0.2134 | S13: =IF($P13="PROXY",DSTDEV('literature entries'!$D:$AI,IF($J13=1,"ACTIVE GHGE, FARM GATE (kg CO2e/kg)","GHGE, processor gate (kg CO2e/kg)"),INDIRECT($K13)),GETPIVOTDATA(IF($J13=1,"StdDev of ACTIVE GHGE, FARM GATE (kg CO2e/kg)","StdDev of GHGE, processor gate (kg CO2e/kg)"),'Pivot Table_GHG'!$A$3,"SUB TYPE",$B13)) -> 0.17992035 | W13: =IF(L13="PROXY",IF(M13>=5,K13,"need group"),IF(M13>=5,"DIRECT","need group")) -> roots | X13: =IF($W13="DIRECT",M13,DCOUNT('literature entries'!$D:$AI,IF($J13=1,"ACTIVE CED, FARM GATE (MJ/kg)","CED, processor gate (MJ/kg)"),INDIRECT($W13))) -> 14 | Y13: =IF($W13="DIRECT","",DAVERAGE('literature entries'!$D:$AI,IF($J13=1,"ACTIVE CED, FARM GATE (MJ/kg)","CED, processor gate (MJ/kg)"),INDIRECT($W13))) -> 1.4220714 | Z13: =IF($W13="DIRECT",$O13,DSTDEV('literature entries'!$D:$AI,IF($J13=1,"ACTIVE CED, FARM GATE (MJ/kg)","CED, processor gate (MJ/kg)"),INDIRECT($W13))) -> 0.57442044 | AA13: =IF($W13="DIRECT",$O13,$Z13/$Y13*$N13) -> 0.57442044 | AB13: =IF(P13="PROXY",IF(Q13>=5,K13,"need group"),IF(Q13>=5,"DIRECT","need group")) -> roots | AC13: =IF($AB13="DIRECT",Q13,DCOUNT('literature entries'!$D:$AI,IF($J13=1,"ACTIVE GHGE, FARM GATE (kg CO2e/kg)","GHGE, processor gate (kg CO2e/kg)"),INDIRECT($AB13))) -> 25 | AD13: =IF($AB13="DIRECT","",DAVERAGE('literature entries'!$D:$AI,IF($J13=1,"ACTIVE GHGE, FARM GATE (kg CO2e/kg)","GHGE, processor gate (kg CO2e/kg)"),INDIRECT($AB13))) -> 0.2134 | AE13: =IF($AB13="DIRECT",$S13,DSTDEV('literature entries'!$D:$AI,IF($J13=1,"ACTIVE GHGE, FARM GATE (kg CO2e/kg)","GHGE, processor gate (kg CO2e/kg)"),INDIRECT($AB13))) -> 0.17992035 | AF13: =IF($AB13="DIRECT",$S13,$AE13/$AD13*$R13) -> 0.17992035
A14: 101314000 | B14: Radish, roots | C14: weight of roots | E14: 503 | F14: =N14*H14+T14 -> 1.5784993 | G14: =R14*H14+U14 -> 0.236874 | H14: 1.11 | I14: FICRCD | J14: 1 | K14: roots | L14: =IF(ISERROR(GETPIVOTDATA(IF($J14=1,"Count of ACTIVE CED, FARM GATE (MJ/kg)","Count of CED, processor gate (MJ/kg)"),'Pivot Table_CED'!$A$3,"SUB TYPE",$B14)),"PROXY",IF(GETPIVOTDATA(IF($J14=1,"Count of ACTIVE CED, FARM GATE (MJ/kg)","Count of CED, processor gate (MJ/kg)"),'Pivot Table_CED'!$A$3,"SUB TYPE",$B14)=0,"PROXY","DB value")) -> PROXY | M14: =IF($L14="PROXY",DCOUNT('literature entries'!$D:$AI,IF($J14=1,"ACTIVE CED, FARM GATE (MJ/kg)","CED, processor gate (MJ/kg)"),INDIRECT($K14)),GETPIVOTDATA(IF($J14=1,"Count of ACTIVE CED, FARM GATE (MJ/kg)","Count of CED, processor gate (MJ/kg)"),'Pivot Table_CED'!$A$3,"SUB TYPE",$B14)) -> 14 | N14: =IF($L14="PROXY",DAVERAGE('literature entries'!$D:$AI,IF($J14=1,"ACTIVE CED, FARM GATE (MJ/kg)","CED, processor gate (MJ/kg)"),INDIRECT($K14)),GETPIVOTDATA(IF($J14=1,"Average of ACTIVE CED, FARM GATE (MJ/kg)","Average of CED, processor gate (MJ/kg)"),'Pivot Table_CED'!$A$3,"SUB TYPE",$B14)) -> 1.4220714 | O14: =IF($L14="PROXY",DSTDEV('literature entries'!D:AI,IF($J14=1,"ACTIVE CED, FARM GATE (MJ/kg)","CED, processor gate (MJ/kg)"),INDIRECT($K14)),GETPIVOTDATA(IF($J14=1,"StdDev of ACTIVE CED, FARM GATE (MJ/kg)","StdDev of CED, processor gate (MJ/kg)"),'Pivot Table_CED'!$A$3,"SUB TYPE",$B14)) -> 0.57442044 | P14: =IF(ISERROR(GETPIVOTDATA(IF($J14=1,"Count of ACTIVE GHGE, FARM GATE (kg CO2e/kg)","Count of GHGE, processor gate (kg CO2e/kg)"),'Pivot Table_GHG'!$A$3,"SUB TYPE",$B14)),"PROXY",IF(GETPIVOTDATA(IF($J14=1,"Count of ACTIVE GHGE, FARM GATE (kg CO2e/kg)","Count of GHGE, processor gate (kg CO2e/kg)"),'Pivot Table_GHG'!$A$3,"SUB TYPE",$B14)=0,"PROXY","DB value")) -> PROXY | Q14: =IF($P14="PROXY",DCOUNT('literature entries'!$D:$AI,IF($J14=1,"ACTIVE GHGE, FARM GATE (kg CO2e/kg)","GHGE, processor gate (kg CO2e/kg)"),INDIRECT($K14)),GETPIVOTDATA(IF($J14=1,"ACTIVE GHGE, FARM GATE (kg CO2e/kg)","Count of GHGE, processor gate (kg CO2e/kg)"),'Pivot Table_GHG'!$A$3,"SUB TYPE",$B14)) -> 25 | R14: =IF($P14="PROXY",DAVERAGE('literature entries'!$D:$AI,IF($J14=1,"ACTIVE GHGE, FARM GATE (kg CO2e/kg)","GHGE, processor gate (kg CO2e/kg)"),INDIRECT($K14)),GETPIVOTDATA(IF($J14=1,"Average of ACTIVE GHGE, FARM GATE (kg CO2e/kg)","Average of GHGE, processor gate (kg CO2e/kg)"),'Pivot Table_GHG'!$A$3,"SUB TYPE",$B14)) -> 0.2134 | S14: =IF($P14="PROXY",DSTDEV('literature entries'!$D:$AI,IF($J14=1,"ACTIVE GHGE, FARM GATE (kg CO2e/kg)","GHGE, processor gate (kg CO2e/kg)"),INDIRECT($K14)),GETPIVOTDATA(IF($J14=1,"StdDev of ACTIVE GHGE, FARM GATE (kg CO2e/kg)","StdDev of GHGE, processor gate (kg CO2e/kg)"),'Pivot Table_GHG'!$A$3,"SUB TYPE",$B14)) -> 0.17992035 | W14: =IF(L14="PROXY",IF(M14>=5,K14,"need group"),IF(M14>=5,"DIRECT","need group")) -> roots | X14: =IF($W14="DIRECT",M14,DCOUNT('literature entries'!$D:$AI,IF($J14=1,"ACTIVE CED, FARM GATE (MJ/kg)","CED, processor gate (MJ/kg)"),INDIRECT($W14))) -> 14 | Y14: =IF($W14="DIRECT","",DAVERAGE('literature entries'!$D:$AI,IF($J14=1,"ACTIVE CED, FARM GATE (MJ/kg)","CED, processor gate (MJ/kg)"),INDIRECT($W14))) -> 1.4220714 | Z14: =IF($W14="DIRECT",$O14,DSTDEV('literature entries'!$D:$AI,IF($J14=1,"ACTIVE CED, FARM GATE (MJ/kg)","CED, processor gate (MJ/kg)"),INDIRECT($W14))) -> 0.57442044 | AA14: =IF($W14="DIRECT",$O14,$Z14/$Y14*$N14) -> 0.57442044 | AB14: =IF(P14="PROXY",IF(Q14>=5,K14,"need group"),IF(Q14>=5,"DIRECT","need group")) -> roots | AC14: =IF($AB14="DIRECT",Q14,DCOUNT('literature entries'!$D:$AI,IF($J14=1,"ACTIVE GHGE, FARM GATE (kg CO2e/kg)","GHGE, processor gate (kg CO2e/kg)"),INDIRECT($AB14))) -> 25 | AD14: =IF($AB14="DIRECT","",DAVERAGE('literature entries'!$D:$AI,IF($J14=1,"ACTIVE GHGE, FARM GATE (kg CO2e/kg)","GHGE, processor gate (kg CO2e/kg)"),INDIRECT($AB14))) -> 0.2134 | AE14: =IF($AB14="DIRECT",$S14,DSTDEV('literature entries'!$D:$AI,IF($J14=1,"ACTIVE GHGE, FARM GATE (kg CO2e/kg)","GHGE, processor gate (kg CO2e/kg)"),INDIRECT($AB14))) -> 0.17992035 | AF14: =IF($AB14="DIRECT",$S14,$AE14/$AD14*$R14) -> 0.17992035
A15: 101316000 | B15: Radish, Oriental, roots | C15: weight of roots | E15: 7 | F15: =N15*H15+T15 -> 1.8060307 | G15: =R15*H15+U15 -> 0.271018 | H15: 1.27 | I15: FICRCD | J15: 1 | K15: roots | L15: =IF(ISERROR(GETPIVOTDATA(IF($J15=1,"Count of ACTIVE CED, FARM GATE (MJ/kg)","Count of CED, processor gate (MJ/kg)"),'Pivot Table_CED'!$A$3,"SUB TYPE",$B15)),"PROXY",IF(GETPIVOTDATA(IF($J15=1,"Count of ACTIVE CED, FARM GATE (MJ/kg)","Count of CED, processor gate (MJ/kg)"),'Pivot Table_CED'!$A$3,"SUB TYPE",$B15)=0,"PROXY","DB value")) -> PROXY | M15: =IF($L15="PROXY",DCOUNT('literature entries'!$D:$AI,IF($J15=1,"ACTIVE CED, FARM GATE (MJ/kg)","CED, processor gate (MJ/kg)"),INDIRECT($K15)),GETPIVOTDATA(IF($J15=1,"Count of ACTIVE CED, FARM GATE (MJ/kg)","Count of CED, processor gate (MJ/kg)"),'Pivot Table_CED'!$A$3,"SUB TYPE",$B15)) -> 14 | N15: =IF($L15="PROXY",DAVERAGE('literature entries'!$D:$AI,IF($J15=1,"ACTIVE CED, FARM GATE (MJ/kg)","CED, processor gate (MJ/kg)"),INDIRECT($K15)),GETPIVOTDATA(IF($J15=1,"Average of ACTIVE CED, FARM GATE (MJ/kg)","Average of CED, processor gate (MJ/kg)"),'Pivot Table_CED'!$A$3,"SUB TYPE",$B15)) -> 1.4220714 | O15: =IF($L15="PROXY",DSTDEV('literature entries'!D:AI,IF($J15=1,"ACTIVE CED, FARM GATE (MJ/kg)","CED, processor gate (MJ/kg)"),INDIRECT($K15)),GETPIVOTDATA(IF($J15=1,"StdDev of ACTIVE CED, FARM GATE (MJ/kg)","StdDev of CED, processor gate (MJ/kg)"),'Pivot Table_CED'!$A$3,"SUB TYPE",$B15)) -> 0.57442044 | P15: =IF(ISERROR(GETPIVOTDATA(IF($J15=1,"Count of ACTIVE GHGE, FARM GATE (kg CO2e/kg)","Count of GHGE, processor gate (kg CO2e/kg)"),'Pivot Table_GHG'!$A$3,"SUB TYPE",$B15)),"PROXY",IF(GETPIVOTDATA(IF($J15=1,"Count of ACTIVE GHGE, FARM GATE (kg CO2e/kg)","Count of GHGE, processor gate (kg CO2e/kg)"),'Pivot Table_GHG'!$A$3,"SUB TYPE",$B15)=0,"PROXY","DB value")) -> PROXY | Q15: =IF($P15="PROXY",DCOUNT('literature entries'!$D:$AI,IF($J15=1,"ACTIVE GHGE, FARM GATE (kg CO2e/kg)","GHGE, processor gate (kg CO2e/kg)"),INDIRECT($K15)),GETPIVOTDATA(IF($J15=1,"ACTIVE GHGE, FARM GATE (kg CO2e/kg)","Count of GHGE, processor gate (kg CO2e/kg)"),'Pivot Table_GHG'!$A$3,"SUB TYPE",$B15)) -> 25 | R15: =IF($P15="PROXY",DAVERAGE('literature entries'!$D:$AI,IF($J15=1,"ACTIVE GHGE, FARM GATE (kg CO2e/kg)","GHGE, processor gate (kg CO2e/kg)"),INDIRECT($K15)),GETPIVOTDATA(IF($J15=1,"Average of ACTIVE GHGE, FARM GATE (kg CO2e/kg)","Average of GHGE, processor gate (kg CO2e/kg)"),'Pivot Table_GHG'!$A$3,"SUB TYPE",$B15)) -> 0.2134 | S15: =IF($P15="PROXY",DSTDEV('literature entries'!$D:$AI,IF($J15=1,"ACTIVE GHGE, FARM GATE (kg CO2e/kg)","GHGE, processor gate (kg CO2e/kg)"),INDIRECT($K15)),GETPIVOTDATA(IF($J15=1,"StdDev of ACTIVE GHGE, FARM GATE (kg CO2e/kg)","StdDev of GHGE, processor gate (kg CO2e/kg)"),'Pivot Table_GHG'!$A$3,"SUB TYPE",$B15)) -> 0.17992035 | W15: =IF(L15="PROXY",IF(M15>=5,K15,"need group"),IF(M15>=5,"DIRECT","need group")) -> roots | X15: =IF($W15="DIRECT",M15,DCOUNT('literature entries'!$D:$AI,IF($J15=1,"ACTIVE CED, FARM GATE (MJ/kg)","CED, processor gate (MJ/kg)"),INDIRECT($W15))) -> 14 | Y15: =IF($W15="DIRECT","",DAVERAGE('literature entries'!$D:$AI,IF($J15=1,"ACTIVE CED, FARM GATE (MJ/kg)","CED, processor gate (MJ/kg)"),INDIRECT($W15))) -> 1.4220714 | Z15: =IF($W15="DIRECT",$O15,DSTDEV('literature entries'!$D:$AI,IF($J15=1,"ACTIVE CED, FARM GATE (MJ/kg)","CED, processor gate (MJ/kg)"),INDIRECT($W15))) -> 0.57442044 | AA15: =IF($W15="DIRECT",$O15,$Z15/$Y15*$N15) -> 0.57442044 | AB15: =IF(P15="PROXY",IF(Q15>=5,K15,"need group"),IF(Q15>=5,"DIRECT","need group")) -> roots | AC15: =IF($AB15="DIRECT",Q15,DCOUNT('literature entries'!$D:$AI,IF($J15=1,"ACTIVE GHGE, FARM GATE (kg CO2e/kg)","GHGE, processor gate (kg CO2e/kg)"),INDIRECT($AB15))) -> 25 | AD15: =IF($AB15="DIRECT","",DAVERAGE('literature entries'!$D:$AI,IF($J15=1,"ACTIVE GHGE, FARM GATE (kg CO2e/kg)","GHGE, processor gate (kg CO2e/kg)"),INDIRECT($AB15))) -> 0.2134 | AE15: =IF($AB15="DIRECT",$S15,DSTDEV('literature entries'!$D:$AI,IF($J15=1,"ACTIVE GHGE, FARM GATE (kg CO2e/kg)","GHGE, processor gate (kg CO2e/kg)"),INDIRECT($AB15))) -> 0.17992035 | AF15: =IF($AB15="DIRECT",$S15,$AE15/$AD15*$R15) -> 0.17992035
A16: 101327000 | B16: Rutabaga | C16: weight of roots; excluding tops | E16: 265 | F16: =N16*H16+T16 -> 1.6780443 | G16: =R16*H16+U16 -> 0.251812 | H16: 1.18 | I16: FICRCD | J16: 1 | K16: roots | L16: =IF(ISERROR(GETPIVOTDATA(IF($J16=1,"Count of ACTIVE CED, FARM GATE (MJ/kg)","Count of CED, processor gate (MJ/kg)"),'Pivot Table_CED'!$A$3,"SUB TYPE",$B16)),"PROXY",IF(GETPIVOTDATA(IF($J16=1,"Count of ACTIVE CED, FARM GATE (MJ/kg)","Count of CED, processor gate (MJ/kg)"),'Pivot Table_CED'!$A$3,"SUB TYPE",$B16)=0,"PROXY","DB value")) -> PROXY | M16: =IF($L16="PROXY",DCOUNT('literature entries'!$D:$AI,IF($J16=1,"ACTIVE CED, FARM GATE (MJ/kg)","CED, processor gate (MJ/kg)"),INDIRECT($K16)),GETPIVOTDATA(IF($J16=1,"Count of ACTIVE CED, FARM GATE (MJ/kg)","Count of CED, processor gate (MJ/kg)"),'Pivot Table_CED'!$A$3,"SUB TYPE",$B16)) -> 14 | N16: =IF($L16="PROXY",DAVERAGE('literature entries'!$D:$AI,IF($J16=1,"ACTIVE CED, FARM GATE (MJ/kg)","CED, processor gate (MJ/kg)"),INDIRECT($K16)),GETPIVOTDATA(IF($J16=1,"Average of ACTIVE CED, FARM GATE (MJ/kg)","Average of CED, processor gate (MJ/kg)"),'Pivot Table_CED'!$A$3,"SUB TYPE",$B16)) -> 1.4220714 | O16: =IF($L16="PROXY",DSTDEV('literature entries'!D:AI,IF($J16=1,"ACTIVE CED, FARM GATE (MJ/kg)","CED, processor gate (MJ/kg)"),INDIRECT($K16)),GETPIVOTDATA(IF($J16=1,"StdDev of ACTIVE CED, FARM GATE (MJ/kg)","StdDev of CED, processor gate (MJ/kg)"),'Pivot Table_CED'!$A$3,"SUB TYPE",$B16)) -> 0.57442044 | P16: =IF(ISERROR(GETPIVOTDATA(IF($J16=1,"Count of ACTIVE GHGE, FARM GATE (kg CO2e/kg)","Count of GHGE, processor gate (kg CO2e/kg)"),'Pivot Table_GHG'!$A$3,"SUB TYPE",$B16)),"PROXY",IF(GETPIVOTDATA(IF($J16=1,"Count of ACTIVE GHGE, FARM GATE (kg CO2e/kg)","Count of GHGE, processor gate (kg CO2e/kg)"),'Pivot Table_GHG'!$A$3,"SUB TYPE",$B16)=0,"PROXY","DB value")) -> PROXY | Q16: =IF($P16="PROXY",DCOUNT('literature entries'!$D:$AI,IF($J16=1,"ACTIVE GHGE, FARM GATE (kg CO2e/kg)","GHGE, processor gate (kg CO2e/kg)"),INDIRECT($K16)),GETPIVOTDATA(IF($J16=1,"ACTIVE GHGE, FARM GATE (kg CO2e/kg)","Count of GHGE, processor gate (kg CO2e/kg)"),'Pivot Table_GHG'!$A$3,"SUB TYPE",$B16)) -> 25 | R16: =IF($P16="PROXY",DAVERAGE('literature entries'!$D:$AI,IF($J16=1,"ACTIVE GHGE, FARM GATE (kg CO2e/kg)","GHGE, processor gate (kg CO2e/kg)"),INDIRECT($K16)),GETPIVOTDATA(IF($J16=1,"Average of ACTIVE GHGE, FARM GATE (kg CO2e/kg)","Average of GHGE, processor gate (kg CO2e/kg)"),'Pivot Table_GHG'!$A$3,"SUB TYPE",$B16)) -> 0.2134 | S16: =IF($P16="PROXY",DSTDEV('literature entries'!$D:$AI,IF($J16=1,"ACTIVE GHGE, FARM GATE (kg CO2e/kg)","GHGE, processor gate (kg CO2e/kg)"),INDIRECT($K16)),GETPIVOTDATA(IF($J16=1,"StdDev of ACTIVE GHGE, FARM GATE (kg CO2e/kg)","StdDev of GHGE, processor gate (kg CO2e/kg)"),'Pivot Table_GHG'!$A$3,"SUB TYPE",$B16)) -> 0.17992035 | W16: =IF(L16="PROXY",IF(M16>=5,K16,"need group"),IF(M16>=5,"DIRECT","need group")) -> roots | X16: =IF($W16="DIRECT",M16,DCOUNT('literature entries'!$D:$AI,IF($J16=1,"ACTIVE CED, FARM GATE (MJ/kg)","CED, processor gate (MJ/kg)"),INDIRECT($W16))) -> 14 | Y16: =IF($W16="DIRECT","",DAVERAGE('literature entries'!$D:$AI,IF($J16=1,"ACTIVE CED, FARM GATE (MJ/kg)","CED, processor gate (MJ/kg)"),INDIRECT($W16))) -> 1.4220714 | Z16: =IF($W16="DIRECT",$O16,DSTDEV('literature entries'!$D:$AI,IF($J16=1,"ACTIVE CED, FARM GATE (MJ/kg)","CED, processor gate (MJ/kg)"),INDIRECT($W16))) -> 0.57442044 | AA16: =IF($W16="DIRECT",$O16,$Z16/$Y16*$N16) -> 0.57442044 | AB16: =IF(P16="PROXY",IF(Q16>=5,K16,"need group"),IF(Q16>=5,"DIRECT","need group")) -> roots | AC16: =IF($AB16="DIRECT",Q16,DCOUNT('literature entries'!$D:$AI,IF($J16=1,"ACTIVE GHGE, FARM GATE (kg CO2e/kg)","GHGE, processor gate (kg CO2e/kg)"),INDIRECT($AB16))) -> 25 | AD16: =IF($AB16="DIRECT","",DAVERAGE('literature entries'!$D:$AI,IF($J16=1,"ACTIVE GHGE, FARM GATE (kg CO2e/kg)","GHGE, processor gate (kg CO2e/kg)"),INDIRECT($AB16))) -> 0.2134 | AE16: =IF($AB16="DIRECT",$S16,DSTDEV('literature entries'!$D:$AI,IF($J16=1,"ACTIVE GHGE, FARM GATE (kg CO2e/kg)","GHGE, processor gate (kg CO2e/kg)"),INDIRECT($AB16))) -> 0.17992035 | AF16: =IF($AB16="DIRECT",$S16,$AE16/$AD16*$R16) -> 0.17992035
A17: 101388000 | B17: Turnip, roots | C17: weight of roots | E17: 59 | F17: =N17*H17+T17 -> 1.7491479 | G17: =R17*H17+U17 -> 0.49815 | H17: 1.23 | I17: FICRCD | J17: 1 | K17: roots | L17: =IF(ISERROR(GETPIVOTDATA(IF($J17=1,"Count of ACTIVE CED, FARM GATE (MJ/kg)","Count of CED, processor gate (MJ/kg)"),'Pivot Table_CED'!$A$3,"SUB TYPE",$B17)),"PROXY",IF(GETPIVOTDATA(IF($J17=1,"Count of ACTIVE CED, FARM GATE (MJ/kg)","Count of CED, processor gate (MJ/kg)"),'Pivot Table_CED'!$A$3,"SUB TYPE",$B17)=0,"PROXY","DB value")) -> PROXY | M17: =IF($L17="PROXY",DCOUNT('literature entries'!$D:$AI,IF($J17=1,"ACTIVE CED, FARM GATE (MJ/kg)","CED, processor gate (MJ/kg)"),INDIRECT($K17)),GETPIVOTDATA(IF($J17=1,"Count of ACTIVE CED, FARM GATE (MJ/kg)","Count of CED, processor gate (MJ/kg)"),'Pivot Table_CED'!$A$3,"SUB TYPE",$B17)) -> 14 | N17: =IF($L17="PROXY",DAVERAGE('literature entries'!$D:$AI,IF($J17=1,"ACTIVE CED, FARM GATE (MJ/kg)","CED, processor gate (MJ/kg)"),INDIRECT($K17)),GETPIVOTDATA(IF($J17=1,"Average of ACTIVE CED, FARM GATE (MJ/kg)","Average of CED, processor gate (MJ/kg)"),'Pivot Table_CED'!$A$3,"SUB TYPE",$B17)) -> 1.4220714 | O17: =IF($L17="PROXY",DSTDEV('literature entries'!D:AI,IF($J17=1,"ACTIVE CED, FARM GATE (MJ/kg)","CED, processor gate (MJ/kg)"),INDIRECT($K17)),GETPIVOTDATA(IF($J17=1,"StdDev of ACTIVE CED, FARM GATE (MJ/kg)","StdDev of CED, processor gate (MJ/kg)"),'Pivot Table_CED'!$A$3,"SUB TYPE",$B17)) -> 0.57442044 | P17: =IF(ISERROR(GETPIVOTDATA(IF($J17=1,"Count of ACTIVE GHGE, FARM GATE (kg CO2e/kg)","Count of GHGE, processor gate (kg CO2e/kg)"),'Pivot Table_GHG'!$A$3,"SUB TYPE",$B17)),"PROXY",IF(GETPIVOTDATA(IF($J17=1,"Count of ACTIVE GHGE, FARM GATE (kg CO2e/kg)","Count of GHGE, processor gate (kg CO2e/kg)"),'Pivot Table_GHG'!$A$3,"SUB TYPE",$B17)=0,"PROXY","DB value")) -> DB value | Q17: =IF($P17="PROXY",DCOUNT('literature entries'!$D:$AI,IF($J17=1,"ACTIVE GHGE, FARM GATE (kg CO2e/kg)","GHGE, processor gate (kg CO2e/kg)"),INDIRECT($K17)),GETPIVOTDATA(IF($J17=1,"ACTIVE GHGE, FARM GATE (kg CO2e/kg)","Count of GHGE, processor gate (kg CO2e/kg)"),'Pivot Table_GHG'!$A$3,"SUB TYPE",$B17)) -> 2 | R17: =IF($P17="PROXY",DAVERAGE('literature entries'!$D:$AI,IF($J17=1,"ACTIVE GHGE, FARM GATE (kg CO2e/kg)","GHGE, processor gate (kg CO2e/kg)"),INDIRECT($K17)),GETPIVOTDATA(IF($J17=1,"Average of ACTIVE GHGE, FARM GATE (kg CO2e/kg)","Average of GHGE, processor gate (kg CO2e/kg)"),'Pivot Table_GHG'!$A$3,"SUB TYPE",$B17)) -> 0.405 | S17: =IF($P17="PROXY",DSTDEV('literature entries'!$D:$AI,IF($J17=1,"ACTIVE GHGE, FARM GATE (kg CO2e/kg)","GHGE, processor gate (kg CO2e/kg)"),INDIRECT($K17)),GETPIVOTDATA(IF($J17=1,"StdDev of ACTIVE GHGE, FARM GATE (kg CO2e/kg)","StdDev of GHGE, processor gate (kg CO2e/kg)"),'Pivot Table_GHG'!$A$3,"SUB TYPE",$B17)) -> 0.077781746 | W17: =IF(L17="PROXY",IF(M17>=5,K17,"need group"),IF(M17>=5,"DIRECT","need group")) -> roots | X17: =IF($W17="DIRECT",M17,DCOUNT('literature entries'!$D:$AI,IF($J17=1,"ACTIVE CED, FARM GATE (MJ/kg)","CED, processor gate (MJ/kg)"),INDIRECT($W17))) -> 14 | Y17: =IF($W17="DIRECT","",DAVERAGE('literature entries'!$D:$AI,IF($J17=1,"ACTIVE CED, FARM GATE (MJ/kg)","CED, processor gate (MJ/kg)"),INDIRECT($W17))) -> 1.4220714 | Z17: =IF($W17="DIRECT",$O17,DSTDEV('literature entries'!$D:$AI,IF($J17=1,"ACTIVE CED, FARM GATE (MJ/kg)","CED, processor gate (MJ/kg)"),INDIRECT($W17))) -> 0.57442044 | AA17: =IF($W17="DIRECT",$O17,$Z17/$Y17*$N17) -> 0.57442044 | AB17: roots | AC17: =IF($AB17="DIRECT",Q17,DCOUNT('literature entries'!$D:$AI,IF($J17=1,"ACTIVE GHGE, FARM GATE (kg CO2e/kg)","GHGE, processor gate (kg CO2e/kg)"),INDIRECT($AB17))) -> 25 | AD17: =IF($AB17="DIRECT","",DAVERAGE('literature entries'!$D:$AI,IF($J17=1,"ACTIVE GHGE, FARM GATE (kg CO2e/kg)","GHGE, processor gate (kg CO2e/kg)"),INDIRECT($AB17))) -> 0.2134 | AE17: =IF($AB17="DIRECT",$S17,DSTDEV('literature entries'!$D:$AI,IF($J17=1,"ACTIVE GHGE, FARM GATE (kg CO2e/kg)","GHGE, processor gate (kg CO2e/kg)"),INDIRECT($AB17))) -> 0.17992035 | AF17: =IF($AB17="DIRECT",$S17,$AE17/$AD17*$R17) -> 0.34146084
A18: 103015000 | B18: Arrowroot, flour | C18: dry weight of flour | E18: 987 | F18: =N18*H18+T18 -> 0.625 | G18: =R18*H18+U18 -> 0.0788 | H18: 1 | I18: None | J18: 1 | K18: cassava | L18: =IF(ISERROR(GETPIVOTDATA(IF($J18=1,"Count of ACTIVE CED, FARM GATE (MJ/kg)","Count of CED, processor gate (MJ/kg)"),'Pivot Table_CED'!$A$3,"SUB TYPE",$B18)),"PROXY",IF(GETPIVOTDATA(IF($J18=1,"Count of ACTIVE CED, FARM GATE (MJ/kg)","Count of CED, processor gate (MJ/kg)"),'Pivot Table_CED'!$A$3,"SUB TYPE",$B18)=0,"PROXY","DB value")) -> PROXY | M18: =IF($L18="PROXY",DCOUNT('literature entries'!$D:$AI,IF($J18=1,"ACTIVE CED, FARM GATE (MJ/kg)","CED, processor gate (MJ/kg)"),INDIRECT($K18)),GETPIVOTDATA(IF($J18=1,"Count of ACTIVE CED, FARM GATE (MJ/kg)","Count of CED, processor gate (MJ/kg)"),'Pivot Table_CED'!$A$3,"SUB TYPE",$B18)) -> 1 | N18: =IF($L18="PROXY",DAVERAGE('literature entries'!$D:$AI,IF($J18=1,"ACTIVE CED, FARM GATE (MJ/kg)","CED, processor gate (MJ/kg)"),INDIRECT($K18)),GETPIVOTDATA(IF($J18=1,"Average of ACTIVE CED, FARM GATE (MJ/kg)","Average of CED, processor gate (MJ/kg)"),'Pivot Table_CED'!$A$3,"SUB TYPE",$B18)) -> 0.625 | O18: =IF($L18="PROXY",DSTDEV('literature entries'!D:AI,IF($J18=1,"ACTIVE CED, FARM GATE (MJ/kg)","CED, processor gate (MJ/kg)"),INDIRECT($K18)),GETPIVOTDATA(IF($J18=1,"StdDev of ACTIVE CED, FARM GATE (MJ/kg)","StdDev of CED, processor gate (MJ/kg)"),'Pivot Table_CED'!$A$3,"SUB TYPE",$B18)) -> #DIV/0! | P18: =IF(ISERROR(GETPIVOTDATA(IF($J18=1,"Count of ACTIVE GHGE, FARM GATE (kg CO2e/kg)","Count of GHGE, processor gate (kg CO2e/kg)"),'Pivot Table_GHG'!$A$3,"SUB TYPE",$B18)),"PROXY",IF(GETPIVOTDATA(IF($J18=1,"Count of ACTIVE GHGE, FARM GATE (kg CO2e/kg)","Count of GHGE, processor gate (kg CO2e/kg)"),'Pivot Table_GHG'!$A$3,"SUB TYPE",$B18)=0,"PROXY","DB value")) -> PROXY | Q18: =IF($P18="PROXY",DCOUNT('literature entries'!$D:$AI,IF($J18=1,"ACTIVE GHGE, FARM GATE (kg CO2e/kg)","GHGE, processor gate (kg CO2e/kg)"),INDIRECT($K18)),GETPIVOTDATA(IF($J18=1,"ACTIVE GHGE, FARM GATE (kg CO2e/kg)","Count of GHGE, processor gate (kg CO2e/kg)"),'Pivot Table_GHG'!$A$3,"SUB TYPE",$B18)) -> 1 | R18: =IF($P18="PROXY",DAVERAGE('literature entries'!$D:$AI,IF($J18=1,"ACTIVE GHGE, FARM GATE (kg CO2e/kg)","GHGE, processor gate (kg CO2e/kg)"),INDIRECT($K18)),GETPIVOTDATA(IF($J18=1,"Average of ACTIVE GHGE, FARM GATE (kg CO2e/kg)","Average of GHGE, processor gate (kg CO2e/kg)"),'Pivot Table_GHG'!$A$3,"SUB TYPE",$B18)) -> 0.0788 | S18: =IF($P18="PROXY",DSTDEV('literature entries'!$D:$AI,IF($J18=1,"ACTIVE GHGE, FARM GATE (kg CO2e/kg)","GHGE, processor gate (kg CO2e/kg)"),INDIRECT($K18)),GETPIVOTDATA(IF($J18=1,"StdDev of ACTIVE GHGE, FARM GATE (kg CO2e/kg)","StdDev of GHGE, processor gate (kg CO2e/kg)"),'Pivot Table_GHG'!$A$3,"SUB TYPE",$B18)) -> #DIV/0! | W18: flours | X18: =IF($W18="DIRECT",M18,DCOUNT('literature entries'!$D:$AI,"CED, processor gate (MJ/kg)",INDIRECT($W18))) -> 9 | Y18: =IF($W18="DIRECT","",DAVERAGE('literature entries'!$D:$AI,"CED, processor gate (MJ/kg)",INDIRECT($W18))) -> 3.7933852 | Z18: =IF($W18="DIRECT",$O18,DSTDEV('literature entries'!$D:$AI,"CED, processor gate (MJ/kg)",INDIRECT($W18))) -> 1.2312612 | AA18: =IF($W18="DIRECT",$O18,$Z18/$Y18*$N18) -> 0.2028632 | AB18: flours | AC18: =IF($AB18="DIRECT",Q18,DCOUNT('literature entries'!$D:$AI,"GHGE, processor gate (kg CO2e/kg)",INDIRECT($AB18))) -> 9 | AD18: =IF($AB18="DIRECT","",DAVERAGE('literature entries'!$D:$AI,"GHGE, processor gate (kg CO2e/kg)",INDIRECT($AB18))) -> 0.43042331 | AE18: =IF($AB18="DIRECT",$S18,DSTDEV('literature entries'!$D:$AI,"GHGE, processor gate (kg CO2e/kg)",INDIRECT($AB18))) -> 0.072682317 | AF18: =IF($AB18="DIRECT",$S18,$AE18/$AD18*$R18) -> 0.013306358
A19: 103017000 | B19: Artichoke, Jerusalem | C19: edible portion of tuber | E19: 1 | F19: =N19*H19+T19 -> 4.028125 | G19: =R19*H19+U19 -> 0.54352941 | H19: 2.5 | I19: FICRCD | J19: 1 | K19: potato | L19: =IF(ISERROR(GETPIVOTDATA(IF($J19=1,"Count of ACTIVE CED, FARM GATE (MJ/kg)","Count of CED, processor gate (MJ/kg)"),'Pivot Table_CED'!$A$3,"SUB TYPE",$B19)),"PROXY",IF(GETPIVOTDATA(IF($J19=1,"Count of ACTIVE CED, FARM GATE (MJ/kg)","Count of CED, processor gate (MJ/kg)"),'Pivot Table_CED'!$A$3,"SUB TYPE",$B19)=0,"PROXY","DB value")) -> PROXY | M19: =IF($L19="PROXY",DCOUNT('literature entries'!$D:$AI,IF($J19=1,"ACTIVE CED, FARM GATE (MJ/kg)","CED, processor gate (MJ/kg)"),INDIRECT($K19)),GETPIVOTDATA(IF($J19=1,"Count of ACTIVE CED, FARM GATE (MJ/kg)","Count of CED, processor gate (MJ/kg)"),'Pivot Table_CED'!$A$3,"SUB TYPE",$B19)) -> 8 | N19: =IF($L19="PROXY",DAVERAGE('literature entries'!$D:$AI,IF($J19=1,"ACTIVE CED, FARM GATE (MJ/kg)","CED, processor gate (MJ/kg)"),INDIRECT($K19)),GETPIVOTDATA(IF($J19=1,"Average of ACTIVE CED, FARM GATE (MJ/kg)","Average of CED, processor gate (MJ/kg)"),'Pivot Table_CED'!$A$3,"SUB TYPE",$B19)) -> 1.61125 | O19: =IF($L19="PROXY",DSTDEV('literature entries'!D:AI,IF($J19=1,"ACTIVE CED, FARM GATE (MJ/kg)","CED, processor gate (MJ/kg)"),INDIRECT($K19)),GETPIVOTDATA(IF($J19=1,"StdDev of ACTIVE CED, FARM GATE (MJ/kg)","StdDev of CED, processor gate (MJ/kg)"),'Pivot Table_CED'!$A$3,"SUB TYPE",$B19)) -> 0.53279418 | P19: =IF(ISERROR(GETPIVOTDATA(IF($J19=1,"Count of ACTIVE GHGE, FARM GATE (kg CO2e/kg)","Count of GHGE, processor gate (kg CO2e/kg)"),'Pivot Table_GHG'!$A$3,"SUB TYPE",$B19)),"PROXY",IF(GETPIVOTDATA(IF($J19=1,"Count of ACTIVE GHGE, FARM GATE (kg CO2e/kg)","Count of GHGE, processor gate (kg CO2e/kg)"),'Pivot Table_GHG'!$A$3,"SUB TYPE",$B19)=0,"PROXY","DB value")) -> PROXY | Q19: =IF($P19="PROXY",DCOUNT('literature entries'!$D:$AI,IF($J19=1,"ACTIVE GHGE, FARM GATE (kg CO2e/kg)","GHGE, processor gate (kg CO2e/kg)"),INDIRECT($K19)),GETPIVOTDATA(IF($J19=1,"ACTIVE GHGE, FARM GATE (kg CO2e/kg)","Count of GHGE, processor gate (kg CO2e/kg)"),'Pivot Table_GHG'!$A$3,"SUB TYPE",$B19)) -> 17 | R19: =IF($P19="PROXY",DAVERAGE('literature entries'!$D:$AI,IF($J19=1,"ACTIVE GHGE, FARM GATE (kg CO2e/kg)","GHGE, processor gate (kg CO2e/kg)"),INDIRECT($K19)),GETPIVOTDATA(IF($J19=1,"Average of ACTIVE GHGE, FARM GATE (kg CO2e/kg)","Average of GHGE, processor gate (kg CO2e/kg)"),'Pivot Table_GHG'!$A$3,"SUB TYPE",$B19)) -> 0.21741176 | S19: =IF($P19="PROXY",DSTDEV('literature entries'!$D:$AI,IF($J19=1,"ACTIVE GHGE, FARM GATE (kg CO2e/kg)","GHGE, processor gate (kg CO2e/kg)"),INDIRECT($K19)),GETPIVOTDATA(IF($J19=1,"StdDev of ACTIVE GHGE, FARM GATE (kg CO2e/kg)","StdDev of GHGE, processor gate (kg CO2e/kg)"),'Pivot Table_GHG'!$A$3,"SUB TYPE",$B19)) -> 0.11818474 | W19: roots | X19: =IF($W19="DIRECT",M19,DCOUNT('literature entries'!$D:$AI,IF($J19=1,"ACTIVE CED, FARM GATE (MJ/kg)","CED, processor gate (MJ/kg)"),INDIRECT($W19))) -> 14 | Y19: =IF($W19="DIRECT","",DAVERAGE('literature entries'!$D:$AI,IF($J19=1,"ACTIVE CED, FARM GATE (MJ/kg)","CED, processor gate (MJ/kg)"),INDIRECT($W19))) -> 1.4220714 | Z19: =IF($W19="DIRECT",$O19,DSTDEV('literature entries'!$D:$AI,IF($J19=1,"ACTIVE CED, FARM GATE (MJ/kg)","CED, processor gate (MJ/kg)"),INDIRECT($W19))) -> 0.57442044 | AA19: =IF($W19="DIRECT",$O19,$Z19/$Y19*$N19) -> 0.65083576 | AB19: roots | AC19: =IF($AB19="DIRECT",Q19,DCOUNT('literature entries'!$D:$AI,IF($J19=1,"ACTIVE GHGE, FARM GATE (kg CO2e/kg)","GHGE, processor gate (kg CO2e/kg)"),INDIRECT($AB19))) -> 25 | AD19: =IF($AB19="DIRECT","",DAVERAGE('literature entries'!$D:$AI,IF($J19=1,"ACTIVE GHGE, FARM GATE (kg CO2e/kg)","GHGE, processor gate (kg CO2e/kg)"),INDIRECT($AB19))) -> 0.2134 | AE19: =IF($AB19="DIRECT",$S19,DSTDEV('literature entries'!$D:$AI,IF($J19=1,"ACTIVE GHGE, FARM GATE (kg CO2e/kg)","GHGE, processor gate (kg CO2e/kg)"),INDIRECT($AB19))) -> 0.17992035 | AF19: =IF($AB19="DIRECT",$S19,$AE19/$AD19*$R19) -> 0.18330272
A20: 103082000 | B20: Cassava | C20: weight of root; dry tapioca | D20: Includes tapioca. | E20: 26995 | F20: =N20*H20+T20 -> 0.625 | G20: =R20*H20+U20 -> 0.0788 | H20: 1 | I20: None | J20: 1 | L20: =IF(ISERROR(GETPIVOTDATA(IF($J20=1,"Count of ACTIVE CED, FARM GATE (MJ/kg)","Count of CED, processor gate (MJ/kg)"),'Pivot Table_CED'!$A$3,"SUB TYPE",$B20)),"PROXY",IF(GETPIVOTDATA(IF($J20=1,"Count of ACTIVE CED, FARM GATE (MJ/kg)","Count of CED, processor gate (MJ/kg)"),'Pivot Table_CED'!$A$3,"SUB TYPE",$B20)=0,"PROXY","DB value")) -> DB value | M20: =IF($L20="PROXY",DCOUNT('literature entries'!$D:$AI,IF($J20=1,"ACTIVE CED, FARM GATE (MJ/kg)","CED, processor gate (MJ/kg)"),INDIRECT($K20)),GETPIVOTDATA(IF($J20=1,"Count of ACTIVE CED, FARM GATE (MJ/kg)","Count of CED, processor gate (MJ/kg)"),'Pivot Table_CED'!$A$3,"SUB TYPE",$B20)) -> 1 | N20: =IF($L20="PROXY",DAVERAGE('literature entries'!$D:$AI,IF($J20=1,"ACTIVE CED, FARM GATE (MJ/kg)","CED, processor gate (MJ/kg)"),INDIRECT($K20)),GETPIVOTDATA(IF($J20=1,"Average of ACTIVE CED, FARM GATE (MJ/kg)","Average of CED, processor gate (MJ/kg)"),'Pivot Table_CED'!$A$3,"SUB TYPE",$B20)) -> 0.625 | O20: =IF($L20="PROXY",DSTDEV('literature entries'!D:AI,IF($J20=1,"ACTIVE CED, FARM GATE (MJ/kg)","CED, processor gate (MJ/kg)"),INDIRECT($K20)),GETPIVOTDATA(IF($J20=1,"StdDev of ACTIVE CED, FARM GATE (MJ/kg)","StdDev of CED, processor gate (MJ/kg)"),'Pivot Table_CED'!$A$3,"SUB TYPE",$B20)) -> 0 | P20: =IF(ISERROR(GETPIVOTDATA(IF($J20=1,"Count of ACTIVE GHGE, FARM GATE (kg CO2e/kg)","Count of GHGE, processor gate (kg CO2e/kg)"),'Pivot Table_GHG'!$A$3,"SUB TYPE",$B20)),"PROXY",IF(GETPIVOTDATA(IF($J20=1,"Count of ACTIVE GHGE, FARM GATE (kg CO2e/kg)","Count of GHGE, processor gate (kg CO2e/kg)"),'Pivot Table_GHG'!$A$3,"SUB TYPE",$B20)=0,"PROXY","DB value")) -> DB value | Q20: =IF($P20="PROXY",DCOUNT('literature entries'!$D:$AI,IF($J20=1,"ACTIVE GHGE, FARM GATE (kg CO2e/kg)","GHGE, processor gate (kg CO2e/kg)"),INDIRECT($K20)),GETPIVOTDATA(IF($J20=1,"ACTIVE GHGE, FARM GATE (kg CO2e/kg)","Count of GHGE, processor gate (kg CO2e/kg)"),'Pivot Table_GHG'!$A$3,"SUB TYPE",$B20)) -> 1 | R20: =IF($P20="PROXY",DAVERAGE('literature entries'!$D:$AI,IF($J20=1,"ACTIVE GHGE, FARM GATE (kg CO2e/kg)","GHGE, processor gate (kg CO2e/kg)"),INDIRECT($K20)),GETPIVOTDATA(IF($J20=1,"Average of ACTIVE GHGE, FARM GATE (kg CO2e/kg)","Average of GHGE, processor gate (kg CO2e/kg)"),'Pivot Table_GHG'!$A$3,"SUB TYPE",$B20)) -> 0.0788 | S20: =IF($P20="PROXY",DSTDEV('literature entries'!$D:$AI,IF($J20=1,"ACTIVE GHGE, FARM GATE (kg CO2e/kg)","GHGE, processor gate (kg CO2e/kg)"),INDIRECT($K20)),GETPIVOTDATA(IF($J20=1,"StdDev of ACTIVE GHGE, FARM GATE (kg CO2e/kg)","StdDev of GHGE, processor gate (kg CO2e/kg)"),'Pivot Table_GHG'!$A$3,"SUB TYPE",$B20)) -> #DIV/0! | W20: roots | X20: =IF($W20="DIRECT",M20,DCOUNT('literature entries'!$D:$AI,IF($J20=1,"ACTIVE CED, FARM GATE (MJ/kg)","CED, processor gate (MJ/kg)"),INDIRECT($W20))) -> 14 | Y20: =IF($W20="DIRECT","",DAVERAGE('literature entries'!$D:$AI,IF($J20=1,"ACTIVE CED, FARM GATE (MJ/kg)","CED, processor gate (MJ/kg)"),INDIRECT($W20))) -> 1.4220714 | Z20: =IF($W20="DIRECT",$O20,DSTDEV('literature entries'!$D:$AI,IF($J20=1,"ACTIVE CED, FARM GATE (MJ/kg)","CED, processor gate (MJ/kg)"),INDIRECT($W20))) -> 0.57442044 | AA20: =IF($W20="DIRECT",$O20,$Z20/$Y20*$N20) -> 0.25245762 | AB20: roots | AC20: =IF($AB20="DIRECT",Q20,DCOUNT('literature entries'!$D:$AI,IF($J20=1,"ACTIVE GHGE, FARM GATE (kg CO2e/kg)","GHGE, processor gate (kg CO2e/kg)"),INDIRECT($AB20))) -> 25 | AD20: =IF($AB20="DIRECT","",DAVERAGE('literature entries'!$D:$AI,IF($J20=1,"ACTIVE GHGE, FARM GATE (kg CO2e/kg)","GHGE, processor gate (kg CO2e/kg)"),INDIRECT($AB20))) -> 0.2134 | AE20: =IF($AB20="DIRECT",$S20,DSTDEV('literature entries'!$D:$AI,IF($J20=1,"ACTIVE GHGE, FARM GATE (kg CO2e/kg)","GHGE, processor gate (kg CO2e/kg)"),INDIRECT($AB20))) -> 0.17992035 | AF20: =IF($AB20="DIRECT",$S20,$AE20/$AD20*$R20) -> 0.066437319
A21: 103139000 | B21: Dasheen, corm | C21: weight of the corm | D21: Includes taro. | E21: 68 | F21: =N21*H21+T21 -> 1.4220714 | G21: =R21*H21+U21 -> 0.2134 | H21: 1 | I21: None | J21: 1 | K21: roots | L21: =IF(ISERROR(GETPIVOTDATA(IF($J21=1,"Count of ACTIVE CED, FARM GATE (MJ/kg)","Count of CED, processor gate (MJ/kg)"),'Pivot Table_CED'!$A$3,"SUB TYPE",$B21)),"PROXY",IF(GETPIVOTDATA(IF($J21=1,"Count of ACTIVE CED, FARM GATE (MJ/kg)","Count of CED, processor gate (MJ/kg)"),'Pivot Table_CED'!$A$3,"SUB TYPE",$B21)=0,"PROXY","DB value")) -> PROXY | M21: =IF($L21="PROXY",DCOUNT('literature entries'!$D:$AI,IF($J21=1,"ACTIVE CED, FARM GATE (MJ/kg)","CED, processor gate (MJ/kg)"),INDIRECT($K21)),GETPIVOTDATA(IF($J21=1,"Count of ACTIVE CED, FARM GATE (MJ/kg)","Count of CED, processor gate (MJ/kg)"),'Pivot Table_CED'!$A$3,"SUB TYPE",$B21)) -> 14 | N21: =IF($L21="PROXY",DAVERAGE('literature entries'!$D:$AI,IF($J21=1,"ACTIVE CED, FARM GATE (MJ/kg)","CED, processor gate (MJ/kg)"),INDIRECT($K21)),GETPIVOTDATA(IF($J21=1,"Average of ACTIVE CED, FARM GATE (MJ/kg)","Average of CED, processor gate (MJ/kg)"),'Pivot Table_CED'!$A$3,"SUB TYPE",$B21)) -> 1.4220714 | O21: =IF($L21="PROXY",DSTDEV('literature entries'!D:AI,IF($J21=1,"ACTIVE CED, FARM GATE (MJ/kg)","CED, processor gate (MJ/kg)"),INDIRECT($K21)),GETPIVOTDATA(IF($J21=1,"StdDev of ACTIVE CED, FARM GATE (MJ/kg)","StdDev of CED, processor gate (MJ/kg)"),'Pivot Table_CED'!$A$3,"SUB TYPE",$B21)) -> 0.57442044 | P21: =IF(ISERROR(GETPIVOTDATA(IF($J21=1,"Count of ACTIVE GHGE, FARM GATE (kg CO2e/kg)","Count of GHGE, processor gate (kg CO2e/kg)"),'Pivot Table_GHG'!$A$3,"SUB TYPE",$B21)),"PROXY",IF(GETPIVOTDATA(IF($J21=1,"Count of ACTIVE GHGE, FARM GATE (kg CO2e/kg)","Count of GHGE, processor gate (kg CO2e/kg)"),'Pivot Table_GHG'!$A$3,"SUB TYPE",$B21)=0,"PROXY","DB value")) -> PROXY | Q21: =IF($P21="PROXY",DCOUNT('literature entries'!$D:$AI,IF($J21=1,"ACTIVE GHGE, FARM GATE (kg CO2e/kg)","GHGE, processor gate (kg CO2e/kg)"),INDIRECT($K21)),GETPIVOTDATA(IF($J21=1,"ACTIVE GHGE, FARM GATE (kg CO2e/kg)","Count of GHGE, processor gate (kg CO2e/kg)"),'Pivot Table_GHG'!$A$3,"SUB TYPE",$B21)) -> 25 | R21: =IF($P21="PROXY",DAVERAGE('literature entries'!$D:$AI,IF($J21=1,"ACTIVE GHGE, FARM GATE (kg CO2e/kg)","GHGE, processor gate (kg CO2e/kg)"),INDIRECT($K21)),GETPIVOTDATA(IF($J21=1,"Average of ACTIVE GHGE, FARM GATE (kg CO2e/kg)","Average of GHGE, processor gate (kg CO2e/kg)"),'Pivot Table_GHG'!$A$3,"SUB TYPE",$B21)) -> 0.2134 | S21: =IF($P21="PROXY",DSTDEV('literature entries'!$D:$AI,IF($J21=1,"ACTIVE GHGE, FARM GATE (kg CO2e/kg)","GHGE, processor gate (kg CO2e/kg)"),INDIRECT($K21)),GETPIVOTDATA(IF($J21=1,"StdDev of ACTIVE GHGE, FARM GATE (kg CO2e/kg)","StdDev of GHGE, processor gate (kg CO2e/kg)"),'Pivot Table_GHG'!$A$3,"SUB TYPE",$B21)) -> 0.17992035 | W21: =IF(L21="PROXY",IF(M21>=5,K21,"need group"),IF(M21>=5,"DIRECT","need group")) -> roots | X21: =IF($W21="DIRECT",M21,DCOUNT('literature entries'!$D:$AI,IF($J21=1,"ACTIVE CED, FARM GATE (MJ/kg)","CED, processor gate (MJ/kg)"),INDIRECT($W21))) -> 14 | Y21: =IF($W21="DIRECT","",DAVERAGE('literature entries'!$D:$AI,IF($J21=1,"ACTIVE CED, FARM GATE (MJ/kg)","CED, processor gate (MJ/kg)"),INDIRECT($W21))) -> 1.4220714 | Z21: =IF($W21="DIRECT",$O21,DSTDEV('literature entries'!$D:$AI,IF($J21=1,"ACTIVE CED, FARM GATE (MJ/kg)","CED, processor gate (MJ/kg)"),INDIRECT($W21))) -> 0.57442044 | AA21: =IF($W21="DIRECT",$O21,$Z21/$Y21*$N21) -> 0.57442044 | AB21: =IF(P21="PROXY",IF(Q21>=5,K21,"need group"),IF(Q21>=5,"DIRECT","need group")) -> roots | AC21: =IF($AB21="DIRECT",Q21,DCOUNT('literature entries'!$D:$AI,IF($J21=1,"ACTIVE GHGE, FARM GATE (kg CO2e/kg)","GHGE, processor gate (kg CO2e/kg)"),INDIRECT($AB21))) -> 25 | AD21: =IF($AB21="DIRECT","",DAVERAGE('literature entries'!$D:$AI,IF($J21=1,"ACTIVE GHGE, FARM GATE (kg CO2e/kg)","GHGE, processor gate (kg CO2e/kg)"),INDIRECT($AB21))) -> 0.2134 | AE21: =IF($AB21="DIRECT",$S21,DSTDEV('literature entries'!$D:$AI,IF($J21=1,"ACTIVE GHGE, FARM GATE (kg CO2e/kg)","GHGE, processor gate (kg CO2e/kg)"),INDIRECT($AB21))) -> 0.17992035 | AF21: =IF($AB21="DIRECT",$S21,$AE21/$AD21*$R21) -> 0.17992035
A22: 103166000 | B22: Ginger | C22: weight of roots; excluding peel | E22: 4399 | F22: =N22*H22+T22 -> 1.5358371 | G22: =R22*H22+U22 -> 0.9504 | H22: 1.08 | I22: NNDSR28 | J22: 1 | K22: roots | L22: =IF(ISERROR(GETPIVOTDATA(IF($J22=1,"Count of ACTIVE CED, FARM GATE (MJ/kg)","Count of CED, processor gate (MJ/kg)"),'Pivot Table_CED'!$A$3,"SUB TYPE",$B22)),"PROXY",IF(GETPIVOTDATA(IF($J22=1,"Count of ACTIVE CED, FARM GATE (MJ/kg)","Count of CED, processor gate (MJ/kg)"),'Pivot Table_CED'!$A$3,"SUB TYPE",$B22)=0,"PROXY","DB value")) -> PROXY | M22: =IF($L22="PROXY",DCOUNT('literature entries'!$D:$AI,IF($J22=1,"ACTIVE CED, FARM GATE (MJ/kg)","CED, processor gate (MJ/kg)"),INDIRECT($K22)),GETPIVOTDATA(IF($J22=1,"Count of ACTIVE CED, FARM GATE (MJ/kg)","Count of CED, processor gate (MJ/kg)"),'Pivot Table_CED'!$A$3,"SUB TYPE",$B22)) -> 14 | N22: =IF($L22="PROXY",DAVERAGE('literature entries'!$D:$AI,IF($J22=1,"ACTIVE CED, FARM GATE (MJ/kg)","CED, processor gate (MJ/kg)"),INDIRECT($K22)),GETPIVOTDATA(IF($J22=1,"Average of ACTIVE CED, FARM GATE (MJ/kg)","Average of CED, processor gate (MJ/kg)"),'Pivot Table_CED'!$A$3,"SUB TYPE",$B22)) -> 1.4220714 | O22: =IF($L22="PROXY",DSTDEV('literature entries'!D:AI,IF($J22=1,"ACTIVE CED, FARM GATE (MJ/kg)","CED, processor gate (MJ/kg)"),INDIRECT($K22)),GETPIVOTDATA(IF($J22=1,"StdDev of ACTIVE CED, FARM GATE (MJ/kg)","StdDev of CED, processor gate (MJ/kg)"),'Pivot Table_CED'!$A$3,"SUB TYPE",$B22)) -> 0.57442044 | P22: =IF(ISERROR(GETPIVOTDATA(IF($J22=1,"Count of ACTIVE GHGE, FARM GATE (kg CO2e/kg)","Count of GHGE, processor gate (kg CO2e/kg)"),'Pivot Table_GHG'!$A$3,"SUB TYPE",$B22)),"PROXY",IF(GETPIVOTDATA(IF($J22=1,"Count of ACTIVE GHGE, FARM GATE (kg CO2e/kg)","Count of GHGE, processor gate (kg CO2e/kg)"),'Pivot Table_GHG'!$A$3,"SUB TYPE",$B22)=0,"PROXY","DB value")) -> DB value | Q22: =IF($P22="PROXY",DCOUNT('literature entries'!$D:$AI,IF($J22=1,"ACTIVE GHGE, FARM GATE (kg CO2e/kg)","GHGE, processor gate (kg CO2e/kg)"),INDIRECT($K22)),GETPIVOTDATA(IF($J22=1,"ACTIVE GHGE, FARM GATE (kg CO2e/kg)","Count of GHGE, processor gate (kg CO2e/kg)"),'Pivot Table_GHG'!$A$3,"SUB TYPE",$B22)) -> 1 | R22: =IF($P22="PROXY",DAVERAGE('literature entries'!$D:$AI,IF($J22=1,"ACTIVE GHGE, FARM GATE (kg CO2e/kg)","GHGE, processor gate (kg CO2e/kg)"),INDIRECT($K22)),GETPIVOTDATA(IF($J22=1,"Average of ACTIVE GHGE, FARM GATE (kg CO2e/kg)","Average of GHGE, processor gate (kg CO2e/kg)"),'Pivot Table_GHG'!$A$3,"SUB TYPE",$B22)) -> 0.88 | S22: =IF($P22="PROXY",DSTDEV('literature entries'!$D:$AI,IF($J22=1,"ACTIVE GHGE, FARM GATE (kg CO2e/kg)","GHGE, processor gate (kg CO2e/kg)"),INDIRECT($K22)),GETPIVOTDATA(IF($J22=1,"StdDev of ACTIVE GHGE, FARM GATE (kg CO2e/kg)","StdDev of GHGE, processor gate (kg CO2e/kg)"),'Pivot Table_GHG'!$A$3,"SUB TYPE",$B22)) -> #DIV/0! | W22: =IF(L22="PROXY",IF(M22>=5,K22,"need group"),IF(M22>=5,"DIRECT","need group")) -> roots | X22: =IF($W22="DIRECT",M22,DCOUNT('literature entries'!$D:$AI,IF($J22=1,"ACTIVE CED, FARM GATE (MJ/kg)","CED, processor gate (MJ/kg)"),INDIRECT($W22))) -> 14 | Y22: =IF($W22="DIRECT","",DAVERAGE('literature entries'!$D:$AI,IF($J22=1,"ACTIVE CED, FARM GATE (MJ/kg)","CED, processor gate (MJ/kg)"),INDIRECT($W22))) -> 1.4220714 | Z22: =IF($W22="DIRECT",$O22,DSTDEV('literature entries'!$D:$AI,IF($J22=1,"ACTIVE CED, FARM GATE (MJ/kg)","CED, processor gate (MJ/kg)"),INDIRECT($W22))) -> 0.57442044 | AA22: =IF($W22="DIRECT",$O22,$Z22/$Y22*$N22) -> 0.57442044 | AB22: roots | AC22: =IF($AB22="DIRECT",Q22,DCOUNT('literature entries'!$D:$AI,IF($J22=1,"ACTIVE GHGE, FARM GATE (kg CO2e/kg)","GHGE, processor gate (kg CO2e/kg)"),INDIRECT($AB22))) -> 25 | AD22: =IF($AB22="DIRECT","",DAVERAGE('literature entries'!$D:$AI,IF($J22=1,"ACTIVE GHGE, FARM GATE (kg CO2e/kg)","GHGE, processor gate (kg CO2e/kg)"),INDIRECT($AB22))) -> 0.2134 | AE22: =IF($AB22="DIRECT",$S22,DSTDEV('literature entries'!$D:$AI,IF($J22=1,"ACTIVE GHGE, FARM GATE (kg CO2e/kg)","GHGE, processor gate (kg CO2e/kg)"),INDIRECT($AB22))) -> 0.17992035 | AF22: =IF($AB22="DIRECT",$S22,$AE22/$AD22*$R22) -> 0.7419396
A23: 103167000 | B23: Ginger, dried | C23: dry weight of roots; excluding peel | E23: 19546 | F23: =N23*H23+T23 -> 6.5130871 | G23: =R23*H23+U23 -> 0.977372 | H23: 4.58 | I23: NNDSR28 | J23: 1 | K23: roots | L23: =IF(ISERROR(GETPIVOTDATA(IF($J23=1,"Count of ACTIVE CED, FARM GATE (MJ/kg)","Count of CED, processor gate (MJ/kg)"),'Pivot Table_CED'!$A$3,"SUB TYPE",$B23)),"PROXY",IF(GETPIVOTDATA(IF($J23=1,"Count of ACTIVE CED, FARM GATE (MJ/kg)","Count of CED, processor gate (MJ/kg)"),'Pivot Table_CED'!$A$3,"SUB TYPE",$B23)=0,"PROXY","DB value")) -> PROXY | M23: =IF($L23="PROXY",DCOUNT('literature entries'!$D:$AI,IF($J23=1,"ACTIVE CED, FARM GATE (MJ/kg)","CED, processor gate (MJ/kg)"),INDIRECT($K23)),GETPIVOTDATA(IF($J23=1,"Count of ACTIVE CED, FARM GATE (MJ/kg)","Count of CED, processor gate (MJ/kg)"),'Pivot Table_CED'!$A$3,"SUB TYPE",$B23)) -> 14 | N23: =IF($L23="PROXY",DAVERAGE('literature entries'!$D:$AI,IF($J23=1,"ACTIVE CED, FARM GATE (MJ/kg)","CED, processor gate (MJ/kg)"),INDIRECT($K23)),GETPIVOTDATA(IF($J23=1,"Average of ACTIVE CED, FARM GATE (MJ/kg)","Average of CED, processor gate (MJ/kg)"),'Pivot Table_CED'!$A$3,"SUB TYPE",$B23)) -> 1.4220714 | O23: =IF($L23="PROXY",DSTDEV('literature entries'!D:AI,IF($J23=1,"ACTIVE CED, FARM GATE (MJ/kg)","CED, processor gate (MJ/kg)"),INDIRECT($K23)),GETPIVOTDATA(IF($J23=1,"StdDev of ACTIVE CED, FARM GATE (MJ/kg)","StdDev of CED, processor gate (MJ/kg)"),'Pivot Table_CED'!$A$3,"SUB TYPE",$B23)) -> 0.57442044 | P23: =IF(ISERROR(GETPIVOTDATA(IF($J23=1,"Count of ACTIVE GHGE, FARM GATE (kg CO2e/kg)","Count of GHGE, processor gate (kg CO2e/kg)"),'Pivot Table_GHG'!$A$3,"SUB TYPE",$B23)),"PROXY",IF(GETPIVOTDATA(IF($J23=1,"Count of ACTIVE GHGE, FARM GATE (kg CO2e/kg)","Count of GHGE, processor gate (kg CO2e/kg)"),'Pivot Table_GHG'!$A$3,"SUB TYPE",$B23)=0,"PROXY","DB value")) -> PROXY | Q23: =IF($P23="PROXY",DCOUNT('literature entries'!$D:$AI,IF($J23=1,"ACTIVE GHGE, FARM GATE (kg CO2e/kg)","GHGE, processor gate (kg CO2e/kg)"),INDIRECT($K23)),GETPIVOTDATA(IF($J23=1,"ACTIVE GHGE, FARM GATE (kg CO2e/kg)","Count of GHGE, processor gate (kg CO2e/kg)"),'Pivot Table_GHG'!$A$3,"SUB TYPE",$B23)) -> 25 | R23: =IF($P23="PROXY",DAVERAGE('literature entries'!$D:$AI,IF($J23=1,"ACTIVE GHGE, FARM GATE (kg CO2e/kg)","GHGE, processor gate (kg CO2e/kg)"),INDIRECT($K23)),GETPIVOTDATA(IF($J23=1,"Average of ACTIVE GHGE, FARM GATE (kg CO2e/kg)","Average of GHGE, processor gate (kg CO2e/kg)"),'Pivot Table_GHG'!$A$3,"SUB TYPE",$B23)) -> 0.2134 | S23: =IF($P23="PROXY",DSTDEV('literature entries'!$D:$AI,IF($J23=1,"ACTIVE GHGE, FARM GATE (kg CO2e/kg)","GHGE, processor gate (kg CO2e/kg)"),INDIRECT($K23)),GETPIVOTDATA(IF($J23=1,"StdDev of ACTIVE GHGE, FARM GATE (kg CO2e/kg)","StdDev of GHGE, processor gate (kg CO2e/kg)"),'Pivot Table_GHG'!$A$3,"SUB TYPE",$B23)) -> 0.17992035 | W23: =IF(L23="PROXY",IF(M23>=5,K23,"need group"),IF(M23>=5,"DIRECT","need group")) -> roots | X23: =IF($W23="DIRECT",M23,DCOUNT('literature entries'!$D:$AI,IF($J23=1,"ACTIVE CED, FARM GATE (MJ/kg)","CED, processor gate (MJ/kg)"),INDIRECT($W23))) -> 14 | Y23: =IF($W23="DIRECT","",DAVERAGE('literature entries'!$D:$AI,IF($J23=1,"ACTIVE CED, FARM GATE (MJ/kg)","CED, processor gate (MJ/kg)"),INDIRECT($W23))) -> 1.4220714 | Z23: =IF($W23="DIRECT",$O23,DSTDEV('literature entries'!$D:$AI,IF($J23=1,"ACTIVE CED, FARM GATE (MJ/kg)","CED, processor gate (MJ/kg)"),INDIRECT($W23))) -> 0.57442044 | AA23: =IF($W23="DIRECT",$O23,$Z23/$Y23*$N23) -> 0.57442044 | AB23: =IF(P23="PROXY",IF(Q23>=5,K23,"need group"),IF(Q23>=5,"DIRECT","need group")) -> roots | AC23: =IF($AB23="DIRECT",Q23,DCOUNT('literature entries'!$D:$AI,IF($J23=1,"ACTIVE GHGE, FARM GATE (kg CO2e/kg)","GHGE, processor gate (kg CO2e/kg)"),INDIRECT($AB23))) -> 25 | AD23: =IF($AB23="DIRECT","",DAVERAGE('literature entries'!$D:$AI,IF($J23=1,"ACTIVE GHGE, FARM GATE (kg CO2e/kg)","GHGE, processor gate (kg CO2e/kg)"),INDIRECT($AB23))) -> 0.2134 | AE23: =IF($AB23="DIRECT",$S23,DSTDEV('literature entries'!$D:$AI,IF($J23=1,"ACTIVE GHGE, FARM GATE (kg CO2e/kg)","GHGE, processor gate (kg CO2e/kg)"),INDIRECT($AB23))) -> 0.17992035 | AF23: =IF($AB23="DIRECT",$S23,$AE23/$AD23*$R23) -> 0.17992035
A24: 103296000 | B24: Potato, chips | C24: weight of potato from chip or stick, with or without peel | E24: 5284 | F24: =N24*H24+T24 -> 19.75 | G24: =R24*H24+U24 -> 1.545 | H24: 1 | I24: none | J24: 2 | L24: =IF(ISERROR(GETPIVOTDATA(IF($J24=1,"Count of ACTIVE CED, FARM GATE (MJ/kg)","Count of CED, processor gate (MJ/kg)"),'Pivot Table_CED'!$A$3,"SUB TYPE",$B24)),"PROXY",IF(GETPIVOTDATA(IF($J24=1,"Count of ACTIVE CED, FARM GATE (MJ/kg)","Count of CED, processor gate (MJ/kg)"),'Pivot Table_CED'!$A$3,"SUB TYPE",$B24)=0,"PROXY","DB value")) -> DB value | M24: =IF($L24="PROXY",DCOUNT('literature entries'!$D:$AI,IF($J24=1,"ACTIVE CED, FARM GATE (MJ/kg)","CED, processor gate (MJ/kg)"),INDIRECT($K24)),GETPIVOTDATA(IF($J24=1,"Count of ACTIVE CED, FARM GATE (MJ/kg)","Count of CED, processor gate (MJ/kg)"),'Pivot Table_CED'!$A$3,"SUB TYPE",$B24)) -> 1 | N24: =IF($L24="PROXY",DAVERAGE('literature entries'!$D:$AI,IF($J24=1,"ACTIVE CED, FARM GATE (MJ/kg)","CED, processor gate (MJ/kg)"),INDIRECT($K24)),GETPIVOTDATA(IF($J24=1,"Average of ACTIVE CED, FARM GATE (MJ/kg)","Average of CED, processor gate (MJ/kg)"),'Pivot Table_CED'!$A$3,"SUB TYPE",$B24)) -> 19.75 | O24: =IF($L24="PROXY",DSTDEV('literature entries'!D:AI,IF($J24=1,"ACTIVE CED, FARM GATE (MJ/kg)","CED, processor gate (MJ/kg)"),INDIRECT($K24)),GETPIVOTDATA(IF($J24=1,"StdDev of ACTIVE CED, FARM GATE (MJ/kg)","StdDev of CED, processor gate (MJ/kg)"),'Pivot Table_CED'!$A$3,"SUB TYPE",$B24)) -> 0 | P24: =IF(ISERROR(GETPIVOTDATA(IF($J24=1,"Count of ACTIVE GHGE, FARM GATE (kg CO2e/kg)","Count of GHGE, processor gate (kg CO2e/kg)"),'Pivot Table_GHG'!$A$3,"SUB TYPE",$B24)),"PROXY",IF(GETPIVOTDATA(IF($J24=1,"Count of ACTIVE GHGE, FARM GATE (kg CO2e/kg)","Count of GHGE, processor gate (kg CO2e/kg)"),'Pivot Table_GHG'!$A$3,"SUB TYPE",$B24)=0,"PROXY","DB value")) -> DB value | Q24: =IF($P24="PROXY",DCOUNT('literature entries'!$D:$AI,IF($J24=1,"ACTIVE GHGE, FARM GATE (kg CO2e/kg)","GHGE, processor gate (kg CO2e/kg)"),INDIRECT($K24)),GETPIVOTDATA(IF($J24=1,"ACTIVE GHGE, FARM GATE (kg CO2e/kg)","Count of GHGE, processor gate (kg CO2e/kg)"),'Pivot Table_GHG'!$A$3,"SUB TYPE",$B24)) -> 3 | R24: =IF($P24="PROXY",DAVERAGE('literature entries'!$D:$AI,IF($J24=1,"ACTIVE GHGE, FARM GATE (kg CO2e/kg)","GHGE, processor gate (kg CO2e/kg)"),INDIRECT($K24)),GETPIVOTDATA(IF($J24=1,"Average of ACTIVE GHGE, FARM GATE (kg CO2e/kg)","Average of GHGE, processor gate (kg CO2e/kg)"),'Pivot Table_GHG'!$A$3,"SUB TYPE",$B24)) -> 1.545 | S24: =IF($P24="PROXY",DSTDEV('literature entries'!$D:$AI,IF($J24=1,"ACTIVE GHGE, FARM GATE (kg CO2e/kg)","GHGE, processor gate (kg CO2e/kg)"),INDIRECT($K24)),GETPIVOTDATA(IF($J24=1,"StdDev of ACTIVE GHGE, FARM GATE (kg CO2e/kg)","StdDev of GHGE, processor gate (kg CO2e/kg)"),'Pivot Table_GHG'!$A$3,"SUB TYPE",$B24)) -> 0.54883969 | W24: roots | X24: =IF($W24="DIRECT",M24,DCOUNT('literature entries'!$D:$AI,"ACTIVE CED, FARM GATE (MJ/kg)",INDIRECT($W24))) -> 14 | Y24: =IF($W24="DIRECT","",DAVERAGE('literature entries'!$D:$AI,"ACTIVE CED, FARM GATE (MJ/kg)",INDIRECT($W24))) -> 1.4220714 | Z24: =IF($W24="DIRECT",$O24,DSTDEV('literature entries'!$D:$AI,"ACTIVE CED, FARM GATE (MJ/kg)",INDIRECT($W24))) -> 0.57442044 | AA24: =IF($W24="DIRECT",$O24,$Z24/$Y24*$N24) -> 7.9776609 | AB24: potato | AC24: =IF($AB24="DIRECT",Q24,DCOUNT('literature entries'!$D:$AI,"ACTIVE GHGE, FARM GATE (kg CO2e/kg)",INDIRECT($AB24))) -> 17 | AD24: =IF($AB24="DIRECT","",DAVERAGE('literature entries'!$D:$AI,"ACTIVE GHGE, FARM GATE (kg CO2e/kg)",INDIRECT($AB24))) -> 0.21741176 | AE24: =IF($AB24="DIRECT",$S24,DSTDEV('literature entries'!$D:$AI,"ACTIVE GHGE, FARM GATE (kg CO2e/kg)",INDIRECT($AB24))) -> 0.11818474 | AF24: =IF($AB24="DIRECT",$S24,$AE24/$AD24*$R24) -> 0.83985989
A25: 103297000 | B25: Potato, dry (granules/ flakes) | C25: dry weight of granules or flakes | E25: 2131 | F25: =N25*H25+T25 -> 9.699725 | G25: =R25*H25+U25 -> 1.3088188 | H25: 6.02 | I25: FICRCD | J25: 1 | K25: potato | L25: =IF(ISERROR(GETPIVOTDATA(IF($J25=1,"Count of ACTIVE CED, FARM GATE (MJ/kg)","Count of CED, processor gate (MJ/kg)"),'Pivot Table_CED'!$A$3,"SUB TYPE",$B25)),"PROXY",IF(GETPIVOTDATA(IF($J25=1,"Count of ACTIVE CED, FARM GATE (MJ/kg)","Count of CED, processor gate (MJ/kg)"),'Pivot Table_CED'!$A$3,"SUB TYPE",$B25)=0,"PROXY","DB value")) -> PROXY | M25: =IF($L25="PROXY",DCOUNT('literature entries'!$D:$AI,IF($J25=1,"ACTIVE CED, FARM GATE (MJ/kg)","CED, processor gate (MJ/kg)"),INDIRECT($K25)),GETPIVOTDATA(IF($J25=1,"Count of ACTIVE CED, FARM GATE (MJ/kg)","Count of CED, processor gate (MJ/kg)"),'Pivot Table_CED'!$A$3,"SUB TYPE",$B25)) -> 8 | N25: =IF($L25="PROXY",DAVERAGE('literature entries'!$D:$AI,IF($J25=1,"ACTIVE CED, FARM GATE (MJ/kg)","CED, processor gate (MJ/kg)"),INDIRECT($K25)),GETPIVOTDATA(IF($J25=1,"Average of ACTIVE CED, FARM GATE (MJ/kg)","Average of CED, processor gate (MJ/kg)"),'Pivot Table_CED'!$A$3,"SUB TYPE",$B25)) -> 1.61125 | O25: =IF($L25="PROXY",DSTDEV('literature entries'!D:AI,IF($J25=1,"ACTIVE CED, FARM GATE (MJ/kg)","CED, processor gate (MJ/kg)"),INDIRECT($K25)),GETPIVOTDATA(IF($J25=1,"StdDev of ACTIVE CED, FARM GATE (MJ/kg)","StdDev of CED, processor gate (MJ/kg)"),'Pivot Table_CED'!$A$3,"SUB TYPE",$B25)) -> 0.53279418 | P25: =IF(ISERROR(GETPIVOTDATA(IF($J25=1,"Count of ACTIVE GHGE, FARM GATE (kg CO2e/kg)","Count of GHGE, processor gate (kg CO2e/kg)"),'Pivot Table_GHG'!$A$3,"SUB TYPE",$B25)),"PROXY",IF(GETPIVOTDATA(IF($J25=1,"Count of ACTIVE GHGE, FARM GATE (kg CO2e/kg)","Count of GHGE, processor gate (kg CO2e/kg)"),'Pivot Table_GHG'!$A$3,"SUB TYPE",$B25)=0,"PROXY","DB value")) -> PROXY | Q25: =IF($P25="PROXY",DCOUNT('literature entries'!$D:$AI,IF($J25=1,"ACTIVE GHGE, FARM GATE (kg CO2e/kg)","GHGE, processor gate (kg CO2e/kg)"),INDIRECT($K25)),GETPIVOTDATA(IF($J25=1,"ACTIVE GHGE, FARM GATE (kg CO2e/kg)","Count of GHGE, processor gate (kg CO2e/kg)"),'Pivot Table_GHG'!$A$3,"SUB TYPE",$B25)) -> 17 | R25: =IF($P25="PROXY",DAVERAGE('literature entries'!$D:$AI,IF($J25=1,"ACTIVE GHGE, FARM GATE (kg CO2e/kg)","GHGE, processor gate (kg CO2e/kg)"),INDIRECT($K25)),GETPIVOTDATA(IF($J25=1,"Average of ACTIVE GHGE, FARM GATE (kg CO2e/kg)","Average of GHGE, processor gate (kg CO2e/kg)"),'Pivot Table_GHG'!$A$3,"SUB TYPE",$B25)) -> 0.21741176 | S25: =IF($P25="PROXY",DSTDEV('literature entries'!$D:$AI,IF($J25=1,"ACTIVE GHGE, FARM GATE (kg CO2e/kg)","GHGE, processor gate (kg CO2e/kg)"),INDIRECT($K25)),GETPIVOTDATA(IF($J25=1,"StdDev of ACTIVE GHGE, FARM GATE (kg CO2e/kg)","StdDev of GHGE, processor gate (kg CO2e/kg)"),'Pivot Table_GHG'!$A$3,"SUB TYPE",$B25)) -> 0.11818474 | W25: roots | X25: =IF($W25="DIRECT",M25,DCOUNT('literature entries'!$D:$AI,IF($J25=1,"ACTIVE CED, FARM GATE (MJ/kg)","CED, processor gate (MJ/kg)"),INDIRECT($W25))) -> 14 | Y25: =IF($W25="DIRECT","",DAVERAGE('literature entries'!$D:$AI,IF($J25=1,"ACTIVE CED, FARM GATE (MJ/kg)","CED, processor gate (MJ/kg)"),INDIRECT($W25))) -> 1.4220714 | Z25: =IF($W25="DIRECT",$O25,DSTDEV('literature entries'!$D:$AI,IF($J25=1,"ACTIVE CED, FARM GATE (MJ/kg)","CED, processor gate (MJ/kg)"),INDIRECT($W25))) -> 0.57442044 | AA25: =IF($W25="DIRECT",$O25,$Z25/$Y25*$N25) -> 0.65083576 | AB25: =IF(P25="PROXY",IF(Q25>=5,K25,"need group"),IF(Q25>=5,"DIRECT","need group")) -> potato | AC25: =IF($AB25="DIRECT",Q25,DCOUNT('literature entries'!$D:$AI,IF($J25=1,"ACTIVE GHGE, FARM GATE (kg CO2e/kg)","GHGE, processor gate (kg CO2e/kg)"),INDIRECT($AB25))) -> 17 | AD25: =IF($AB25="DIRECT","",DAVERAGE('literature entries'!$D:$AI,IF($J25=1,"ACTIVE GHGE, FARM GATE (kg CO2e/kg)","GHGE, processor gate (kg CO2e/kg)"),INDIRECT($AB25))) -> 0.21741176 | AE25: =IF($AB25="DIRECT",$S25,DSTDEV('literature entries'!$D:$AI,IF($J25=1,"ACTIVE GHGE, FARM GATE (kg CO2e/kg)","GHGE, processor gate (kg CO2e/kg)"),INDIRECT($AB25))) -> 0.11818474 | AF25: =IF($AB25="DIRECT",$S25,$AE25/$AD25*$R25) -> 0.11818474
A26: 103298000 | B26: Potato, flour | C26: dry weight of flour or potato starch | E26: 27032 | F26: =N26*H26+T26 -> 6.6309645 | G26: =R26*H26+U26 -> 0.95251464 | H26: 1 | I26: none | J26: 2 | L26: =IF(ISERROR(GETPIVOTDATA(IF($J26=1,"Count of ACTIVE CED, FARM GATE (MJ/kg)","Count of CED, processor gate (MJ/kg)"),'Pivot Table_CED'!$A$3,"SUB TYPE",$B26)),"PROXY",IF(GETPIVOTDATA(IF($J26=1,"Count of ACTIVE CED, FARM GATE (MJ/kg)","Count of CED, processor gate (MJ/kg)"),'Pivot Table_CED'!$A$3,"SUB TYPE",$B26)=0,"PROXY","DB value")) -> DB value | M26: =IF($L26="PROXY",DCOUNT('literature entries'!$D:$AI,IF($J26=1,"ACTIVE CED, FARM GATE (MJ/kg)","CED, processor gate (MJ/kg)"),INDIRECT($K26)),GETPIVOTDATA(IF($J26=1,"Count of ACTIVE CED, FARM GATE (MJ/kg)","Count of CED, processor gate (MJ/kg)"),'Pivot Table_CED'!$A$3,"SUB TYPE",$B26)) -> 2 | N26: =IF($L26="PROXY",DAVERAGE('literature entries'!$D:$AI,IF($J26=1,"ACTIVE CED, FARM GATE (MJ/kg)","CED, processor gate (MJ/kg)"),INDIRECT($K26)),GETPIVOTDATA(IF($J26=1,"Average of ACTIVE CED, FARM GATE (MJ/kg)","Average of CED, processor gate (MJ/kg)"),'Pivot Table_CED'!$A$3,"SUB TYPE",$B26)) -> 6.6309645 | O26: =IF($L26="PROXY",DSTDEV('literature entries'!D:AI,IF($J26=1,"ACTIVE CED, FARM GATE (MJ/kg)","CED, processor gate (MJ/kg)"),INDIRECT($K26)),GETPIVOTDATA(IF($J26=1,"StdDev of ACTIVE CED, FARM GATE (MJ/kg)","StdDev of CED, processor gate (MJ/kg)"),'Pivot Table_CED'!$A$3,"SUB TYPE",$B26)) -> 0.21616488 | P26: =IF(ISERROR(GETPIVOTDATA(IF($J26=1,"Count of ACTIVE GHGE, FARM GATE (kg CO2e/kg)","Count of GHGE, processor gate (kg CO2e/kg)"),'Pivot Table_GHG'!$A$3,"SUB TYPE",$B26)),"PROXY",IF(GETPIVOTDATA(IF($J26=1,"Count of ACTIVE GHGE, FARM GATE (kg CO2e/kg)","Count of GHGE, processor gate (kg CO2e/kg)"),'Pivot Table_GHG'!$A$3,"SUB TYPE",$B26)=0,"PROXY","DB value")) -> DB value | Q26: =IF($P26="PROXY",DCOUNT('literature entries'!$D:$AI,IF($J26=1,"ACTIVE GHGE, FARM GATE (kg CO2e/kg)","GHGE, processor gate (kg CO2e/kg)"),INDIRECT($K26)),GETPIVOTDATA(IF($J26=1,"ACTIVE GHGE, FARM GATE (kg CO2e/kg)","Count of GHGE, processor gate (kg CO2e/kg)"),'Pivot Table_GHG'!$A$3,"SUB TYPE",$B26)) -> 2 | R26: =IF($P26="PROXY",DAVERAGE('literature entries'!$D:$AI,IF($J26=1,"ACTIVE GHGE, FARM GATE (kg CO2e/kg)","GHGE, processor gate (kg CO2e/kg)"),INDIRECT($K26)),GETPIVOTDATA(IF($J26=1,"Average of ACTIVE GHGE, FARM GATE (kg CO2e/kg)","Average of GHGE, processor gate (kg CO2e/kg)"),'Pivot Table_GHG'!$A$3,"SUB TYPE",$B26)) -> 0.95251464 | S26: =IF($P26="PROXY",DSTDEV('literature entries'!$D:$AI,IF($J26=1,"ACTIVE GHGE, FARM GATE (kg CO2e/kg)","GHGE, processor gate (kg CO2e/kg)"),INDIRECT($K26)),GETPIVOTDATA(IF($J26=1,"StdDev of ACTIVE GHGE, FARM GATE (kg CO2e/kg)","StdDev of GHGE, processor gate (kg CO2e/kg)"),'Pivot Table_GHG'!$A$3,"SUB TYPE",$B26)) -> 0.027712512 | W26: roots | X26: =IF($W26="DIRECT",M26,DCOUNT('literature entries'!$D:$AI,"ACTIVE CED, FARM GATE (MJ/kg)",INDIRECT($W26))) -> 14 | Y26: =IF($W26="DIRECT","",DAVERAGE('literature entries'!$D:$AI,"ACTIVE CED, FARM GATE (MJ/kg)",INDIRECT($W26))) -> 1.4220714 | Z26: =IF($W26="DIRECT",$O26,DSTDEV('literature entries'!$D:$AI,"ACTIVE CED, FARM GATE (MJ/kg)",INDIRECT($W26))) -> 0.57442044 | AA26: =IF($W26="DIRECT",$O26,$Z26/$Y26*$N26) -> 2.6784601 | AB26: potato | AC26: =IF($AB26="DIRECT",Q26,DCOUNT('literature entries'!$D:$AI,"ACTIVE GHGE, FARM GATE (kg CO2e/kg)",INDIRECT($AB26))) -> 17 | AD26: =IF($AB26="DIRECT","",DAVERAGE('literature entries'!$D:$AI,"ACTIVE GHGE, FARM GATE (kg CO2e/kg)",INDIRECT($AB26))) -> 0.21741176 | AE26: =IF($AB26="DIRECT",$S26,DSTDEV('literature entries'!$D:$AI,"ACTIVE GHGE, FARM GATE (kg CO2e/kg)",INDIRECT($AB26))) -> 0.11818474 | AF26: =IF($AB26="DIRECT",$S26,$AE26/$AD26*$R26) -> 0.51778566
A27: 103299000 | B27: Potato, tuber, w/peel | C27: weight of tuber; including peel | E27: 2630 | F27: =N27*H27+T27 -> 1.61125 | G27: =R27*H27+U27 -> 0.21741176 | H27: 1 | I27: none | J27: 1 | L27: =IF(ISERROR(GETPIVOTDATA(IF($J27=1,"Count of ACTIVE CED, FARM GATE (MJ/kg)","Count of CED, processor gate (MJ/kg)"),'Pivot Table_CED'!$A$3,"SUB TYPE",$B27)),"PROXY",IF(GETPIVOTDATA(IF($J27=1,"Count of ACTIVE CED, FARM GATE (MJ/kg)","Count of CED, processor gate (MJ/kg)"),'Pivot Table_CED'!$A$3,"SUB TYPE",$B27)=0,"PROXY","DB value")) -> DB value | M27: =IF($L27="PROXY",DCOUNT('literature entries'!$D:$AI,IF($J27=1,"ACTIVE CED, FARM GATE (MJ/kg)","CED, processor gate (MJ/kg)"),INDIRECT($K27)),GETPIVOTDATA(IF($J27=1,"Count of ACTIVE CED, FARM GATE (MJ/kg)","Count of CED, processor gate (MJ/kg)"),'Pivot Table_CED'!$A$3,"SUB TYPE",$B27)) -> 8 | N27: =IF($L27="PROXY",DAVERAGE('literature entries'!$D:$AI,IF($J27=1,"ACTIVE CED, FARM GATE (MJ/kg)","CED, processor gate (MJ/kg)"),INDIRECT($K27)),GETPIVOTDATA(IF($J27=1,"Average of ACTIVE CED, FARM GATE (MJ/kg)","Average of CED, processor gate (MJ/kg)"),'Pivot Table_CED'!$A$3,"SUB TYPE",$B27)) -> 1.61125 | O27: =IF($L27="PROXY",DSTDEV('literature entries'!D:AI,IF($J27=1,"ACTIVE CED, FARM GATE (MJ/kg)","CED, processor gate (MJ/kg)"),INDIRECT($K27)),GETPIVOTDATA(IF($J27=1,"StdDev of ACTIVE CED, FARM GATE (MJ/kg)","StdDev of CED, processor gate (MJ/kg)"),'Pivot Table_CED'!$A$3,"SUB TYPE",$B27)) -> 0.53279418 | P27: =IF(ISERROR(GETPIVOTDATA(IF($J27=1,"Count of ACTIVE GHGE, FARM GATE (kg CO2e/kg)","Count of GHGE, processor gate (kg CO2e/kg)"),'Pivot Table_GHG'!$A$3,"SUB TYPE",$B27)),"PROXY",IF(GETPIVOTDATA(IF($J27=1,"Count of ACTIVE GHGE, FARM GATE (kg CO2e/kg)","Count of GHGE, processor gate (kg CO2e/kg)"),'Pivot Table_GHG'!$A$3,"SUB TYPE",$B27)=0,"PROXY","DB value")) -> DB value | Q27: =IF($P27="PROXY",DCOUNT('literature entries'!$D:$AI,IF($J27=1,"ACTIVE GHGE, FARM GATE (kg CO2e/kg)","GHGE, processor gate (kg CO2e/kg)"),INDIRECT($K27)),GETPIVOTDATA(IF($J27=1,"ACTIVE GHGE, FARM GATE (kg CO2e/kg)","Count of GHGE, processor gate (kg CO2e/kg)"),'Pivot Table_GHG'!$A$3,"SUB TYPE",$B27)) -> 17 | R27: =IF($P27="PROXY",DAVERAGE('literature entries'!$D:$AI,IF($J27=1,"ACTIVE GHGE, FARM GATE (kg CO2e/kg)","GHGE, processor gate (kg CO2e/kg)"),INDIRECT($K27)),GETPIVOTDATA(IF($J27=1,"Average of ACTIVE GHGE, FARM GATE (kg CO2e/kg)","Average of GHGE, processor gate (kg CO2e/kg)"),'Pivot Table_GHG'!$A$3,"SUB TYPE",$B27)) -> 0.21741176 | S27: =IF($P27="PROXY",DSTDEV('literature entries'!$D:$AI,IF($J27=1,"ACTIVE GHGE, FARM GATE (kg CO2e/kg)","GHGE, processor gate (kg CO2e/kg)"),INDIRECT($K27)),GETPIVOTDATA(IF($J27=1,"StdDev of ACTIVE GHGE, FARM GATE (kg CO2e/kg)","StdDev of GHGE, processor gate (kg CO2e/kg)"),'Pivot Table_GHG'!$A$3,"SUB TYPE",$B27)) -> 0.11818474 | W27: =IF(L27="PROXY",IF(M27>=5,K27,"need group"),IF(M27>=5,"DIRECT","need group")) -> DIRECT | X27: =IF($W27="DIRECT",M27,DCOUNT('literature entries'!$D:$AI,IF($J27=1,"ACTIVE CED, FARM GATE (MJ/kg)","CED, processor gate (MJ/kg)"),INDIRECT($W27))) -> 8 | Y27: =IF($W27="DIRECT","",DAVERAGE('literature entries'!$D:$AI,IF($J27=1,"ACTIVE CED, FARM GATE (MJ/kg)","CED, processor gate (MJ/kg)"),INDIRECT($W27))) | Z27: =IF($W27="DIRECT",$O27,DSTDEV('literature entries'!$D:$AI,IF($J27=1,"ACTIVE CED, FARM GATE (MJ/kg)","CED, processor gate (MJ/kg)"),INDIRECT($W27))) -> 0.53279418 | AA27: =IF($W27="DIRECT",$O27,$Z27/$Y27*$N27) -> 0.53279418 | AB27: =IF(P27="PROXY",IF(Q27>=5,K27,"need group"),IF(Q27>=5,"DIRECT","need group")) -> DIRECT | AC27: =IF($AB27="DIRECT",Q27,DCOUNT('literature entries'!$D:$AI,IF($J27=1,"ACTIVE GHGE, FARM GATE (kg CO2e/kg)","GHGE, processor gate (kg CO2e/kg)"),INDIRECT($AB27))) -> 17 | AD27: =IF($AB27="DIRECT","",DAVERAGE('literature entries'!$D:$AI,IF($J27=1,"ACTIVE GHGE, FARM GATE (kg CO2e/kg)","GHGE, processor gate (kg CO2e/kg)"),INDIRECT($AB27))) | AE27: =IF($AB27="DIRECT",$S27,DSTDEV('literature entries'!$D:$AI,IF($J27=1,"ACTIVE GHGE, FARM GATE (kg CO2e/kg)","GHGE, processor gate (kg CO2e/kg)"),INDIRECT($AB27))) -> 0.11818474 | AF27: =IF($AB27="DIRECT",$S27,$AE27/$AD27*$R27) -> 0.11818474
A28: 103300000 | B28: Potato, tuber, w/o peel | C28: weight of tuber; excluding peel | E28: 15758 | F28: =N28*H28+T28 -> 2.1429625 | G28: =R28*H28+U28 -> 0.216125 | H28: 1.33 | I28: FICRCD | J28: 1 | K28: potato | L28: =IF(ISERROR(GETPIVOTDATA(IF($J28=1,"Count of ACTIVE CED, FARM GATE (MJ/kg)","Count of CED, processor gate (MJ/kg)"),'Pivot Table_CED'!$A$3,"SUB TYPE",$B28)),"PROXY",IF(GETPIVOTDATA(IF($J28=1,"Count of ACTIVE CED, FARM GATE (MJ/kg)","Count of CED, processor gate (MJ/kg)"),'Pivot Table_CED'!$A$3,"SUB TYPE",$B28)=0,"PROXY","DB value")) -> PROXY | M28: =IF($L28="PROXY",DCOUNT('literature entries'!$D:$AI,IF($J28=1,"ACTIVE CED, FARM GATE (MJ/kg)","CED, processor gate (MJ/kg)"),INDIRECT($K28)),GETPIVOTDATA(IF($J28=1,"Count of ACTIVE CED, FARM GATE (MJ/kg)","Count of CED, processor gate (MJ/kg)"),'Pivot Table_CED'!$A$3,"SUB TYPE",$B28)) -> 8 | N28: =IF($L28="PROXY",DAVERAGE('literature entries'!$D:$AI,IF($J28=1,"ACTIVE CED, FARM GATE (MJ/kg)","CED, processor gate (MJ/kg)"),INDIRECT($K28)),GETPIVOTDATA(IF($J28=1,"Average of ACTIVE CED, FARM GATE (MJ/kg)","Average of CED, processor gate (MJ/kg)"),'Pivot Table_CED'!$A$3,"SUB TYPE",$B28)) -> 1.61125 | O28: =IF($L28="PROXY",DSTDEV('literature entries'!D:AI,IF($J28=1,"ACTIVE CED, FARM GATE (MJ/kg)","CED, processor gate (MJ/kg)"),INDIRECT($K28)),GETPIVOTDATA(IF($J28=1,"StdDev of ACTIVE CED, FARM GATE (MJ/kg)","StdDev of CED, processor gate (MJ/kg)"),'Pivot Table_CED'!$A$3,"SUB TYPE",$B28)) -> 0.53279418 | P28: =IF(ISERROR(GETPIVOTDATA(IF($J28=1,"Count of ACTIVE GHGE, FARM GATE (kg CO2e/kg)","Count of GHGE, processor gate (kg CO2e/kg)"),'Pivot Table_GHG'!$A$3,"SUB TYPE",$B28)),"PROXY",IF(GETPIVOTDATA(IF($J28=1,"Count of ACTIVE GHGE, FARM GATE (kg CO2e/kg)","Count of GHGE, processor gate (kg CO2e/kg)"),'Pivot Table_GHG'!$A$3,"SUB TYPE",$B28)=0,"PROXY","DB value")) -> DB value | Q28: =IF($P28="PROXY",DCOUNT('literature entries'!$D:$AI,IF($J28=1,"ACTIVE GHGE, FARM GATE (kg CO2e/kg)","GHGE, processor gate (kg CO2e/kg)"),INDIRECT($K28)),GETPIVOTDATA(IF($J28=1,"ACTIVE GHGE, FARM GATE (kg CO2e/kg)","Count of GHGE, processor gate (kg CO2e/kg)"),'Pivot Table_GHG'!$A$3,"SUB TYPE",$B28)) -> 2 | R28: =IF($P28="PROXY",DAVERAGE('literature entries'!$D:$AI,IF($J28=1,"ACTIVE GHGE, FARM GATE (kg CO2e/kg)","GHGE, processor gate (kg CO2e/kg)"),INDIRECT($K28)),GETPIVOTDATA(IF($J28=1,"Average of ACTIVE GHGE, FARM GATE (kg CO2e/kg)","Average of GHGE, processor gate (kg CO2e/kg)"),'Pivot Table_GHG'!$A$3,"SUB TYPE",$B28)) -> 0.1625 | S28: =IF($P28="PROXY",DSTDEV('literature entries'!$D:$AI,IF($J28=1,"ACTIVE GHGE, FARM GATE (kg CO2e/kg)","GHGE, processor gate (kg CO2e/kg)"),INDIRECT($K28)),GETPIVOTDATA(IF($J28=1,"StdDev of ACTIVE GHGE, FARM GATE (kg CO2e/kg)","StdDev of GHGE, processor gate (kg CO2e/kg)"),'Pivot Table_GHG'!$A$3,"SUB TYPE",$B28)) -> 0.016263456 | W28: =IF(L28="PROXY",IF(M28>=5,K28,"need group"),IF(M28>=5,"DIRECT","need group")) -> potato | X28: =IF($W28="DIRECT",M28,DCOUNT('literature entries'!$D:$AI,IF($J28=1,"ACTIVE CED, FARM GATE (MJ/kg)","CED, processor gate (MJ/kg)"),INDIRECT($W28))) -> 8 | Y28: =IF($W28="DIRECT","",DAVERAGE('literature entries'!$D:$AI,IF($J28=1,"ACTIVE CED, FARM GATE (MJ/kg)","CED, processor gate (MJ/kg)"),INDIRECT($W28))) -> 1.61125 | Z28: =IF($W28="DIRECT",$O28,DSTDEV('literature entries'!$D:$AI,IF($J28=1,"ACTIVE CED, FARM GATE (MJ/kg)","CED, processor gate (MJ/kg)"),INDIRECT($W28))) -> 0.53279418 | AA28: =IF($W28="DIRECT",$O28,$Z28/$Y28*$N28) -> 0.53279418 | AB28: potato | AC28: =IF($AB28="DIRECT",Q28,DCOUNT('literature entries'!$D:$AI,IF($J28=1,"ACTIVE GHGE, FARM GATE (kg CO2e/kg)","GHGE, processor gate (kg CO2e/kg)"),INDIRECT($AB28))) -> 17 | AD28: =IF($AB28="DIRECT","",DAVERAGE('literature entries'!$D:$AI,IF($J28=1,"ACTIVE GHGE, FARM GATE (kg CO2e/kg)","GHGE, processor gate (kg CO2e/kg)"),INDIRECT($AB28))) -> 0.21741176 | AE28: =IF($AB28="DIRECT",$S28,DSTDEV('literature entries'!$D:$AI,IF($J28=1,"ACTIVE GHGE, FARM GATE (kg CO2e/kg)","GHGE, processor gate (kg CO2e/kg)"),INDIRECT($AB28))) -> 0.11818474 | AF28: =IF($AB28="DIRECT",$S28,$AE28/$AD28*$R28) -> 0.088334778
A29: 103366000 | B29: Sweet potato | C29: weight of roots, with or without peel; juice | E29: 825 | F29: =N29*H29+T29 -> 2.2396375 | G29: =R29*H29+U29 -> 0.30220235 | H29: 1.39 | I29: FICRCD | J29: 1 | K29: potato | L29: =IF(ISERROR(GETPIVOTDATA(IF($J29=1,"Count of ACTIVE CED, FARM GATE (MJ/kg)","Count of CED, processor gate (MJ/kg)"),'Pivot Table_CED'!$A$3,"SUB TYPE",$B29)),"PROXY",IF(GETPIVOTDATA(IF($J29=1,"Count of ACTIVE CED, FARM GATE (MJ/kg)","Count of CED, processor gate (MJ/kg)"),'Pivot Table_CED'!$A$3,"SUB TYPE",$B29)=0,"PROXY","DB value")) -> PROXY | M29: =IF($L29="PROXY",DCOUNT('literature entries'!$D:$AI,IF($J29=1,"ACTIVE CED, FARM GATE (MJ/kg)","CED, processor gate (MJ/kg)"),INDIRECT($K29)),GETPIVOTDATA(IF($J29=1,"Count of ACTIVE CED, FARM GATE (MJ/kg)","Count of CED, processor gate (MJ/kg)"),'Pivot Table_CED'!$A$3,"SUB TYPE",$B29)) -> 8 | N29: =IF($L29="PROXY",DAVERAGE('literature entries'!$D:$AI,IF($J29=1,"ACTIVE CED, FARM GATE (MJ/kg)","CED, processor gate (MJ/kg)"),INDIRECT($K29)),GETPIVOTDATA(IF($J29=1,"Average of ACTIVE CED, FARM GATE (MJ/kg)","Average of CED, processor gate (MJ/kg)"),'Pivot Table_CED'!$A$3,"SUB TYPE",$B29)) -> 1.61125 | O29: =IF($L29="PROXY",DSTDEV('literature entries'!D:AI,IF($J29=1,"ACTIVE CED, FARM GATE (MJ/kg)","CED, processor gate (MJ/kg)"),INDIRECT($K29)),GETPIVOTDATA(IF($J29=1,"StdDev of ACTIVE CED, FARM GATE (MJ/kg)","StdDev of CED, processor gate (MJ/kg)"),'Pivot Table_CED'!$A$3,"SUB TYPE",$B29)) -> 0.53279418 | P29: =IF(ISERROR(GETPIVOTDATA(IF($J29=1,"Count of ACTIVE GHGE, FARM GATE (kg CO2e/kg)","Count of GHGE, processor gate (kg CO2e/kg)"),'Pivot Table_GHG'!$A$3,"SUB TYPE",$B29)),"PROXY",IF(GETPIVOTDATA(IF($J29=1,"Count of ACTIVE GHGE, FARM GATE (kg CO2e/kg)","Count of GHGE, processor gate (kg CO2e/kg)"),'Pivot Table_GHG'!$A$3,"SUB TYPE",$B29)=0,"PROXY","DB value")) -> PROXY | Q29: =IF($P29="PROXY",DCOUNT('literature entries'!$D:$AI,IF($J29=1,"ACTIVE GHGE, FARM GATE (kg CO2e/kg)","GHGE, processor gate (kg CO2e/kg)"),INDIRECT($K29)),GETPIVOTDATA(IF($J29=1,"ACTIVE GHGE, FARM GATE (kg CO2e/kg)","Count of GHGE, processor gate (kg CO2e/kg)"),'Pivot Table_GHG'!$A$3,"SUB TYPE",$B29)) -> 17 | R29: =IF($P29="PROXY",DAVERAGE('literature entries'!$D:$AI,IF($J29=1,"ACTIVE GHGE, FARM GATE (kg CO2e/kg)","GHGE, processor gate (kg CO2e/kg)"),INDIRECT($K29)),GETPIVOTDATA(IF($J29=1,"Average of ACTIVE GHGE, FARM GATE (kg CO2e/kg)","Average of GHGE, processor gate (kg CO2e/kg)"),'Pivot Table_GHG'!$A$3,"SUB TYPE",$B29)) -> 0.21741176 | S29: =IF($P29="PROXY",DSTDEV('literature entries'!$D:$AI,IF($J29=1,"ACTIVE GHGE, FARM GATE (kg CO2e/kg)","GHGE, processor gate (kg CO2e/kg)"),INDIRECT($K29)),GETPIVOTDATA(IF($J29=1,"StdDev of ACTIVE GHGE, FARM GATE (kg CO2e/kg)","StdDev of GHGE, processor gate (kg CO2e/kg)"),'Pivot Table_GHG'!$A$3,"SUB TYPE",$B29)) -> 0.11818474 | W29: =IF(L29="PROXY",IF(M29>=5,K29,"need group"),IF(M29>=5,"DIRECT","need group")) -> potato | X29: =IF($W29="DIRECT",M29,DCOUNT('literature entries'!$D:$AI,IF($J29=1,"ACTIVE CED, FARM GATE (MJ/kg)","CED, processor gate (MJ/kg)"),INDIRECT($W29))) -> 8 | Y29: =IF($W29="DIRECT","",DAVERAGE('literature entries'!$D:$AI,IF($J29=1,"ACTIVE CED, FARM GATE (MJ/kg)","CED, processor gate (MJ/kg)"),INDIRECT($W29))) -> 1.61125 | Z29: =IF($W29="DIRECT",$O29,DSTDEV('literature entries'!$D:$AI,IF($J29=1,"ACTIVE CED, FARM GATE (MJ/kg)","CED, processor gate (MJ/kg)"),INDIRECT($W29))) -> 0.53279418 | AA29: =IF($W29="DIRECT",$O29,$Z29/$Y29*$N29) -> 0.53279418 | AB29: =IF(P29="PROXY",IF(Q29>=5,K29,"need group"),IF(Q29>=5,"DIRECT","need group")) -> potato | AC29: =IF($AB29="DIRECT",Q29,DCOUNT('literature entries'!$D:$AI,IF($J29=1,"ACTIVE GHGE, FARM GATE (kg CO2e/kg)","GHGE, processor gate (kg CO2e/kg)"),INDIRECT($AB29))) -> 17 | AD29: =IF($AB29="DIRECT","",DAVERAGE('literature entries'!$D:$AI,IF($J29=1,"ACTIVE GHGE, FARM GATE (kg CO2e/kg)","GHGE, processor gate (kg CO2e/kg)"),INDIRECT($AB29))) -> 0.21741176 | AE29: =IF($AB29="DIRECT",$S29,DSTDEV('literature entries'!$D:$AI,IF($J29=1,"ACTIVE GHGE, FARM GATE (kg CO2e/kg)","GHGE, processor gate (kg CO2e/kg)"),INDIRECT($AB29))) -> 0.11818474 | AF29: =IF($AB29="DIRECT",$S29,$AE29/$AD29*$R29) -> 0.11818474
A30: 103371000 | B30: Tanier, corm | C30: weight of corm | D30: Also called Cocoyam. | E30: 8 | F30: =N30*H30+T30 -> 1.4220714 | G30: =R30*H30+U30 -> 0.2134 | H30: 1 | I30: None | J30: 1 | K30: roots | L30: =IF(ISERROR(GETPIVOTDATA(IF($J30=1,"Count of ACTIVE CED, FARM GATE (MJ/kg)","Count of CED, processor gate (MJ/kg)"),'Pivot Table_CED'!$A$3,"SUB TYPE",$B30)),"PROXY",IF(GETPIVOTDATA(IF($J30=1,"Count of ACTIVE CED, FARM GATE (MJ/kg)","Count of CED, processor gate (MJ/kg)"),'Pivot Table_CED'!$A$3,"SUB TYPE",$B30)=0,"PROXY","DB value")) -> PROXY | M30: =IF($L30="PROXY",DCOUNT('literature entries'!$D:$AI,IF($J30=1,"ACTIVE CED, FARM GATE (MJ/kg)","CED, processor gate (MJ/kg)"),INDIRECT($K30)),GETPIVOTDATA(IF($J30=1,"Count of ACTIVE CED, FARM GATE (MJ/kg)","Count of CED, processor gate (MJ/kg)"),'Pivot Table_CED'!$A$3,"SUB TYPE",$B30)) -> 14 | N30: =IF($L30="PROXY",DAVERAGE('literature entries'!$D:$AI,IF($J30=1,"ACTIVE CED, FARM GATE (MJ/kg)","CED, processor gate (MJ/kg)"),INDIRECT($K30)),GETPIVOTDATA(IF($J30=1,"Average of ACTIVE CED, FARM GATE (MJ/kg)","Average of CED, processor gate (MJ/kg)"),'Pivot Table_CED'!$A$3,"SUB TYPE",$B30)) -> 1.4220714 | O30: =IF($L30="PROXY",DSTDEV('literature entries'!D:AI,IF($J30=1,"ACTIVE CED, FARM GATE (MJ/kg)","CED, processor gate (MJ/kg)"),INDIRECT($K30)),GETPIVOTDATA(IF($J30=1,"StdDev of ACTIVE CED, FARM GATE (MJ/kg)","StdDev of CED, processor gate (MJ/kg)"),'Pivot Table_CED'!$A$3,"SUB TYPE",$B30)) -> 0.57442044 | P30: =IF(ISERROR(GETPIVOTDATA(IF($J30=1,"Count of ACTIVE GHGE, FARM GATE (kg CO2e/kg)","Count of GHGE, processor gate (kg CO2e/kg)"),'Pivot Table_GHG'!$A$3,"SUB TYPE",$B30)),"PROXY",IF(GETPIVOTDATA(IF($J30=1,"Count of ACTIVE GHGE, FARM GATE (kg CO2e/kg)","Count of GHGE, processor gate (kg CO2e/kg)"),'Pivot Table_GHG'!$A$3,"SUB TYPE",$B30)=0,"PROXY","DB value")) -> PROXY | Q30: =IF($P30="PROXY",DCOUNT('literature entries'!$D:$AI,IF($J30=1,"ACTIVE GHGE, FARM GATE (kg CO2e/kg)","GHGE, processor gate (kg CO2e/kg)"),INDIRECT($K30)),GETPIVOTDATA(IF($J30=1,"ACTIVE GHGE, FARM GATE (kg CO2e/kg)","Count of GHGE, processor gate (kg CO2e/kg)"),'Pivot Table_GHG'!$A$3,"SUB TYPE",$B30)) -> 25 | R30: =IF($P30="PROXY",DAVERAGE('literature entries'!$D:$AI,IF($J30=1,"ACTIVE GHGE, FARM GATE (kg CO2e/kg)","GHGE, processor gate (kg CO2e/kg)"),INDIRECT($K30)),GETPIVOTDATA(IF($J30=1,"Average of ACTIVE GHGE, FARM GATE (kg CO2e/kg)","Average of GHGE, processor gate (kg CO2e/kg)"),'Pivot Table_GHG'!$A$3,"SUB TYPE",$B30)) -> 0.2134 | S30: =IF($P30="PROXY",DSTDEV('literature entries'!$D:$AI,IF($J30=1,"ACTIVE GHGE, FARM GATE (kg CO2e/kg)","GHGE, processor gate (kg CO2e/kg)"),INDIRECT($K30)),GETPIVOTDATA(IF($J30=1,"StdDev of ACTIVE GHGE, FARM GATE (kg CO2e/kg)","StdDev of GHGE, processor gate (kg CO2e/kg)"),'Pivot Table_GHG'!$A$3,"SUB TYPE",$B30)) -> 0.17992035 | W30: =IF(L30="PROXY",IF(M30>=5,K30,"need group"),IF(M30>=5,"DIRECT","need group")) -> roots | X30: =IF($W30="DIRECT",M30,DCOUNT('literature entries'!$D:$AI,IF($J30=1,"ACTIVE CED, FARM GATE (MJ/kg)","CED, processor gate (MJ/kg)"),INDIRECT($W30))) -> 14 | Y30: =IF($W30="DIRECT","",DAVERAGE('literature entries'!$D:$AI,IF($J30=1,"ACTIVE CED, FARM GATE (MJ/kg)","CED, processor gate (MJ/kg)"),INDIRECT($W30))) -> 1.4220714 | Z30: =IF($W30="DIRECT",$O30,DSTDEV('literature entries'!$D:$AI,IF($J30=1,"ACTIVE CED, FARM GATE (MJ/kg)","CED, processor gate (MJ/kg)"),INDIRECT($W30))) -> 0.57442044 | AA30: =IF($W30="DIRECT",$O30,$Z30/$Y30*$N30) -> 0.57442044 | AB30: =IF(P30="PROXY",IF(Q30>=5,K30,"need group"),IF(Q30>=5,"DIRECT","need group")) -> roots | AC30: =IF($AB30="DIRECT",Q30,DCOUNT('literature entries'!$D:$AI,IF($J30=1,"ACTIVE GHGE, FARM GATE (kg CO2e/kg)","GHGE, processor gate (kg CO2e/kg)"),INDIRECT($AB30))) -> 25 | AD30: =IF($AB30="DIRECT","",DAVERAGE('literature entries'!$D:$AI,IF($J30=1,"ACTIVE GHGE, FARM GATE (kg CO2e/kg)","GHGE, processor gate (kg CO2e/kg)"),INDIRECT($AB30))) -> 0.2134 | AE30: =IF($AB30="DIRECT",$S30,DSTDEV('literature entries'!$D:$AI,IF($J30=1,"ACTIVE GHGE, FARM GATE (kg CO2e/kg)","GHGE, processor gate (kg CO2e/kg)"),INDIRECT($AB30))) -> 0.17992035 | AF30: =IF($AB30="DIRECT",$S30,$AE30/$AD30*$R30) -> 0.17992035
A31: 103387000 | B31: Turmeric | C31: weight of roots | E31: 7304 | F31: =N31*H31+T31 -> 1.4220714 | G31: =R31*H31+U31 -> 0.2134 | H31: 1 | I31: None | J31: 1 | K31: roots | L31: =IF(ISERROR(GETPIVOTDATA(IF($J31=1,"Count of ACTIVE CED, FARM GATE (MJ/kg)","Count of CED, processor gate (MJ/kg)"),'Pivot Table_CED'!$A$3,"SUB TYPE",$B31)),"PROXY",IF(GETPIVOTDATA(IF($J31=1,"Count of ACTIVE CED, FARM GATE (MJ/kg)","Count of CED, processor gate (MJ/kg)"),'Pivot Table_CED'!$A$3,"SUB TYPE",$B31)=0,"PROXY","DB value")) -> PROXY | M31: =IF($L31="PROXY",DCOUNT('literature entries'!$D:$AI,IF($J31=1,"ACTIVE CED, FARM GATE (MJ/kg)","CED, processor gate (MJ/kg)"),INDIRECT($K31)),GETPIVOTDATA(IF($J31=1,"Count of ACTIVE CED, FARM GATE (MJ/kg)","Count of CED, processor gate (MJ/kg)"),'Pivot Table_CED'!$A$3,"SUB TYPE",$B31)) -> 14 | N31: =IF($L31="PROXY",DAVERAGE('literature entries'!$D:$AI,IF($J31=1,"ACTIVE CED, FARM GATE (MJ/kg)","CED, processor gate (MJ/kg)"),INDIRECT($K31)),GETPIVOTDATA(IF($J31=1,"Average of ACTIVE CED, FARM GATE (MJ/kg)","Average of CED, processor gate (MJ/kg)"),'Pivot Table_CED'!$A$3,"SUB TYPE",$B31)) -> 1.4220714 | O31: =IF($L31="PROXY",DSTDEV('literature entries'!D:AI,IF($J31=1,"ACTIVE CED, FARM GATE (MJ/kg)","CED, processor gate (MJ/kg)"),INDIRECT($K31)),GETPIVOTDATA(IF($J31=1,"StdDev of ACTIVE CED, FARM GATE (MJ/kg)","StdDev of CED, processor gate (MJ/kg)"),'Pivot Table_CED'!$A$3,"SUB TYPE",$B31)) -> 0.57442044 | P31: =IF(ISERROR(GETPIVOTDATA(IF($J31=1,"Count of ACTIVE GHGE, FARM GATE (kg CO2e/kg)","Count of GHGE, processor gate (kg CO2e/kg)"),'Pivot Table_GHG'!$A$3,"SUB TYPE",$B31)),"PROXY",IF(GETPIVOTDATA(IF($J31=1,"Count of ACTIVE GHGE, FARM GATE (kg CO2e/kg)","Count of GHGE, processor gate (kg CO2e/kg)"),'Pivot Table_GHG'!$A$3,"SUB TYPE",$B31)=0,"PROXY","DB value")) -> PROXY | Q31: =IF($P31="PROXY",DCOUNT('literature entries'!$D:$AI,IF($J31=1,"ACTIVE GHGE, FARM GATE (kg CO2e/kg)","GHGE, processor gate (kg CO2e/kg)"),INDIRECT($K31)),GETPIVOTDATA(IF($J31=1,"ACTIVE GHGE, FARM GATE (kg CO2e/kg)","Count of GHGE, processor gate (kg CO2e/kg)"),'Pivot Table_GHG'!$A$3,"SUB TYPE",$B31)) -> 25 | R31: =IF($P31="PROXY",DAVERAGE('literature entries'!$D:$AI,IF($J31=1,"ACTIVE GHGE, FARM GATE (kg CO2e/kg)","GHGE, processor gate (kg CO2e/kg)"),INDIRECT($K31)),GETPIVOTDATA(IF($J31=1,"Average of ACTIVE GHGE, FARM GATE (kg CO2e/kg)","Average of GHGE, processor gate (kg CO2e/kg)"),'Pivot Table_GHG'!$A$3,"SUB TYPE",$B31)) -> 0.2134 | S31: =IF($P31="PROXY",DSTDEV('literature entries'!$D:$AI,IF($J31=1,"ACTIVE GHGE, FARM GATE (kg CO2e/kg)","GHGE, processor gate (kg CO2e/kg)"),INDIRECT($K31)),GETPIVOTDATA(IF($J31=1,"StdDev of ACTIVE GHGE, FARM GATE (kg CO2e/kg)","StdDev of GHGE, processor gate (kg CO2e/kg)"),'Pivot Table_GHG'!$A$3,"SUB TYPE",$B31)) -> 0.17992035 | W31: =IF(L31="PROXY",IF(M31>=5,K31,"need group"),IF(M31>=5,"DIRECT","need group")) -> roots | X31: =IF($W31="DIRECT",M31,DCOUNT('literature entries'!$D:$AI,IF($J31=1,"ACTIVE CED, FARM GATE (MJ/kg)","CED, processor gate (MJ/kg)"),INDIRECT($W31))) -> 14 | Y31: =IF($W31="DIRECT","",DAVERAGE('literature entries'!$D:$AI,IF($J31=1,"ACTIVE CED, FARM GATE (MJ/kg)","CED, processor gate (MJ/kg)"),INDIRECT($W31))) -> 1.4220714 | Z31: =IF($W31="DIRECT",$O31,DSTDEV('literature entries'!$D:$AI,IF($J31=1,"ACTIVE CED, FARM GATE (MJ/kg)","CED, processor gate (MJ/kg)"),INDIRECT($W31))) -> 0.57442044 | AA31: =IF($W31="DIRECT",$O31,$Z31/$Y31*$N31) -> 0.57442044 | AB31: =IF(P31="PROXY",IF(Q31>=5,K31,"need group"),IF(Q31>=5,"DIRECT","need group")) -> roots | AC31: =IF($AB31="DIRECT",Q31,DCOUNT('literature entries'!$D:$AI,IF($J31=1,"ACTIVE GHGE, FARM GATE (kg CO2e/kg)","GHGE, processor gate (kg CO2e/kg)"),INDIRECT($AB31))) -> 25 | AD31: =IF($AB31="DIRECT","",DAVERAGE('literature entries'!$D:$AI,IF($J31=1,"ACTIVE GHGE, FARM GATE (kg CO2e/kg)","GHGE, processor gate (kg CO2e/kg)"),INDIRECT($AB31))) -> 0.2134 | AE31: =IF($AB31="DIRECT",$S31,DSTDEV('literature entries'!$D:$AI,IF($J31=1,"ACTIVE GHGE, FARM GATE (kg CO2e/kg)","GHGE, processor gate (kg CO2e/kg)"),INDIRECT($AB31))) -> 0.17992035 | AF31: =IF($AB31="DIRECT",$S31,$AE31/$AD31*$R31) -> 0.17992035
A32: 103406000 | B32: Yam, true | C32: weight of roots | E32: 24 | F32: =N32*H32+T32 -> 1.86905 | G32: =R32*H32+U32 -> 1.0208 | H32: 1.16 | I32: FICRCD | J32: 1 | K32: potato | L32: =IF(ISERROR(GETPIVOTDATA(IF($J32=1,"Count of ACTIVE CED, FARM GATE (MJ/kg)","Count of CED, processor gate (MJ/kg)"),'Pivot Table_CED'!$A$3,"SUB TYPE",$B32)),"PROXY",IF(GETPIVOTDATA(IF($J32=1,"Count of ACTIVE CED, FARM GATE (MJ/kg)","Count of CED, processor gate (MJ/kg)"),'Pivot Table_CED'!$A$3,"SUB TYPE",$B32)=0,"PROXY","DB value")) -> PROXY | M32: =IF($L32="PROXY",DCOUNT('literature entries'!$D:$AI,IF($J32=1,"ACTIVE CED, FARM GATE (MJ/kg)","CED, processor gate (MJ/kg)"),INDIRECT($K32)),GETPIVOTDATA(IF($J32=1,"Count of ACTIVE CED, FARM GATE (MJ/kg)","Count of CED, processor gate (MJ/kg)"),'Pivot Table_CED'!$A$3,"SUB TYPE",$B32)) -> 8 | N32: =IF($L32="PROXY",DAVERAGE('literature entries'!$D:$AI,IF($J32=1,"ACTIVE CED, FARM GATE (MJ/kg)","CED, processor gate (MJ/kg)"),INDIRECT($K32)),GETPIVOTDATA(IF($J32=1,"Average of ACTIVE CED, FARM GATE (MJ/kg)","Average of CED, processor gate (MJ/kg)"),'Pivot Table_CED'!$A$3,"SUB TYPE",$B32)) -> 1.61125 | O32: =IF($L32="PROXY",DSTDEV('literature entries'!D:AI,IF($J32=1,"ACTIVE CED, FARM GATE (MJ/kg)","CED, processor gate (MJ/kg)"),INDIRECT($K32)),GETPIVOTDATA(IF($J32=1,"StdDev of ACTIVE CED, FARM GATE (MJ/kg)","StdDev of CED, processor gate (MJ/kg)"),'Pivot Table_CED'!$A$3,"SUB TYPE",$B32)) -> 0.53279418 | P32: =IF(ISERROR(GETPIVOTDATA(IF($J32=1,"Count of ACTIVE GHGE, FARM GATE (kg CO2e/kg)","Count of GHGE, processor gate (kg CO2e/kg)"),'Pivot Table_GHG'!$A$3,"SUB TYPE",$B32)),"PROXY",IF(GETPIVOTDATA(IF($J32=1,"Count of ACTIVE GHGE, FARM GATE (kg CO2e/kg)","Count of GHGE, processor gate (kg CO2e/kg)"),'Pivot Table_GHG'!$A$3,"SUB TYPE",$B32)=0,"PROXY","DB value")) -> DB value | Q32: =IF($P32="PROXY",DCOUNT('literature entries'!$D:$AI,IF($J32=1,"ACTIVE GHGE, FARM GATE (kg CO2e/kg)","GHGE, processor gate (kg CO2e/kg)"),INDIRECT($K32)),GETPIVOTDATA(IF($J32=1,"ACTIVE GHGE, FARM GATE (kg CO2e/kg)","Count of GHGE, processor gate (kg CO2e/kg)"),'Pivot Table_GHG'!$A$3,"SUB TYPE",$B32)) -> 1 | R32: =IF($P32="PROXY",DAVERAGE('literature entries'!$D:$AI,IF($J32=1,"ACTIVE GHGE, FARM GATE (kg CO2e/kg)","GHGE, processor gate (kg CO2e/kg)"),INDIRECT($K32)),GETPIVOTDATA(IF($J32=1,"Average of ACTIVE GHGE, FARM GATE (kg CO2e/kg)","Average of GHGE, processor gate (kg CO2e/kg)"),'Pivot Table_GHG'!$A$3,"SUB TYPE",$B32)) -> 0.88 | S32: =IF($P32="PROXY",DSTDEV('literature entries'!$D:$AI,IF($J32=1,"ACTIVE GHGE, FARM GATE (kg CO2e/kg)","GHGE, processor gate (kg CO2e/kg)"),INDIRECT($K32)),GETPIVOTDATA(IF($J32=1,"StdDev of ACTIVE GHGE, FARM GATE (kg CO2e/kg)","StdDev of GHGE, processor gate (kg CO2e/kg)"),'Pivot Table_GHG'!$A$3,"SUB TYPE",$B32)) -> #DIV/0! | W32: roots | X32: =IF($W32="DIRECT",M32,DCOUNT('literature entries'!$D:$AI,IF($J32=1,"ACTIVE CED, FARM GATE (MJ/kg)","CED, processor gate (MJ/kg)"),INDIRECT($W32))) -> 14 | Y32: =IF($W32="DIRECT","",DAVERAGE('literature entries'!$D:$AI,IF($J32=1,"ACTIVE CED, FARM GATE (MJ/kg)","CED, processor gate (MJ/kg)"),INDIRECT($W32))) -> 1.4220714 | Z32: =IF($W32="DIRECT",$O32,DSTDEV('literature entries'!$D:$AI,IF($J32=1,"ACTIVE CED, FARM GATE (MJ/kg)","CED, processor gate (MJ/kg)"),INDIRECT($W32))) -> 0.57442044 | AA32: =IF($W32="DIRECT",$O32,$Z32/$Y32*$N32) -> 0.65083576 | AB32: roots | AC32: =IF($AB32="DIRECT",Q32,DCOUNT('literature entries'!$D:$AI,IF($J32=1,"ACTIVE GHGE, FARM GATE (kg CO2e/kg)","GHGE, processor gate (kg CO2e/kg)"),INDIRECT($AB32))) -> 25 | AD32: =IF($AB32="DIRECT","",DAVERAGE('literature entries'!$D:$AI,IF($J32=1,"ACTIVE GHGE, FARM GATE (kg CO2e/kg)","GHGE, processor gate (kg CO2e/kg)"),INDIRECT($AB32))) -> 0.2134 | AE32: =IF($AB32="DIRECT",$S32,DSTDEV('literature entries'!$D:$AI,IF($J32=1,"ACTIVE GHGE, FARM GATE (kg CO2e/kg)","GHGE, processor gate (kg CO2e/kg)"),INDIRECT($AB32))) -> 0.17992035 | AF32: =IF($AB32="DIRECT",$S32,$AE32/$AD32*$R32) -> 0.7419396
A33: 103407000 | B33: Yam bean | C33: weight of roots | D33: Also called jicama. | E33: 62 | F33: =N33*H33+T33 -> 1.7562625 | G33: =R33*H33+U33 -> 0.23697882 | H33: 1.09 | I33: FICRCD | J33: 1 | K33: potato | L33: =IF(ISERROR(GETPIVOTDATA(IF($J33=1,"Count of ACTIVE CED, FARM GATE (MJ/kg)","Count of CED, processor gate (MJ/kg)"),'Pivot Table_CED'!$A$3,"SUB TYPE",$B33)),"PROXY",IF(GETPIVOTDATA(IF($J33=1,"Count of ACTIVE CED, FARM GATE (MJ/kg)","Count of CED, processor gate (MJ/kg)"),'Pivot Table_CED'!$A$3,"SUB TYPE",$B33)=0,"PROXY","DB value")) -> PROXY | M33: =IF($L33="PROXY",DCOUNT('literature entries'!$D:$AI,IF($J33=1,"ACTIVE CED, FARM GATE (MJ/kg)","CED, processor gate (MJ/kg)"),INDIRECT($K33)),GETPIVOTDATA(IF($J33=1,"Count of ACTIVE CED, FARM GATE (MJ/kg)","Count of CED, processor gate (MJ/kg)"),'Pivot Table_CED'!$A$3,"SUB TYPE",$B33)) -> 8 | N33: =IF($L33="PROXY",DAVERAGE('literature entries'!$D:$AI,IF($J33=1,"ACTIVE CED, FARM GATE (MJ/kg)","CED, processor gate (MJ/kg)"),INDIRECT($K33)),GETPIVOTDATA(IF($J33=1,"Average of ACTIVE CED, FARM GATE (MJ/kg)","Average of CED, processor gate (MJ/kg)"),'Pivot Table_CED'!$A$3,"SUB TYPE",$B33)) -> 1.61125 | O33: =IF($L33="PROXY",DSTDEV('literature entries'!D:AI,IF($J33=1,"ACTIVE CED, FARM GATE (MJ/kg)","CED, processor gate (MJ/kg)"),INDIRECT($K33)),GETPIVOTDATA(IF($J33=1,"StdDev of ACTIVE CED, FARM GATE (MJ/kg)","StdDev of CED, processor gate (MJ/kg)"),'Pivot Table_CED'!$A$3,"SUB TYPE",$B33)) -> 0.53279418 | P33: =IF(ISERROR(GETPIVOTDATA(IF($J33=1,"Count of ACTIVE GHGE, FARM GATE (kg CO2e/kg)","Count of GHGE, processor gate (kg CO2e/kg)"),'Pivot Table_GHG'!$A$3,"SUB TYPE",$B33)),"PROXY",IF(GETPIVOTDATA(IF($J33=1,"Count of ACTIVE GHGE, FARM GATE (kg CO2e/kg)","Count of GHGE, processor gate (kg CO2e/kg)"),'Pivot Table_GHG'!$A$3,"SUB TYPE",$B33)=0,"PROXY","DB value")) -> PROXY | Q33: =IF($P33="PROXY",DCOUNT('literature entries'!$D:$AI,IF($J33=1,"ACTIVE GHGE, FARM GATE (kg CO2e/kg)","GHGE, processor gate (kg CO2e/kg)"),INDIRECT($K33)),GETPIVOTDATA(IF($J33=1,"ACTIVE GHGE, FARM GATE (kg CO2e/kg)","Count of GHGE, processor gate (kg CO2e/kg)"),'Pivot Table_GHG'!$A$3,"SUB TYPE",$B33)) -> 17 | R33: =IF($P33="PROXY",DAVERAGE('literature entries'!$D:$AI,IF($J33=1,"ACTIVE GHGE, FARM GATE (kg CO2e/kg)","GHGE, processor gate (kg CO2e/kg)"),INDIRECT($K33)),GETPIVOTDATA(IF($J33=1,"Average of ACTIVE GHGE, FARM GATE (kg CO2e/kg)","Average of GHGE, processor gate (kg CO2e/kg)"),'Pivot Table_GHG'!$A$3,"SUB TYPE",$B33)) -> 0.21741176 | S33: =IF($P33="PROXY",DSTDEV('literature entries'!$D:$AI,IF($J33=1,"ACTIVE GHGE, FARM GATE (kg CO2e/kg)","GHGE, processor gate (kg CO2e/kg)"),INDIRECT($K33)),GETPIVOTDATA(IF($J33=1,"StdDev of ACTIVE GHGE, FARM GATE (kg CO2e/kg)","StdDev of GHGE, processor gate (kg CO2e/kg)"),'Pivot Table_GHG'!$A$3,"SUB TYPE",$B33)) -> 0.11818474 | W33: roots | X33: =IF($W33="DIRECT",M33,DCOUNT('literature entries'!$D:$AI,IF($J33=1,"ACTIVE CED, FARM GATE (MJ/kg)","CED, processor gate (MJ/kg)"),INDIRECT($W33))) -> 14 | Y33: =IF($W33="DIRECT","",DAVERAGE('literature entries'!$D:$AI,IF($J33=1,"ACTIVE CED, FARM GATE (MJ/kg)","CED, processor gate (MJ/kg)"),INDIRECT($W33))) -> 1.4220714 | Z33: =IF($W33="DIRECT",$O33,DSTDEV('literature entries'!$D:$AI,IF($J33=1,"ACTIVE CED, FARM GATE (MJ/kg)","CED, processor gate (MJ/kg)"),INDIRECT($W33))) -> 0.57442044 | AA33: =IF($W33="DIRECT",$O33,$Z33/$Y33*$N33) -> 0.65083576 | AB33: =IF(P33="PROXY",IF(Q33>=5,K33,"need group"),IF(Q33>=5,"DIRECT","need group")) -> potato | AC33: =IF($AB33="DIRECT",Q33,DCOUNT('literature entries'!$D:$AI,IF($J33=1,"ACTIVE GHGE, FARM GATE (kg CO2e/kg)","GHGE, processor gate (kg CO2e/kg)"),INDIRECT($AB33))) -> 17 | AD33: =IF($AB33="DIRECT","",DAVERAGE('literature entries'!$D:$AI,IF($J33=1,"ACTIVE GHGE, FARM GATE (kg CO2e/kg)","GHGE, processor gate (kg CO2e/kg)"),INDIRECT($AB33))) -> 0.21741176 | AE33: =IF($AB33="DIRECT",$S33,DSTDEV('literature entries'!$D:$AI,IF($J33=1,"ACTIVE GHGE, FARM GATE (kg CO2e/kg)","GHGE, processor gate (kg CO2e/kg)"),INDIRECT($AB33))) -> 0.11818474 | AF33: =IF($AB33="DIRECT",$S33,$AE33/$AD33*$R33) -> 0.11818474
A34: 200051000 | B34: Beet, garden, tops | C34: weight of leaves | D34: Include pumpkin leaves. | E34: 15 | F34: =N34*H34+T34 -> 4.5926522 | G34: =R34*H34+U34 -> 0.33225934 | H34: 1.79 | I34: FICRCD | J34: 1 | K34: greens | L34: =IF(ISERROR(GETPIVOTDATA(IF($J34=1,"Count of ACTIVE CED, FARM GATE (MJ/kg)","Count of CED, processor gate (MJ/kg)"),'Pivot Table_CED'!$A$3,"SUB TYPE",$B34)),"PROXY",IF(GETPIVOTDATA(IF($J34=1,"Count of ACTIVE CED, FARM GATE (MJ/kg)","Count of CED, processor gate (MJ/kg)"),'Pivot Table_CED'!$A$3,"SUB TYPE",$B34)=0,"PROXY","DB value")) -> PROXY | M34: =IF($L34="PROXY",DCOUNT('literature entries'!$D:$AI,IF($J34=1,"ACTIVE CED, FARM GATE (MJ/kg)","CED, processor gate (MJ/kg)"),INDIRECT($K34)),GETPIVOTDATA(IF($J34=1,"Count of ACTIVE CED, FARM GATE (MJ/kg)","Count of CED, processor gate (MJ/kg)"),'Pivot Table_CED'!$A$3,"SUB TYPE",$B34)) -> 10 | N34: =IF($L34="PROXY",DAVERAGE('literature entries'!$D:$AI,IF($J34=1,"ACTIVE CED, FARM GATE (MJ/kg)","CED, processor gate (MJ/kg)"),INDIRECT($K34)),GETPIVOTDATA(IF($J34=1,"Average of ACTIVE CED, FARM GATE (MJ/kg)","Average of CED, processor gate (MJ/kg)"),'Pivot Table_CED'!$A$3,"SUB TYPE",$B34)) -> 2.5657275 | O34: =IF($L34="PROXY",DSTDEV('literature entries'!D:AI,IF($J34=1,"ACTIVE CED, FARM GATE (MJ/kg)","CED, processor gate (MJ/kg)"),INDIRECT($K34)),GETPIVOTDATA(IF($J34=1,"StdDev of ACTIVE CED, FARM GATE (MJ/kg)","StdDev of CED, processor gate (MJ/kg)"),'Pivot Table_CED'!$A$3,"SUB TYPE",$B34)) -> 1.5197673 | P34: =IF(ISERROR(GETPIVOTDATA(IF($J34=1,"Count of ACTIVE GHGE, FARM GATE (kg CO2e/kg)","Count of GHGE, processor gate (kg CO2e/kg)"),'Pivot Table_GHG'!$A$3,"SUB TYPE",$B34)),"PROXY",IF(GETPIVOTDATA(IF($J34=1,"Count of ACTIVE GHGE, FARM GATE (kg CO2e/kg)","Count of GHGE, processor gate (kg CO2e/kg)"),'Pivot Table_GHG'!$A$3,"SUB TYPE",$B34)=0,"PROXY","DB value")) -> PROXY | Q34: =IF($P34="PROXY",DCOUNT('literature entries'!$D:$AI,IF($J34=1,"ACTIVE GHGE, FARM GATE (kg CO2e/kg)","GHGE, processor gate (kg CO2e/kg)"),INDIRECT($K34)),GETPIVOTDATA(IF($J34=1,"ACTIVE GHGE, FARM GATE (kg CO2e/kg)","Count of GHGE, processor gate (kg CO2e/kg)"),'Pivot Table_GHG'!$A$3,"SUB TYPE",$B34)) -> 22 | R34: =IF($P34="PROXY",DAVERAGE('literature entries'!$D:$AI,IF($J34=1,"ACTIVE GHGE, FARM GATE (kg CO2e/kg)","GHGE, processor gate (kg CO2e/kg)"),INDIRECT($K34)),GETPIVOTDATA(IF($J34=1,"Average of ACTIVE GHGE, FARM GATE (kg CO2e/kg)","Average of GHGE, processor gate (kg CO2e/kg)"),'Pivot Table_GHG'!$A$3,"SUB TYPE",$B34)) -> 0.18561974 | S34: =IF($P34="PROXY",DSTDEV('literature entries'!$D:$AI,IF($J34=1,"ACTIVE GHGE, FARM GATE (kg CO2e/kg)","GHGE, processor gate (kg CO2e/kg)"),INDIRECT($K34)),GETPIVOTDATA(IF($J34=1,"StdDev of ACTIVE GHGE, FARM GATE (kg CO2e/kg)","StdDev of GHGE, processor gate (kg CO2e/kg)"),'Pivot Table_GHG'!$A$3,"SUB TYPE",$B34)) -> 0.097833632 | W34: =IF(L34="PROXY",IF(M34>=5,K34,"need group"),IF(M34>=5,"DIRECT","need group")) -> greens | X34: =IF($W34="DIRECT",M34,DCOUNT('literature entries'!$D:$AI,IF($J34=1,"ACTIVE CED, FARM GATE (MJ/kg)","CED, processor gate (MJ/kg)"),INDIRECT($W34))) -> 10 | Y34: =IF($W34="DIRECT","",DAVERAGE('literature entries'!$D:$AI,IF($J34=1,"ACTIVE CED, FARM GATE (MJ/kg)","CED, processor gate (MJ/kg)"),INDIRECT($W34))) -> 2.5657275 | Z34: =IF($W34="DIRECT",$O34,DSTDEV('literature entries'!$D:$AI,IF($J34=1,"ACTIVE CED, FARM GATE (MJ/kg)","CED, processor gate (MJ/kg)"),INDIRECT($W34))) -> 1.5197673 | AA34: =IF($W34="DIRECT",$O34,$Z34/$Y34*$N34) -> 1.5197673 | AB34: =IF(P34="PROXY",IF(Q34>=5,K34,"need group"),IF(Q34>=5,"DIRECT","need group")) -> greens | AC34: =IF($AB34="DIRECT",Q34,DCOUNT('literature entries'!$D:$AI,IF($J34=1,"ACTIVE GHGE, FARM GATE (kg CO2e/kg)","GHGE, processor gate (kg CO2e/kg)"),INDIRECT($AB34))) -> 22 | AD34: =IF($AB34="DIRECT","",DAVERAGE('literature entries'!$D:$AI,IF($J34=1,"ACTIVE GHGE, FARM GATE (kg CO2e/kg)","GHGE, processor gate (kg CO2e/kg)"),INDIRECT($AB34))) -> 0.18561974 | AE34: =IF($AB34="DIRECT",$S34,DSTDEV('literature entries'!$D:$AI,IF($J34=1,"ACTIVE GHGE, FARM GATE (kg CO2e/kg)","GHGE, processor gate (kg CO2e/kg)"),INDIRECT($AB34))) -> 0.097833632 | AF34: =IF($AB34="DIRECT",$S34,$AE34/$AD34*$R34) -> 0.097833632
A35: 200101000 | B35: Chicory, tops | C35: weight of leaves | E35: 1557 | F35: =N35*H35+T35 -> 1.21476 | G35: =R35*H35+U35 -> 0.063794 | H35: 1.146 | I35: FICRCD | J35: 1 | K35: Escarole | L35: =IF(ISERROR(GETPIVOTDATA(IF($J35=1,"Count of ACTIVE CED, FARM GATE (MJ/kg)","Count of CED, processor gate (MJ/kg)"),'Pivot Table_CED'!$A$3,"SUB TYPE",$B35)),"PROXY",IF(GETPIVOTDATA(IF($J35=1,"Count of ACTIVE CED, FARM GATE (MJ/kg)","Count of CED, processor gate (MJ/kg)"),'Pivot Table_CED'!$A$3,"SUB TYPE",$B35)=0,"PROXY","DB value")) -> PROXY | M35: =IF($L35="PROXY",DCOUNT('literature entries'!$D:$AI,IF($J35=1,"ACTIVE CED, FARM GATE (MJ/kg)","CED, processor gate (MJ/kg)"),INDIRECT($K35)),GETPIVOTDATA(IF($J35=1,"Count of ACTIVE CED, FARM GATE (MJ/kg)","Count of CED, processor gate (MJ/kg)"),'Pivot Table_CED'!$A$3,"SUB TYPE",$B35)) -> 3 | N35: =IF($L35="PROXY",DAVERAGE('literature entries'!$D:$AI,IF($J35=1,"ACTIVE CED, FARM GATE (MJ/kg)","CED, processor gate (MJ/kg)"),INDIRECT($K35)),GETPIVOTDATA(IF($J35=1,"Average of ACTIVE CED, FARM GATE (MJ/kg)","Average of CED, processor gate (MJ/kg)"),'Pivot Table_CED'!$A$3,"SUB TYPE",$B35)) -> 1.06 | O35: =IF($L35="PROXY",DSTDEV('literature entries'!D:AI,IF($J35=1,"ACTIVE CED, FARM GATE (MJ/kg)","CED, processor gate (MJ/kg)"),INDIRECT($K35)),GETPIVOTDATA(IF($J35=1,"StdDev of ACTIVE CED, FARM GATE (MJ/kg)","StdDev of CED, processor gate (MJ/kg)"),'Pivot Table_CED'!$A$3,"SUB TYPE",$B35)) -> 0.28583212 | P35: =IF(ISERROR(GETPIVOTDATA(IF($J35=1,"Count of ACTIVE GHGE, FARM GATE (kg CO2e/kg)","Count of GHGE, processor gate (kg CO2e/kg)"),'Pivot Table_GHG'!$A$3,"SUB TYPE",$B35)),"PROXY",IF(GETPIVOTDATA(IF($J35=1,"Count of ACTIVE GHGE, FARM GATE (kg CO2e/kg)","Count of GHGE, processor gate (kg CO2e/kg)"),'Pivot Table_GHG'!$A$3,"SUB TYPE",$B35)=0,"PROXY","DB value")) -> PROXY | Q35: =IF($P35="PROXY",DCOUNT('literature entries'!$D:$AI,IF($J35=1,"ACTIVE GHGE, FARM GATE (kg CO2e/kg)","GHGE, processor gate (kg CO2e/kg)"),INDIRECT($K35)),GETPIVOTDATA(IF($J35=1,"ACTIVE GHGE, FARM GATE (kg CO2e/kg)","Count of GHGE, processor gate (kg CO2e/kg)"),'Pivot Table_GHG'!$A$3,"SUB TYPE",$B35)) -> 3 | R35: =IF($P35="PROXY",DAVERAGE('literature entries'!$D:$AI,IF($J35=1,"ACTIVE GHGE, FARM GATE (kg CO2e/kg)","GHGE, processor gate (kg CO2e/kg)"),INDIRECT($K35)),GETPIVOTDATA(IF($J35=1,"Average of ACTIVE GHGE, FARM GATE (kg CO2e/kg)","Average of GHGE, processor gate (kg CO2e/kg)"),'Pivot Table_GHG'!$A$3,"SUB TYPE",$B35)) -> 0.055666667 | S35: =IF($P35="PROXY",DSTDEV('literature entries'!$D:$AI,IF($J35=1,"ACTIVE GHGE, FARM GATE (kg CO2e/kg)","GHGE, processor gate (kg CO2e/kg)"),INDIRECT($K35)),GETPIVOTDATA(IF($J35=1,"StdDev of ACTIVE GHGE, FARM GATE (kg CO2e/kg)","StdDev of GHGE, processor gate (kg CO2e/kg)"),'Pivot Table_GHG'!$A$3,"SUB TYPE",$B35)) -> 0.0037287174 | W35: greens | X35: =IF($W35="DIRECT",M35,DCOUNT('literature entries'!$D:$AI,IF($J35=1,"ACTIVE CED, FARM GATE (MJ/kg)","CED, processor gate (MJ/kg)"),INDIRECT($W35))) -> 10 | Y35: =IF($W35="DIRECT","",DAVERAGE('literature entries'!$D:$AI,IF($J35=1,"ACTIVE CED, FARM GATE (MJ/kg)","CED, processor gate (MJ/kg)"),INDIRECT($W35))) -> 2.5657275 | Z35: =IF($W35="DIRECT",$O35,DSTDEV('literature entries'!$D:$AI,IF($J35=1,"ACTIVE CED, FARM GATE (MJ/kg)","CED, processor gate (MJ/kg)"),INDIRECT($W35))) -> 1.5197673 | AA35: =IF($W35="DIRECT",$O35,$Z35/$Y35*$N35) -> 0.62787391 | AB35: greens | AC35: =IF($AB35="DIRECT",Q35,DCOUNT('literature entries'!$D:$AI,IF($J35=1,"ACTIVE GHGE, FARM GATE (kg CO2e/kg)","GHGE, processor gate (kg CO2e/kg)"),INDIRECT($AB35))) -> 22 | AD35: =IF($AB35="DIRECT","",DAVERAGE('literature entries'!$D:$AI,IF($J35=1,"ACTIVE GHGE, FARM GATE (kg CO2e/kg)","GHGE, processor gate (kg CO2e/kg)"),INDIRECT($AB35))) -> 0.18561974 | AE35: =IF($AB35="DIRECT",$S35,DSTDEV('literature entries'!$D:$AI,IF($J35=1,"ACTIVE GHGE, FARM GATE (kg CO2e/kg)","GHGE, processor gate (kg CO2e/kg)"),INDIRECT($AB35))) -> 0.097833632 | AF35: =IF($AB35="DIRECT",$S35,$AE35/$AD35*$R35) -> 0.029339941
A36: 200140000 | B36: Dasheen, leaves | C36: weight of the leaves | D36: Includes taro. | E36: 3 | F36: =N36*H36+T36 -> 2.5657275 | G36: =R36*H36+U36 -> 0.18561974 | H36: 1 | I36: None | J36: 1 | K36: greens | L36: =IF(ISERROR(GETPIVOTDATA(IF($J36=1,"Count of ACTIVE CED, FARM GATE (MJ/kg)","Count of CED, processor gate (MJ/kg)"),'Pivot Table_CED'!$A$3,"SUB TYPE",$B36)),"PROXY",IF(GETPIVOTDATA(IF($J36=1,"Count of ACTIVE CED, FARM GATE (MJ/kg)","Count of CED, processor gate (MJ/kg)"),'Pivot Table_CED'!$A$3,"SUB TYPE",$B36)=0,"PROXY","DB value")) -> PROXY | M36: =IF($L36="PROXY",DCOUNT('literature entries'!$D:$AI,IF($J36=1,"ACTIVE CED, FARM GATE (MJ/kg)","CED, processor gate (MJ/kg)"),INDIRECT($K36)),GETPIVOTDATA(IF($J36=1,"Count of ACTIVE CED, FARM GATE (MJ/kg)","Count of CED, processor gate (MJ/kg)"),'Pivot Table_CED'!$A$3,"SUB TYPE",$B36)) -> 10 | N36: =IF($L36="PROXY",DAVERAGE('literature entries'!$D:$AI,IF($J36=1,"ACTIVE CED, FARM GATE (MJ/kg)","CED, processor gate (MJ/kg)"),INDIRECT($K36)),GETPIVOTDATA(IF($J36=1,"Average of ACTIVE CED, FARM GATE (MJ/kg)","Average of CED, processor gate (MJ/kg)"),'Pivot Table_CED'!$A$3,"SUB TYPE",$B36)) -> 2.5657275 | O36: =IF($L36="PROXY",DSTDEV('literature entries'!D:AI,IF($J36=1,"ACTIVE CED, FARM GATE (MJ/kg)","CED, processor gate (MJ/kg)"),INDIRECT($K36)),GETPIVOTDATA(IF($J36=1,"StdDev of ACTIVE CED, FARM GATE (MJ/kg)","StdDev of CED, processor gate (MJ/kg)"),'Pivot Table_CED'!$A$3,"SUB TYPE",$B36)) -> 1.5197673 | P36: =IF(ISERROR(GETPIVOTDATA(IF($J36=1,"Count of ACTIVE GHGE, FARM GATE (kg CO2e/kg)","Count of GHGE, processor gate (kg CO2e/kg)"),'Pivot Table_GHG'!$A$3,"SUB TYPE",$B36)),"PROXY",IF(GETPIVOTDATA(IF($J36=1,"Count of ACTIVE GHGE, FARM GATE (kg CO2e/kg)","Count of GHGE, processor gate (kg CO2e/kg)"),'Pivot Table_GHG'!$A$3,"SUB TYPE",$B36)=0,"PROXY","DB value")) -> PROXY | Q36: =IF($P36="PROXY",DCOUNT('literature entries'!$D:$AI,IF($J36=1,"ACTIVE GHGE, FARM GATE (kg CO2e/kg)","GHGE, processor gate (kg CO2e/kg)"),INDIRECT($K36)),GETPIVOTDATA(IF($J36=1,"ACTIVE GHGE, FARM GATE (kg CO2e/kg)","Count of GHGE, processor gate (kg CO2e/kg)"),'Pivot Table_GHG'!$A$3,"SUB TYPE",$B36)) -> 22 | R36: =IF($P36="PROXY",DAVERAGE('literature entries'!$D:$AI,IF($J36=1,"ACTIVE GHGE, FARM GATE (kg CO2e/kg)","GHGE, processor gate (kg CO2e/kg)"),INDIRECT($K36)),GETPIVOTDATA(IF($J36=1,"Average of ACTIVE GHGE, FARM GATE (kg CO2e/kg)","Average of GHGE, processor gate (kg CO2e/kg)"),'Pivot Table_GHG'!$A$3,"SUB TYPE",$B36)) -> 0.18561974 | S36: =IF($P36="PROXY",DSTDEV('literature entries'!$D:$AI,IF($J36=1,"ACTIVE GHGE, FARM GATE (kg CO2e/kg)","GHGE, processor gate (kg CO2e/kg)"),INDIRECT($K36)),GETPIVOTDATA(IF($J36=1,"StdDev of ACTIVE GHGE, FARM GATE (kg CO2e/kg)","StdDev of GHGE, processor gate (kg CO2e/kg)"),'Pivot Table_GHG'!$A$3,"SUB TYPE",$B36)) -> 0.097833632 | W36: =IF(L36="PROXY",IF(M36>=5,K36,"need group"),IF(M36>=5,"DIRECT","need group")) -> greens | X36: =IF($W36="DIRECT",M36,DCOUNT('literature entries'!$D:$AI,IF($J36=1,"ACTIVE CED, FARM GATE (MJ/kg)","CED, processor gate (MJ/kg)"),INDIRECT($W36))) -> 10 | Y36: =IF($W36="DIRECT","",DAVERAGE('literature entries'!$D:$AI,IF($J36=1,"ACTIVE CED, FARM GATE (MJ/kg)","CED, processor gate (MJ/kg)"),INDIRECT($W36))) -> 2.5657275 | Z36: =IF($W36="DIRECT",$O36,DSTDEV('literature entries'!$D:$AI,IF($J36=1,"ACTIVE CED, FARM GATE (MJ/kg)","CED, processor gate (MJ/kg)"),INDIRECT($W36))) -> 1.5197673 | AA36: =IF($W36="DIRECT",$O36,$Z36/$Y36*$N36) -> 1.5197673 | AB36: =IF(P36="PROXY",IF(Q36>=5,K36,"need group"),IF(Q36>=5,"DIRECT","need group")) -> greens | AC36: =IF($AB36="DIRECT",Q36,DCOUNT('literature entries'!$D:$AI,IF($J36=1,"ACTIVE GHGE, FARM GATE (kg CO2e/kg)","GHGE, processor gate (kg CO2e/kg)"),INDIRECT($AB36))) -> 22 | AD36: =IF($AB36="DIRECT","",DAVERAGE('literature entries'!$D:$AI,IF($J36=1,"ACTIVE GHGE, FARM GATE (kg CO2e/kg)","GHGE, processor gate (kg CO2e/kg)"),INDIRECT($AB36))) -> 0.18561974 | AE36: =IF($AB36="DIRECT",$S36,DSTDEV('literature entries'!$D:$AI,IF($J36=1,"ACTIVE GHGE, FARM GATE (kg CO2e/kg)","GHGE, processor gate (kg CO2e/kg)"),INDIRECT($AB36))) -> 0.097833632 | AF36: =IF($AB36="DIRECT",$S36,$AE36/$AD36*$R36) -> 0.097833632
A37: 301165000 | B37: Garlic, bulb | C37: dry weight of bulb; excluding skin (outer scales) | D37: same as Garlic, bulb includes great headed garlic, serpent garlic, and elephant garlic. | E37: 33951 | F37: =N37*H37+T37 -> 2.9321299 | G37: =R37*H37+U37 -> 0.74251667 | H37: 1.15 | I37: FICRCD | J37: 1 | K37: onion_bulb | L37: =IF(ISERROR(GETPIVOTDATA(IF($J37=1,"Count of ACTIVE CED, FARM GATE (MJ/kg)","Count of CED, processor gate (MJ/kg)"),'Pivot Table_CED'!$A$3,"SUB TYPE",$B37)),"PROXY",IF(GETPIVOTDATA(IF($J37=1,"Count of ACTIVE CED, FARM GATE (MJ/kg)","Count of CED, processor gate (MJ/kg)"),'Pivot Table_CED'!$A$3,"SUB TYPE",$B37)=0,"PROXY","DB value")) -> PROXY | M37: =IF($L37="PROXY",DCOUNT('literature entries'!$D:$AI,IF($J37=1,"ACTIVE CED, FARM GATE (MJ/kg)","CED, processor gate (MJ/kg)"),INDIRECT($K37)),GETPIVOTDATA(IF($J37=1,"Count of ACTIVE CED, FARM GATE (MJ/kg)","Count of CED, processor gate (MJ/kg)"),'Pivot Table_CED'!$A$3,"SUB TYPE",$B37)) -> 7 | N37: =IF($L37="PROXY",DAVERAGE('literature entries'!$D:$AI,IF($J37=1,"ACTIVE CED, FARM GATE (MJ/kg)","CED, processor gate (MJ/kg)"),INDIRECT($K37)),GETPIVOTDATA(IF($J37=1,"Average of ACTIVE CED, FARM GATE (MJ/kg)","Average of CED, processor gate (MJ/kg)"),'Pivot Table_CED'!$A$3,"SUB TYPE",$B37)) -> 2.5496782 | O37: =IF($L37="PROXY",DSTDEV('literature entries'!D:AI,IF($J37=1,"ACTIVE CED, FARM GATE (MJ/kg)","CED, processor gate (MJ/kg)"),INDIRECT($K37)),GETPIVOTDATA(IF($J37=1,"StdDev of ACTIVE CED, FARM GATE (MJ/kg)","StdDev of CED, processor gate (MJ/kg)"),'Pivot Table_CED'!$A$3,"SUB TYPE",$B37)) -> 1.6075251 | P37: =IF(ISERROR(GETPIVOTDATA(IF($J37=1,"Count of ACTIVE GHGE, FARM GATE (kg CO2e/kg)","Count of GHGE, processor gate (kg CO2e/kg)"),'Pivot Table_GHG'!$A$3,"SUB TYPE",$B37)),"PROXY",IF(GETPIVOTDATA(IF($J37=1,"Count of ACTIVE GHGE, FARM GATE (kg CO2e/kg)","Count of GHGE, processor gate (kg CO2e/kg)"),'Pivot Table_GHG'!$A$3,"SUB TYPE",$B37)=0,"PROXY","DB value")) -> DB value | Q37: =IF($P37="PROXY",DCOUNT('literature entries'!$D:$AI,IF($J37=1,"ACTIVE GHGE, FARM GATE (kg CO2e/kg)","GHGE, processor gate (kg CO2e/kg)"),INDIRECT($K37)),GETPIVOTDATA(IF($J37=1,"ACTIVE GHGE, FARM GATE (kg CO2e/kg)","Count of GHGE, processor gate (kg CO2e/kg)"),'Pivot Table_GHG'!$A$3,"SUB TYPE",$B37)) -> 3 | R37: =IF($P37="PROXY",DAVERAGE('literature entries'!$D:$AI,IF($J37=1,"ACTIVE GHGE, FARM GATE (kg CO2e/kg)","GHGE, processor gate (kg CO2e/kg)"),INDIRECT($K37)),GETPIVOTDATA(IF($J37=1,"Average of ACTIVE GHGE, FARM GATE (kg CO2e/kg)","Average of GHGE, processor gate (kg CO2e/kg)"),'Pivot Table_GHG'!$A$3,"SUB TYPE",$B37)) -> 0.64566667 | S37: =IF($P37="PROXY",DSTDEV('literature entries'!$D:$AI,IF($J37=1,"ACTIVE GHGE, FARM GATE (kg CO2e/kg)","GHGE, processor gate (kg CO2e/kg)"),INDIRECT($K37)),GETPIVOTDATA(IF($J37=1,"StdDev of ACTIVE GHGE, FARM GATE (kg CO2e/kg)","StdDev of GHGE, processor gate (kg CO2e/kg)"),'Pivot Table_GHG'!$A$3,"SUB TYPE",$B37)) -> 0.065622659 | W37: =IF(L37="PROXY",IF(M37>=5,K37,"need group"),IF(M37>=5,"DIRECT","need group")) -> onion_bulb | X37: =IF($W37="DIRECT",M37,DCOUNT('literature entries'!$D:$AI,IF($J37=1,"ACTIVE CED, FARM GATE (MJ/kg)","CED, processor gate (MJ/kg)"),INDIRECT($W37))) -> 7 | Y37: =IF($W37="DIRECT","",DAVERAGE('literature entries'!$D:$AI,IF($J37=1,"ACTIVE CED, FARM GATE (MJ/kg)","CED, processor gate (MJ/kg)"),INDIRECT($W37))) -> 2.5496782 | Z37: =IF($W37="DIRECT",$O37,DSTDEV('literature entries'!$D:$AI,IF($J37=1,"ACTIVE CED, FARM GATE (MJ/kg)","CED, processor gate (MJ/kg)"),INDIRECT($W37))) -> 1.6075251 | AA37: =IF($W37="DIRECT",$O37,$Z37/$Y37*$N37) -> 1.6075251 | AB37: onion_bulb | AC37: =IF($AB37="DIRECT",Q37,DCOUNT('literature entries'!$D:$AI,IF($J37=1,"ACTIVE GHGE, FARM GATE (kg CO2e/kg)","GHGE, processor gate (kg CO2e/kg)"),INDIRECT($AB37))) -> 7 | AD37: =IF($AB37="DIRECT","",DAVERAGE('literature entries'!$D:$AI,IF($J37=1,"ACTIVE GHGE, FARM GATE (kg CO2e/kg)","GHGE, processor gate (kg CO2e/kg)"),INDIRECT($AB37))) -> 0.24193689 | AE37: =IF($AB37="DIRECT",$S37,DSTDEV('literature entries'!$D:$AI,IF($J37=1,"ACTIVE GHGE, FARM GATE (kg CO2e/kg)","GHGE, processor gate (kg CO2e/kg)"),INDIRECT($AB37))) -> 0.155461 | AF37: =IF($AB37="DIRECT",$S37,$AE37/$AD37*$R37) -> 0.414885
A38: 301237000 | B38: Onion, bulb | C38: weight of bulb; excluding outer skin | D38: Includes Daylily; Fritillaria, bulb; Lily; Chinese onion, bulb. | E38: 33634 | F38: =N38*H38+T38 -> 2.8301428 | G38: =R38*H38+U38 -> 0.26854995 | H38: 1.11 | I38: FICRCD | J38: 1 | L38: =IF(ISERROR(GETPIVOTDATA(IF($J38=1,"Count of ACTIVE CED, FARM GATE (MJ/kg)","Count of CED, processor gate (MJ/kg)"),'Pivot Table_CED'!$A$3,"SUB TYPE",$B38)),"PROXY",IF(GETPIVOTDATA(IF($J38=1,"Count of ACTIVE CED, FARM GATE (MJ/kg)","Count of CED, processor gate (MJ/kg)"),'Pivot Table_CED'!$A$3,"SUB TYPE",$B38)=0,"PROXY","DB value")) -> DB value | M38: =IF($L38="PROXY",DCOUNT('literature entries'!$D:$AI,IF($J38=1,"ACTIVE CED, FARM GATE (MJ/kg)","CED, processor gate (MJ/kg)"),INDIRECT($K38)),GETPIVOTDATA(IF($J38=1,"Count of ACTIVE CED, FARM GATE (MJ/kg)","Count of CED, processor gate (MJ/kg)"),'Pivot Table_CED'!$A$3,"SUB TYPE",$B38)) -> 7 | N38: =IF($L38="PROXY",DAVERAGE('literature entries'!$D:$AI,IF($J38=1,"ACTIVE CED, FARM GATE (MJ/kg)","CED, processor gate (MJ/kg)"),INDIRECT($K38)),GETPIVOTDATA(IF($J38=1,"Average of ACTIVE CED, FARM GATE (MJ/kg)","Average of CED, processor gate (MJ/kg)"),'Pivot Table_CED'!$A$3,"SUB TYPE",$B38)) -> 2.5496782 | O38: =IF($L38="PROXY",DSTDEV('literature entries'!D:AI,IF($J38=1,"ACTIVE CED, FARM GATE (MJ/kg)","CED, processor gate (MJ/kg)"),INDIRECT($K38)),GETPIVOTDATA(IF($J38=1,"StdDev of ACTIVE CED, FARM GATE (MJ/kg)","StdDev of CED, processor gate (MJ/kg)"),'Pivot Table_CED'!$A$3,"SUB TYPE",$B38)) -> 1.6075251 | P38: =IF(ISERROR(GETPIVOTDATA(IF($J38=1,"Count of ACTIVE GHGE, FARM GATE (kg CO2e/kg)","Count of GHGE, processor gate (kg CO2e/kg)"),'Pivot Table_GHG'!$A$3,"SUB TYPE",$B38)),"PROXY",IF(GETPIVOTDATA(IF($J38=1,"Count of ACTIVE GHGE, FARM GATE (kg CO2e/kg)","Count of GHGE, processor gate (kg CO2e/kg)"),'Pivot Table_GHG'!$A$3,"SUB TYPE",$B38)=0,"PROXY","DB value")) -> DB value | Q38: =IF($P38="PROXY",DCOUNT('literature entries'!$D:$AI,IF($J38=1,"ACTIVE GHGE, FARM GATE (kg CO2e/kg)","GHGE, processor gate (kg CO2e/kg)"),INDIRECT($K38)),GETPIVOTDATA(IF($J38=1,"ACTIVE GHGE, FARM GATE (kg CO2e/kg)","Count of GHGE, processor gate (kg CO2e/kg)"),'Pivot Table_GHG'!$A$3,"SUB TYPE",$B38)) -> 7 | R38: =IF($P38="PROXY",DAVERAGE('literature entries'!$D:$AI,IF($J38=1,"ACTIVE GHGE, FARM GATE (kg CO2e/kg)","GHGE, processor gate (kg CO2e/kg)"),INDIRECT($K38)),GETPIVOTDATA(IF($J38=1,"Average of ACTIVE GHGE, FARM GATE (kg CO2e/kg)","Average of GHGE, processor gate (kg CO2e/kg)"),'Pivot Table_GHG'!$A$3,"SUB TYPE",$B38)) -> 0.24193689 | S38: =IF($P38="PROXY",DSTDEV('literature entries'!$D:$AI,IF($J38=1,"ACTIVE GHGE, FARM GATE (kg CO2e/kg)","GHGE, processor gate (kg CO2e/kg)"),INDIRECT($K38)),GETPIVOTDATA(IF($J38=1,"StdDev of ACTIVE GHGE, FARM GATE (kg CO2e/kg)","StdDev of GHGE, processor gate (kg CO2e/kg)"),'Pivot Table_GHG'!$A$3,"SUB TYPE",$B38)) -> 0.155461 | W38: =IF(L38="PROXY",IF(M38>=5,K38,"need group"),IF(M38>=5,"DIRECT","need group")) -> DIRECT | X38: =IF($W38="DIRECT",M38,DCOUNT('literature entries'!$D:$AI,IF($J38=1,"ACTIVE CED, FARM GATE (MJ/kg)","CED, processor gate (MJ/kg)"),INDIRECT($W38))) -> 7 | Y38: =IF($W38="DIRECT","",DAVERAGE('literature entries'!$D:$AI,IF($J38=1,"ACTIVE CED, FARM GATE (MJ/kg)","CED, processor gate (MJ/kg)"),INDIRECT($W38))) | Z38: =IF($W38="DIRECT",$O38,DSTDEV('literature entries'!$D:$AI,IF($J38=1,"ACTIVE CED, FARM GATE (MJ/kg)","CED, processor gate (MJ/kg)"),INDIRECT($W38))) -> 1.6075251 | AA38: =IF($W38="DIRECT",$O38,$Z38/$Y38*$N38) -> 1.6075251 | AB38: =IF(P38="PROXY",IF(Q38>=5,K38,"need group"),IF(Q38>=5,"DIRECT","need group")) -> DIRECT | AC38: =IF($AB38="DIRECT",Q38,DCOUNT('literature entries'!$D:$AI,IF($J38=1,"ACTIVE GHGE, FARM GATE (kg CO2e/kg)","GHGE, processor gate (kg CO2e/kg)"),INDIRECT($AB38))) -> 7 | AD38: =IF($AB38="DIRECT","",DAVERAGE('literature entries'!$D:$AI,IF($J38=1,"ACTIVE GHGE, FARM GATE (kg CO2e/kg)","GHGE, processor gate (kg CO2e/kg)"),INDIRECT($AB38))) | AE38: =IF($AB38="DIRECT",$S38,DSTDEV('literature entries'!$D:$AI,IF($J38=1,"ACTIVE GHGE, FARM GATE (kg CO2e/kg)","GHGE, processor gate (kg CO2e/kg)"),INDIRECT($AB38))) -> 0.155461 | AF38: =IF($AB38="DIRECT",$S38,$AE38/$AD38*$R38) -> 0.155461
A39: 301238000 | B39: Onion, bulb, dried | C39: dry weight of bulb; excluding outer skin | D39: Includes Daylily; Fritillaria, bulb; Lily; Chinese onion, bulb. | E39: 30475 | F39: =N39*H39+T39 -> 22.151604 | G39: =R39*H39+U39 -> 2.1019477 | H39: 8.688 | I39: NNDSR28 | J39: 1 | K39: onion_bulb | L39: =IF(ISERROR(GETPIVOTDATA(IF($J39=1,"Count of ACTIVE CED, FARM GATE (MJ/kg)","Count of CED, processor gate (MJ/kg)"),'Pivot Table_CED'!$A$3,"SUB TYPE",$B39)),"PROXY",IF(GETPIVOTDATA(IF($J39=1,"Count of ACTIVE CED, FARM GATE (MJ/kg)","Count of CED, processor gate (MJ/kg)"),'Pivot Table_CED'!$A$3,"SUB TYPE",$B39)=0,"PROXY","DB value")) -> PROXY | M39: =IF($L39="PROXY",DCOUNT('literature entries'!$D:$AI,IF($J39=1,"ACTIVE CED, FARM GATE (MJ/kg)","CED, processor gate (MJ/kg)"),INDIRECT($K39)),GETPIVOTDATA(IF($J39=1,"Count of ACTIVE CED, FARM GATE (MJ/kg)","Count of CED, processor gate (MJ/kg)"),'Pivot Table_CED'!$A$3,"SUB TYPE",$B39)) -> 7 | N39: =IF($L39="PROXY",DAVERAGE('literature entries'!$D:$AI,IF($J39=1,"ACTIVE CED, FARM GATE (MJ/kg)","CED, processor gate (MJ/kg)"),INDIRECT($K39)),GETPIVOTDATA(IF($J39=1,"Average of ACTIVE CED, FARM GATE (MJ/kg)","Average of CED, processor gate (MJ/kg)"),'Pivot Table_CED'!$A$3,"SUB TYPE",$B39)) -> 2.5496782 | O39: =IF($L39="PROXY",DSTDEV('literature entries'!D:AI,IF($J39=1,"ACTIVE CED, FARM GATE (MJ/kg)","CED, processor gate (MJ/kg)"),INDIRECT($K39)),GETPIVOTDATA(IF($J39=1,"StdDev of ACTIVE CED, FARM GATE (MJ/kg)","StdDev of CED, processor gate (MJ/kg)"),'Pivot Table_CED'!$A$3,"SUB TYPE",$B39)) -> 1.6075251 | P39: =IF(ISERROR(GETPIVOTDATA(IF($J39=1,"Count of ACTIVE GHGE, FARM GATE (kg CO2e/kg)","Count of GHGE, processor gate (kg CO2e/kg)"),'Pivot Table_GHG'!$A$3,"SUB TYPE",$B39)),"PROXY",IF(GETPIVOTDATA(IF($J39=1,"Count of ACTIVE GHGE, FARM GATE (kg CO2e/kg)","Count of GHGE, processor gate (kg CO2e/kg)"),'Pivot Table_GHG'!$A$3,"SUB TYPE",$B39)=0,"PROXY","DB value")) -> PROXY | Q39: =IF($P39="PROXY",DCOUNT('literature entries'!$D:$AI,IF($J39=1,"ACTIVE GHGE, FARM GATE (kg CO2e/kg)","GHGE, processor gate (kg CO2e/kg)"),INDIRECT($K39)),GETPIVOTDATA(IF($J39=1,"ACTIVE GHGE, FARM GATE (kg CO2e/kg)","Count of GHGE, processor gate (kg CO2e/kg)"),'Pivot Table_GHG'!$A$3,"SUB TYPE",$B39)) -> 7 | R39: =IF($P39="PROXY",DAVERAGE('literature entries'!$D:$AI,IF($J39=1,"ACTIVE GHGE, FARM GATE (kg CO2e/kg)","GHGE, processor gate (kg CO2e/kg)"),INDIRECT($K39)),GETPIVOTDATA(IF($J39=1,"Average of ACTIVE GHGE, FARM GATE (kg CO2e/kg)","Average of GHGE, processor gate (kg CO2e/kg)"),'Pivot Table_GHG'!$A$3,"SUB TYPE",$B39)) -> 0.24193689 | S39: =IF($P39="PROXY",DSTDEV('literature entries'!$D:$AI,IF($J39=1,"ACTIVE GHGE, FARM GATE (kg CO2e/kg)","GHGE, processor gate (kg CO2e/kg)"),INDIRECT($K39)),GETPIVOTDATA(IF($J39=1,"StdDev of ACTIVE GHGE, FARM GATE (kg CO2e/kg)","StdDev of GHGE, processor gate (kg CO2e/kg)"),'Pivot Table_GHG'!$A$3,"SUB TYPE",$B39)) -> 0.155461 | W39: =IF(L39="PROXY",IF(M39>=5,K39,"need group"),IF(M39>=5,"DIRECT","need group")) -> onion_bulb | X39: =IF($W39="DIRECT",M39,DCOUNT('literature entries'!$D:$AI,IF($J39=1,"ACTIVE CED, FARM GATE (MJ/kg)","CED, processor gate (MJ/kg)"),INDIRECT($W39))) -> 7 | Y39: =IF($W39="DIRECT","",DAVERAGE('literature entries'!$D:$AI,IF($J39=1,"ACTIVE CED, FARM GATE (MJ/kg)","CED, processor gate (MJ/kg)"),INDIRECT($W39))) -> 2.5496782 | Z39: =IF($W39="DIRECT",$O39,DSTDEV('literature entries'!$D:$AI,IF($J39=1,"ACTIVE CED, FARM GATE (MJ/kg)","CED, processor gate (MJ/kg)"),INDIRECT($W39))) -> 1.6075251 | AA39: =IF($W39="DIRECT",$O39,$Z39/$Y39*$N39) -> 1.6075251 | AB39: =IF(P39="PROXY",IF(Q39>=5,K39,"need group"),IF(Q39>=5,"DIRECT","need group")) -> onion_bulb | AC39: =IF($AB39="DIRECT",Q39,DCOUNT('literature entries'!$D:$AI,IF($J39=1,"ACTIVE GHGE, FARM GATE (kg CO2e/kg)","GHGE, processor gate (kg CO2e/kg)"),INDIRECT($AB39))) -> 7 | AD39: =IF($AB39="DIRECT","",DAVERAGE('literature entries'!$D:$AI,IF($J39=1,"ACTIVE GHGE, FARM GATE (kg CO2e/kg)","GHGE, processor gate (kg CO2e/kg)"),INDIRECT($AB39))) -> 0.24193689 | AE39: =IF($AB39="DIRECT",$S39,DSTDEV('literature entries'!$D:$AI,IF($J39=1,"ACTIVE GHGE, FARM GATE (kg CO2e/kg)","GHGE, processor gate (kg CO2e/kg)"),INDIRECT($AB39))) -> 0.155461 | AF39: =IF($AB39="DIRECT",$S39,$AE39/$AD39*$R39) -> 0.155461
A40: 301338000 | B40: Shallot, bulb | C40: weight of bulb; excluding skin | E40: 6 | F40: =N40*H40+T40 -> 2.8964344 | G40: =R40*H40+U40 -> 0.27484031 | H40: 1.136 | I40: NNDSR28 | J40: 1 | K40: onion_bulb | L40: =IF(ISERROR(GETPIVOTDATA(IF($J40=1,"Count of ACTIVE CED, FARM GATE (MJ/kg)","Count of CED, processor gate (MJ/kg)"),'Pivot Table_CED'!$A$3,"SUB TYPE",$B40)),"PROXY",IF(GETPIVOTDATA(IF($J40=1,"Count of ACTIVE CED, FARM GATE (MJ/kg)","Count of CED, processor gate (MJ/kg)"),'Pivot Table_CED'!$A$3,"SUB TYPE",$B40)=0,"PROXY","DB value")) -> PROXY | M40: =IF($L40="PROXY",DCOUNT('literature entries'!$D:$AI,IF($J40=1,"ACTIVE CED, FARM GATE (MJ/kg)","CED, processor gate (MJ/kg)"),INDIRECT($K40)),GETPIVOTDATA(IF($J40=1,"Count of ACTIVE CED, FARM GATE (MJ/kg)","Count of CED, processor gate (MJ/kg)"),'Pivot Table_CED'!$A$3,"SUB TYPE",$B40)) -> 7 | N40: =IF($L40="PROXY",DAVERAGE('literature entries'!$D:$AI,IF($J40=1,"ACTIVE CED, FARM GATE (MJ/kg)","CED, processor gate (MJ/kg)"),INDIRECT($K40)),GETPIVOTDATA(IF($J40=1,"Average of ACTIVE CED, FARM GATE (MJ/kg)","Average of CED, processor gate (MJ/kg)"),'Pivot Table_CED'!$A$3,"SUB TYPE",$B40)) -> 2.5496782 | O40: =IF($L40="PROXY",DSTDEV('literature entries'!D:AI,IF($J40=1,"ACTIVE CED, FARM GATE (MJ/kg)","CED, processor gate (MJ/kg)"),INDIRECT($K40)),GETPIVOTDATA(IF($J40=1,"StdDev of ACTIVE CED, FARM GATE (MJ/kg)","StdDev of CED, processor gate (MJ/kg)"),'Pivot Table_CED'!$A$3,"SUB TYPE",$B40)) -> 1.6075251 | P40: =IF(ISERROR(GETPIVOTDATA(IF($J40=1,"Count of ACTIVE GHGE, FARM GATE (kg CO2e/kg)","Count of GHGE, processor gate (kg CO2e/kg)"),'Pivot Table_GHG'!$A$3,"SUB TYPE",$B40)),"PROXY",IF(GETPIVOTDATA(IF($J40=1,"Count of ACTIVE GHGE, FARM GATE (kg CO2e/kg)","Count of GHGE, processor gate (kg CO2e/kg)"),'Pivot Table_GHG'!$A$3,"SUB TYPE",$B40)=0,"PROXY","DB value")) -> PROXY | Q40: =IF($P40="PROXY",DCOUNT('literature entries'!$D:$AI,IF($J40=1,"ACTIVE GHGE, FARM GATE (kg CO2e/kg)","GHGE, processor gate (kg CO2e/kg)"),INDIRECT($K40)),GETPIVOTDATA(IF($J40=1,"ACTIVE GHGE, FARM GATE (kg CO2e/kg)","Count of GHGE, processor gate (kg CO2e/kg)"),'Pivot Table_GHG'!$A$3,"SUB TYPE",$B40)) -> 7 | R40: =IF($P40="PROXY",DAVERAGE('literature entries'!$D:$AI,IF($J40=1,"ACTIVE GHGE, FARM GATE (kg CO2e/kg)","GHGE, processor gate (kg CO2e/kg)"),INDIRECT($K40)),GETPIVOTDATA(IF($J40=1,"Average of ACTIVE GHGE, FARM GATE (kg CO2e/kg)","Average of GHGE, processor gate (kg CO2e/kg)"),'Pivot Table_GHG'!$A$3,"SUB TYPE",$B40)) -> 0.24193689 | S40: =IF($P40="PROXY",DSTDEV('literature entries'!$D:$AI,IF($J40=1,"ACTIVE GHGE, FARM GATE (kg CO2e/kg)","GHGE, processor gate (kg CO2e/kg)"),INDIRECT($K40)),GETPIVOTDATA(IF($J40=1,"StdDev of ACTIVE GHGE, FARM GATE (kg CO2e/kg)","StdDev of GHGE, processor gate (kg CO2e/kg)"),'Pivot Table_GHG'!$A$3,"SUB TYPE",$B40)) -> 0.155461 | W40: =IF(L40="PROXY",IF(M40>=5,K40,"need group"),IF(M40>=5,"DIRECT","need group")) -> onion_bulb | X40: =IF($W40="DIRECT",M40,DCOUNT('literature entries'!$D:$AI,IF($J40=1,"ACTIVE CED, FARM GATE (MJ/kg)","CED, processor gate (MJ/kg)"),INDIRECT($W40))) -> 7 | Y40: =IF($W40="DIRECT","",DAVERAGE('literature entries'!$D:$AI,IF($J40=1,"ACTIVE CED, FARM GATE (MJ/kg)","CED, processor gate (MJ/kg)"),INDIRECT($W40))) -> 2.5496782 | Z40: =IF($W40="DIRECT",$O40,DSTDEV('literature entries'!$D:$AI,IF($J40=1,"ACTIVE CED, FARM GATE (MJ/kg)","CED, processor gate (MJ/kg)"),INDIRECT($W40))) -> 1.6075251 | AA40: =IF($W40="DIRECT",$O40,$Z40/$Y40*$N40) -> 1.6075251 | AB40: =IF(P40="PROXY",IF(Q40>=5,K40,"need group"),IF(Q40>=5,"DIRECT","need group")) -> onion_bulb | AC40: =IF($AB40="DIRECT",Q40,DCOUNT('literature entries'!$D:$AI,IF($J40=1,"ACTIVE GHGE, FARM GATE (kg CO2e/kg)","GHGE, processor gate (kg CO2e/kg)"),INDIRECT($AB40))) -> 7 | AD40: =IF($AB40="DIRECT","",DAVERAGE('literature entries'!$D:$AI,IF($J40=1,"ACTIVE GHGE, FARM GATE (kg CO2e/kg)","GHGE, processor gate (kg CO2e/kg)"),INDIRECT($AB40))) -> 0.24193689 | AE40: =IF($AB40="DIRECT",$S40,DSTDEV('literature entries'!$D:$AI,IF($J40=1,"ACTIVE GHGE, FARM GATE (kg CO2e/kg)","GHGE, processor gate (kg CO2e/kg)"),INDIRECT($AB40))) -> 0.155461 | AF40: =IF($AB40="DIRECT",$S40,$AE40/$AD40*$R40) -> 0.155461
A41: 302103000 | B41: Chive, fresh leaves | C41: weight of fresh leaves | D41: Includes Chinese chives. | E41: 1638 | F41: =N41*H41+T41 -> 1.5507452 | G41: =R41*H41+U41 -> 0.22093144 | H41: 1 | I41: FICRCD | J41: 1 | K41: spinach | L41: =IF(ISERROR(GETPIVOTDATA(IF($J41=1,"Count of ACTIVE CED, FARM GATE (MJ/kg)","Count of CED, processor gate (MJ/kg)"),'Pivot Table_CED'!$A$3,"SUB TYPE",$B41)),"PROXY",IF(GETPIVOTDATA(IF($J41=1,"Count of ACTIVE CED, FARM GATE (MJ/kg)","Count of CED, processor gate (MJ/kg)"),'Pivot Table_CED'!$A$3,"SUB TYPE",$B41)=0,"PROXY","DB value")) -> PROXY | M41: =IF($L41="PROXY",DCOUNT('literature entries'!$D:$AI,IF($J41=1,"ACTIVE CED, FARM GATE (MJ/kg)","CED, processor gate (MJ/kg)"),INDIRECT($K41)),GETPIVOTDATA(IF($J41=1,"Count of ACTIVE CED, FARM GATE (MJ/kg)","Count of CED, processor gate (MJ/kg)"),'Pivot Table_CED'!$A$3,"SUB TYPE",$B41)) -> 3 | N41: =IF($L41="PROXY",DAVERAGE('literature entries'!$D:$AI,IF($J41=1,"ACTIVE CED, FARM GATE (MJ/kg)","CED, processor gate (MJ/kg)"),INDIRECT($K41)),GETPIVOTDATA(IF($J41=1,"Average of ACTIVE CED, FARM GATE (MJ/kg)","Average of CED, processor gate (MJ/kg)"),'Pivot Table_CED'!$A$3,"SUB TYPE",$B41)) -> 1.5507452 | O41: =IF($L41="PROXY",DSTDEV('literature entries'!D:AI,IF($J41=1,"ACTIVE CED, FARM GATE (MJ/kg)","CED, processor gate (MJ/kg)"),INDIRECT($K41)),GETPIVOTDATA(IF($J41=1,"StdDev of ACTIVE CED, FARM GATE (MJ/kg)","StdDev of CED, processor gate (MJ/kg)"),'Pivot Table_CED'!$A$3,"SUB TYPE",$B41)) -> 1.5455737 | P41: =IF(ISERROR(GETPIVOTDATA(IF($J41=1,"Count of ACTIVE GHGE, FARM GATE (kg CO2e/kg)","Count of GHGE, processor gate (kg CO2e/kg)"),'Pivot Table_GHG'!$A$3,"SUB TYPE",$B41)),"PROXY",IF(GETPIVOTDATA(IF($J41=1,"Count of ACTIVE GHGE, FARM GATE (kg CO2e/kg)","Count of GHGE, processor gate (kg CO2e/kg)"),'Pivot Table_GHG'!$A$3,"SUB TYPE",$B41)=0,"PROXY","DB value")) -> PROXY | Q41: =IF($P41="PROXY",DCOUNT('literature entries'!$D:$AI,IF($J41=1,"ACTIVE GHGE, FARM GATE (kg CO2e/kg)","GHGE, processor gate (kg CO2e/kg)"),INDIRECT($K41)),GETPIVOTDATA(IF($J41=1,"ACTIVE GHGE, FARM GATE (kg CO2e/kg)","Count of GHGE, processor gate (kg CO2e/kg)"),'Pivot Table_GHG'!$A$3,"SUB TYPE",$B41)) -> 3 | R41: =IF($P41="PROXY",DAVERAGE('literature entries'!$D:$AI,IF($J41=1,"ACTIVE GHGE, FARM GATE (kg CO2e/kg)","GHGE, processor gate (kg CO2e/kg)"),INDIRECT($K41)),GETPIVOTDATA(IF($J41=1,"Average of ACTIVE GHGE, FARM GATE (kg CO2e/kg)","Average of GHGE, processor gate (kg CO2e/kg)"),'Pivot Table_GHG'!$A$3,"SUB TYPE",$B41)) -> 0.22093144 | S41: =IF($P41="PROXY",DSTDEV('literature entries'!$D:$AI,IF($J41=1,"ACTIVE GHGE, FARM GATE (kg CO2e/kg)","GHGE, processor gate (kg CO2e/kg)"),INDIRECT($K41)),GETPIVOTDATA(IF($J41=1,"StdDev of ACTIVE GHGE, FARM GATE (kg CO2e/kg)","StdDev of GHGE, processor gate (kg CO2e/kg)"),'Pivot Table_GHG'!$A$3,"SUB TYPE",$B41)) -> 0.083542949 | W41: greens | X41: =IF($W41="DIRECT",M41,DCOUNT('literature entries'!$D:$AI,IF($J41=1,"ACTIVE CED, FARM GATE (MJ/kg)","CED, processor gate (MJ/kg)"),INDIRECT($W41))) -> 10 | Y41: =IF($W41="DIRECT","",DAVERAGE('literature entries'!$D:$AI,IF($J41=1,"ACTIVE CED, FARM GATE (MJ/kg)","CED, processor gate (MJ/kg)"),INDIRECT($W41))) -> 2.5657275 | Z41: =IF($W41="DIRECT",$O41,DSTDEV('literature entries'!$D:$AI,IF($J41=1,"ACTIVE CED, FARM GATE (MJ/kg)","CED, processor gate (MJ/kg)"),INDIRECT($W41))) -> 1.5197673 | AA41: =IF($W41="DIRECT",$O41,$Z41/$Y41*$N41) -> 0.91855891 | AB41: greens | AC41: =IF($AB41="DIRECT",Q41,DCOUNT('literature entries'!$D:$AI,IF($J41=1,"ACTIVE GHGE, FARM GATE (kg CO2e/kg)","GHGE, processor gate (kg CO2e/kg)"),INDIRECT($AB41))) -> 22 | AD41: =IF($AB41="DIRECT","",DAVERAGE('literature entries'!$D:$AI,IF($J41=1,"ACTIVE GHGE, FARM GATE (kg CO2e/kg)","GHGE, processor gate (kg CO2e/kg)"),INDIRECT($AB41))) -> 0.18561974 | AE41: =IF($AB41="DIRECT",$S41,DSTDEV('literature entries'!$D:$AI,IF($J41=1,"ACTIVE GHGE, FARM GATE (kg CO2e/kg)","GHGE, processor gate (kg CO2e/kg)"),INDIRECT($AB41))) -> 0.097833632 | AF41: =IF($AB41="DIRECT",$S41,$AE41/$AD41*$R41) -> 0.11644518
A42: 302198000 | B42: Leek | C42: weight of whole plant; including leaves and bulb | D42: Includes lady leek and wild leek | E42: 67 | F42: =N42*H42+T42 -> 2.5496782 | G42: =R42*H42+U42 -> 0.069 | H42: 1 | I42: none | J42: 1 | K42: onion_bulb | L42: =IF(ISERROR(GETPIVOTDATA(IF($J42=1,"Count of ACTIVE CED, FARM GATE (MJ/kg)","Count of CED, processor gate (MJ/kg)"),'Pivot Table_CED'!$A$3,"SUB TYPE",$B42)),"PROXY",IF(GETPIVOTDATA(IF($J42=1,"Count of ACTIVE CED, FARM GATE (MJ/kg)","Count of CED, processor gate (MJ/kg)"),'Pivot Table_CED'!$A$3,"SUB TYPE",$B42)=0,"PROXY","DB value")) -> PROXY | M42: =IF($L42="PROXY",DCOUNT('literature entries'!$D:$AI,IF($J42=1,"ACTIVE CED, FARM GATE (MJ/kg)","CED, processor gate (MJ/kg)"),INDIRECT($K42)),GETPIVOTDATA(IF($J42=1,"Count of ACTIVE CED, FARM GATE (MJ/kg)","Count of CED, processor gate (MJ/kg)"),'Pivot Table_CED'!$A$3,"SUB TYPE",$B42)) -> 7 | N42: =IF($L42="PROXY",DAVERAGE('literature entries'!$D:$AI,IF($J42=1,"ACTIVE CED, FARM GATE (MJ/kg)","CED, processor gate (MJ/kg)"),INDIRECT($K42)),GETPIVOTDATA(IF($J42=1,"Average of ACTIVE CED, FARM GATE (MJ/kg)","Average of CED, processor gate (MJ/kg)"),'Pivot Table_CED'!$A$3,"SUB TYPE",$B42)) -> 2.5496782 | O42: =IF($L42="PROXY",DSTDEV('literature entries'!D:AI,IF($J42=1,"ACTIVE CED, FARM GATE (MJ/kg)","CED, processor gate (MJ/kg)"),INDIRECT($K42)),GETPIVOTDATA(IF($J42=1,"StdDev of ACTIVE CED, FARM GATE (MJ/kg)","StdDev of CED, processor gate (MJ/kg)"),'Pivot Table_CED'!$A$3,"SUB TYPE",$B42)) -> 1.6075251 | P42: =IF(ISERROR(GETPIVOTDATA(IF($J42=1,"Count of ACTIVE GHGE, FARM GATE (kg CO2e/kg)","Count of GHGE, processor gate (kg CO2e/kg)"),'Pivot Table_GHG'!$A$3,"SUB TYPE",$B42)),"PROXY",IF(GETPIVOTDATA(IF($J42=1,"Count of ACTIVE GHGE, FARM GATE (kg CO2e/kg)","Count of GHGE, processor gate (kg CO2e/kg)"),'Pivot Table_GHG'!$A$3,"SUB TYPE",$B42)=0,"PROXY","DB value")) -> DB value | Q42: =IF($P42="PROXY",DCOUNT('literature entries'!$D:$AI,IF($J42=1,"ACTIVE GHGE, FARM GATE (kg CO2e/kg)","GHGE, processor gate (kg CO2e/kg)"),INDIRECT($K42)),GETPIVOTDATA(IF($J42=1,"ACTIVE GHGE, FARM GATE (kg CO2e/kg)","Count of GHGE, processor gate (kg CO2e/kg)"),'Pivot Table_GHG'!$A$3,"SUB TYPE",$B42)) -> 2 | R42: =IF($P42="PROXY",DAVERAGE('literature entries'!$D:$AI,IF($J42=1,"ACTIVE GHGE, FARM GATE (kg CO2e/kg)","GHGE, processor gate (kg CO2e/kg)"),INDIRECT($K42)),GETPIVOTDATA(IF($J42=1,"Average of ACTIVE GHGE, FARM GATE (kg CO2e/kg)","Average of GHGE, processor gate (kg CO2e/kg)"),'Pivot Table_GHG'!$A$3,"SUB TYPE",$B42)) -> 0.069 | S42: =IF($P42="PROXY",DSTDEV('literature entries'!$D:$AI,IF($J42=1,"ACTIVE GHGE, FARM GATE (kg CO2e/kg)","GHGE, processor gate (kg CO2e/kg)"),INDIRECT($K42)),GETPIVOTDATA(IF($J42=1,"StdDev of ACTIVE GHGE, FARM GATE (kg CO2e/kg)","StdDev of GHGE, processor gate (kg CO2e/kg)"),'Pivot Table_GHG'!$A$3,"SUB TYPE",$B42)) -> 0.035355339 | W42: =IF(L42="PROXY",IF(M42>=5,K42,"need group"),IF(M42>=5,"DIRECT","need group")) -> onion_bulb | X42: =IF($W42="DIRECT",M42,DCOUNT('literature entries'!$D:$AI,IF($J42=1,"ACTIVE CED, FARM GATE (MJ/kg)","CED, processor gate (MJ/kg)"),INDIRECT($W42))) -> 7 | Y42: =IF($W42="DIRECT","",DAVERAGE('literature entries'!$D:$AI,IF($J42=1,"ACTIVE CED, FARM GATE (MJ/kg)","CED, processor gate (MJ/kg)"),INDIRECT($W42))) -> 2.5496782 | Z42: =IF($W42="DIRECT",$O42,DSTDEV('literature entries'!$D:$AI,IF($J42=1,"ACTIVE CED, FARM GATE (MJ/kg)","CED, processor gate (MJ/kg)"),INDIRECT($W42))) -> 1.6075251 | AA42: =IF($W42="DIRECT",$O42,$Z42/$Y42*$N42) -> 1.6075251 | AB42: onion_bulb | AC42: =IF($AB42="DIRECT",Q42,DCOUNT('literature entries'!$D:$AI,IF($J42=1,"ACTIVE GHGE, FARM GATE (kg CO2e/kg)","GHGE, processor gate (kg CO2e/kg)"),INDIRECT($AB42))) -> 7 | AD42: =IF($AB42="DIRECT","",DAVERAGE('literature entries'!$D:$AI,IF($J42=1,"ACTIVE GHGE, FARM GATE (kg CO2e/kg)","GHGE, processor gate (kg CO2e/kg)"),INDIRECT($AB42))) -> 0.24193689 | AE42: =IF($AB42="DIRECT",$S42,DSTDEV('literature entries'!$D:$AI,IF($J42=1,"ACTIVE GHGE, FARM GATE (kg CO2e/kg)","GHGE, processor gate (kg CO2e/kg)"),INDIRECT($AB42))) -> 0.155461 | AF42: =IF($AB42="DIRECT",$S42,$AE42/$AD42*$R42) -> 0.04433722
A43: 302239000 | B43: Onion, green | C43: weight of bulb or bulb and leaves | D43: Includes Elegans hosta; Fritillaria, leaves, Kurrat; Beltsville bunching onion; Macrostem onion, pearl onion, potato onion, tree onion, and, Welsh onion | E43: 2507 | F43: =N43*H43+T43 -> 1.231152 | G43: =R43*H43+U43 -> 0.085072 | H43: 1.04 | I43: FICRCD | J43: 1 | K43: carrot | L43: =IF(ISERROR(GETPIVOTDATA(IF($J43=1,"Count of ACTIVE CED, FARM GATE (MJ/kg)","Count of CED, processor gate (MJ/kg)"),'Pivot Table_CED'!$A$3,"SUB TYPE",$B43)),"PROXY",IF(GETPIVOTDATA(IF($J43=1,"Count of ACTIVE CED, FARM GATE (MJ/kg)","Count of CED, processor gate (MJ/kg)"),'Pivot Table_CED'!$A$3,"SUB TYPE",$B43)=0,"PROXY","DB value")) -> PROXY | M43: =IF($L43="PROXY",DCOUNT('literature entries'!$D:$AI,IF($J43=1,"ACTIVE CED, FARM GATE (MJ/kg)","CED, processor gate (MJ/kg)"),INDIRECT($K43)),GETPIVOTDATA(IF($J43=1,"Count of ACTIVE CED, FARM GATE (MJ/kg)","Count of CED, processor gate (MJ/kg)"),'Pivot Table_CED'!$A$3,"SUB TYPE",$B43)) -> 5 | N43: =IF($L43="PROXY",DAVERAGE('literature entries'!$D:$AI,IF($J43=1,"ACTIVE CED, FARM GATE (MJ/kg)","CED, processor gate (MJ/kg)"),INDIRECT($K43)),GETPIVOTDATA(IF($J43=1,"Average of ACTIVE CED, FARM GATE (MJ/kg)","Average of CED, processor gate (MJ/kg)"),'Pivot Table_CED'!$A$3,"SUB TYPE",$B43)) -> 1.1838 | O43: =IF($L43="PROXY",DSTDEV('literature entries'!D:AI,IF($J43=1,"ACTIVE CED, FARM GATE (MJ/kg)","CED, processor gate (MJ/kg)"),INDIRECT($K43)),GETPIVOTDATA(IF($J43=1,"StdDev of ACTIVE CED, FARM GATE (MJ/kg)","StdDev of CED, processor gate (MJ/kg)"),'Pivot Table_CED'!$A$3,"SUB TYPE",$B43)) -> 0.63805815 | P43: =IF(ISERROR(GETPIVOTDATA(IF($J43=1,"Count of ACTIVE GHGE, FARM GATE (kg CO2e/kg)","Count of GHGE, processor gate (kg CO2e/kg)"),'Pivot Table_GHG'!$A$3,"SUB TYPE",$B43)),"PROXY",IF(GETPIVOTDATA(IF($J43=1,"Count of ACTIVE GHGE, FARM GATE (kg CO2e/kg)","Count of GHGE, processor gate (kg CO2e/kg)"),'Pivot Table_GHG'!$A$3,"SUB TYPE",$B43)=0,"PROXY","DB value")) -> PROXY | Q43: =IF($P43="PROXY",DCOUNT('literature entries'!$D:$AI,IF($J43=1,"ACTIVE GHGE, FARM GATE (kg CO2e/kg)","GHGE, processor gate (kg CO2e/kg)"),INDIRECT($K43)),GETPIVOTDATA(IF($J43=1,"ACTIVE GHGE, FARM GATE (kg CO2e/kg)","Count of GHGE, processor gate (kg CO2e/kg)"),'Pivot Table_GHG'!$A$3,"SUB TYPE",$B43)) -> 5 | R43: =IF($P43="PROXY",DAVERAGE('literature entries'!$D:$AI,IF($J43=1,"ACTIVE GHGE, FARM GATE (kg CO2e/kg)","GHGE, processor gate (kg CO2e/kg)"),INDIRECT($K43)),GETPIVOTDATA(IF($J43=1,"Average of ACTIVE GHGE, FARM GATE (kg CO2e/kg)","Average of GHGE, processor gate (kg CO2e/kg)"),'Pivot Table_GHG'!$A$3,"SUB TYPE",$B43)) -> 0.0818 | S43: =IF($P43="PROXY",DSTDEV('literature entries'!$D:$AI,IF($J43=1,"ACTIVE GHGE, FARM GATE (kg CO2e/kg)","GHGE, processor gate (kg CO2e/kg)"),INDIRECT($K43)),GETPIVOTDATA(IF($J43=1,"StdDev of ACTIVE GHGE, FARM GATE (kg CO2e/kg)","StdDev of GHGE, processor gate (kg CO2e/kg)"),'Pivot Table_GHG'!$A$3,"SUB TYPE",$B43)) -> 0.051982689 | W43: roots | X43: =IF($W43="DIRECT",M43,DCOUNT('literature entries'!$D:$AI,IF($J43=1,"ACTIVE CED, FARM GATE (MJ/kg)","CED, processor gate (MJ/kg)"),INDIRECT($W43))) -> 14 | Y43: =IF($W43="DIRECT","",DAVERAGE('literature entries'!$D:$AI,IF($J43=1,"ACTIVE CED, FARM GATE (MJ/kg)","CED, processor gate (MJ/kg)"),INDIRECT($W43))) -> 1.4220714 | Z43: =IF($W43="DIRECT",$O43,DSTDEV('literature entries'!$D:$AI,IF($J43=1,"ACTIVE CED, FARM GATE (MJ/kg)","CED, processor gate (MJ/kg)"),INDIRECT($W43))) -> 0.57442044 | AA43: =IF($W43="DIRECT",$O43,$Z43/$Y43*$N43) -> 0.47817494 | AB43: roots | AC43: =IF($AB43="DIRECT",Q43,DCOUNT('literature entries'!$D:$AI,IF($J43=1,"ACTIVE GHGE, FARM GATE (kg CO2e/kg)","GHGE, processor gate (kg CO2e/kg)"),INDIRECT($AB43))) -> 25 | AD43: =IF($AB43="DIRECT","",DAVERAGE('literature entries'!$D:$AI,IF($J43=1,"ACTIVE GHGE, FARM GATE (kg CO2e/kg)","GHGE, processor gate (kg CO2e/kg)"),INDIRECT($AB43))) -> 0.2134 | AE43: =IF($AB43="DIRECT",$S43,DSTDEV('literature entries'!$D:$AI,IF($J43=1,"ACTIVE GHGE, FARM GATE (kg CO2e/kg)","GHGE, processor gate (kg CO2e/kg)"),INDIRECT($AB43))) -> 0.17992035 | AF43: =IF($AB43="DIRECT",$S43,$AE43/$AD43*$R43) -> 0.068966658
A44: 401005000 | B44: Amaranth, leafy | C44: weight of leaf | D44: Includes Tampala, Chinese spinach, lambsquarter, and pokeweed (pokeberry). | E44: 12 | F44: =N44*H44+T44 -> 2.5657275 | G44: =R44*H44+U44 -> 0.18561974 | H44: 1 | I44: None | J44: 1 | K44: greens | L44: =IF(ISERROR(GETPIVOTDATA(IF($J44=1,"Count of ACTIVE CED, FARM GATE (MJ/kg)","Count of CED, processor gate (MJ/kg)"),'Pivot Table_CED'!$A$3,"SUB TYPE",$B44)),"PROXY",IF(GETPIVOTDATA(IF($J44=1,"Count of ACTIVE CED, FARM GATE (MJ/kg)","Count of CED, processor gate (MJ/kg)"),'Pivot Table_CED'!$A$3,"SUB TYPE",$B44)=0,"PROXY","DB value")) -> PROXY | M44: =IF($L44="PROXY",DCOUNT('literature entries'!$D:$AI,IF($J44=1,"ACTIVE CED, FARM GATE (MJ/kg)","CED, processor gate (MJ/kg)"),INDIRECT($K44)),GETPIVOTDATA(IF($J44=1,"Count of ACTIVE CED, FARM GATE (MJ/kg)","Count of CED, processor gate (MJ/kg)"),'Pivot Table_CED'!$A$3,"SUB TYPE",$B44)) -> 10 | N44: =IF($L44="PROXY",DAVERAGE('literature entries'!$D:$AI,IF($J44=1,"ACTIVE CED, FARM GATE (MJ/kg)","CED, processor gate (MJ/kg)"),INDIRECT($K44)),GETPIVOTDATA(IF($J44=1,"Average of ACTIVE CED, FARM GATE (MJ/kg)","Average of CED, processor gate (MJ/kg)"),'Pivot Table_CED'!$A$3,"SUB TYPE",$B44)) -> 2.5657275 | O44: =IF($L44="PROXY",DSTDEV('literature entries'!D:AI,IF($J44=1,"ACTIVE CED, FARM GATE (MJ/kg)","CED, processor gate (MJ/kg)"),INDIRECT($K44)),GETPIVOTDATA(IF($J44=1,"StdDev of ACTIVE CED, FARM GATE (MJ/kg)","StdDev of CED, processor gate (MJ/kg)"),'Pivot Table_CED'!$A$3,"SUB TYPE",$B44)) -> 1.5197673 | P44: =IF(ISERROR(GETPIVOTDATA(IF($J44=1,"Count of ACTIVE GHGE, FARM GATE (kg CO2e/kg)","Count of GHGE, processor gate (kg CO2e/kg)"),'Pivot Table_GHG'!$A$3,"SUB TYPE",$B44)),"PROXY",IF(GETPIVOTDATA(IF($J44=1,"Count of ACTIVE GHGE, FARM GATE (kg CO2e/kg)","Count of GHGE, processor gate (kg CO2e/kg)"),'Pivot Table_GHG'!$A$3,"SUB TYPE",$B44)=0,"PROXY","DB value")) -> PROXY | Q44: =IF($P44="PROXY",DCOUNT('literature entries'!$D:$AI,IF($J44=1,"ACTIVE GHGE, FARM GATE (kg CO2e/kg)","GHGE, processor gate (kg CO2e/kg)"),INDIRECT($K44)),GETPIVOTDATA(IF($J44=1,"ACTIVE GHGE, FARM GATE (kg CO2e/kg)","Count of GHGE, processor gate (kg CO2e/kg)"),'Pivot Table_GHG'!$A$3,"SUB TYPE",$B44)) -> 22 | R44: =IF($P44="PROXY",DAVERAGE('literature entries'!$D:$AI,IF($J44=1,"ACTIVE GHGE, FARM GATE (kg CO2e/kg)","GHGE, processor gate (kg CO2e/kg)"),INDIRECT($K44)),GETPIVOTDATA(IF($J44=1,"Average of ACTIVE GHGE, FARM GATE (kg CO2e/kg)","Average of GHGE, processor gate (kg CO2e/kg)"),'Pivot Table_GHG'!$A$3,"SUB TYPE",$B44)) -> 0.18561974 | S44: =IF($P44="PROXY",DSTDEV('literature entries'!$D:$AI,IF($J44=1,"ACTIVE GHGE, FARM GATE (kg CO2e/kg)","GHGE, processor gate (kg CO2e/kg)"),INDIRECT($K44)),GETPIVOTDATA(IF($J44=1,"StdDev of ACTIVE GHGE, FARM GATE (kg CO2e/kg)","StdDev of GHGE, processor gate (kg CO2e/kg)"),'Pivot Table_GHG'!$A$3,"SUB TYPE",$B44)) -> 0.097833632 | W44: =IF(L44="PROXY",IF(M44>=5,K44,"need group"),IF(M44>=5,"DIRECT","need group")) -> greens | X44: =IF($W44="DIRECT",M44,DCOUNT('literature entries'!$D:$AI,IF($J44=1,"ACTIVE CED, FARM GATE (MJ/kg)","CED, processor gate (MJ/kg)"),INDIRECT($W44))) -> 10 | Y44: =IF($W44="DIRECT","",DAVERAGE('literature entries'!$D:$AI,IF($J44=1,"ACTIVE CED, FARM GATE (MJ/kg)","CED, processor gate (MJ/kg)"),INDIRECT($W44))) -> 2.5657275 | Z44: =IF($W44="DIRECT",$O44,DSTDEV('literature entries'!$D:$AI,IF($J44=1,"ACTIVE CED, FARM GATE (MJ/kg)","CED, processor gate (MJ/kg)"),INDIRECT($W44))) -> 1.5197673 | AA44: =IF($W44="DIRECT",$O44,$Z44/$Y44*$N44) -> 1.5197673 | AB44: =IF(P44="PROXY",IF(Q44>=5,K44,"need group"),IF(Q44>=5,"DIRECT","need group")) -> greens | AC44: =IF($AB44="DIRECT",Q44,DCOUNT('literature entries'!$D:$AI,IF($J44=1,"ACTIVE GHGE, FARM GATE (kg CO2e/kg)","GHGE, processor gate (kg CO2e/kg)"),INDIRECT($AB44))) -> 22 | AD44: =IF($AB44="DIRECT","",DAVERAGE('literature entries'!$D:$AI,IF($J44=1,"ACTIVE GHGE, FARM GATE (kg CO2e/kg)","GHGE, processor gate (kg CO2e/kg)"),INDIRECT($AB44))) -> 0.18561974 | AE44: =IF($AB44="DIRECT",$S44,DSTDEV('literature entries'!$D:$AI,IF($J44=1,"ACTIVE GHGE, FARM GATE (kg CO2e/kg)","GHGE, processor gate (kg CO2e/kg)"),INDIRECT($AB44))) -> 0.097833632 | AF44: =IF($AB44="DIRECT",$S44,$AE44/$AD44*$R44) -> 0.097833632
A45: 401118000 | B45: Cilantro, leaves | C45: weight of leaves | D45: Includes Chinese parsley and coriander leaves. | E45: 21992 | F45: =N45*H45+T45 -> 1.8298793 | G45: =R45*H45+U45 -> 0.2606991 | H45: 1.18 | I45: FICRCD | J45: 1 | K45: spinach | L45: =IF(ISERROR(GETPIVOTDATA(IF($J45=1,"Count of ACTIVE CED, FARM GATE (MJ/kg)","Count of CED, processor gate (MJ/kg)"),'Pivot Table_CED'!$A$3,"SUB TYPE",$B45)),"PROXY",IF(GETPIVOTDATA(IF($J45=1,"Count of ACTIVE CED, FARM GATE (MJ/kg)","Count of CED, processor gate (MJ/kg)"),'Pivot Table_CED'!$A$3,"SUB TYPE",$B45)=0,"PROXY","DB value")) -> PROXY | M45: =IF($L45="PROXY",DCOUNT('literature entries'!$D:$AI,IF($J45=1,"ACTIVE CED, FARM GATE (MJ/kg)","CED, processor gate (MJ/kg)"),INDIRECT($K45)),GETPIVOTDATA(IF($J45=1,"Count of ACTIVE CED, FARM GATE (MJ/kg)","Count of CED, processor gate (MJ/kg)"),'Pivot Table_CED'!$A$3,"SUB TYPE",$B45)) -> 3 | N45: =IF($L45="PROXY",DAVERAGE('literature entries'!$D:$AI,IF($J45=1,"ACTIVE CED, FARM GATE (MJ/kg)","CED, processor gate (MJ/kg)"),INDIRECT($K45)),GETPIVOTDATA(IF($J45=1,"Average of ACTIVE CED, FARM GATE (MJ/kg)","Average of CED, processor gate (MJ/kg)"),'Pivot Table_CED'!$A$3,"SUB TYPE",$B45)) -> 1.5507452 | O45: =IF($L45="PROXY",DSTDEV('literature entries'!D:AI,IF($J45=1,"ACTIVE CED, FARM GATE (MJ/kg)","CED, processor gate (MJ/kg)"),INDIRECT($K45)),GETPIVOTDATA(IF($J45=1,"StdDev of ACTIVE CED, FARM GATE (MJ/kg)","StdDev of CED, processor gate (MJ/kg)"),'Pivot Table_CED'!$A$3,"SUB TYPE",$B45)) -> 1.5455737 | P45: =IF(ISERROR(GETPIVOTDATA(IF($J45=1,"Count of ACTIVE GHGE, FARM GATE (kg CO2e/kg)","Count of GHGE, processor gate (kg CO2e/kg)"),'Pivot Table_GHG'!$A$3,"SUB TYPE",$B45)),"PROXY",IF(GETPIVOTDATA(IF($J45=1,"Count of ACTIVE GHGE, FARM GATE (kg CO2e/kg)","Count of GHGE, processor gate (kg CO2e/kg)"),'Pivot Table_GHG'!$A$3,"SUB TYPE",$B45)=0,"PROXY","DB value")) -> PROXY | Q45: =IF($P45="PROXY",DCOUNT('literature entries'!$D:$AI,IF($J45=1,"ACTIVE GHGE, FARM GATE (kg CO2e/kg)","GHGE, processor gate (kg CO2e/kg)"),INDIRECT($K45)),GETPIVOTDATA(IF($J45=1,"ACTIVE GHGE, FARM GATE (kg CO2e/kg)","Count of GHGE, processor gate (kg CO2e/kg)"),'Pivot Table_GHG'!$A$3,"SUB TYPE",$B45)) -> 3 | R45: =IF($P45="PROXY",DAVERAGE('literature entries'!$D:$AI,IF($J45=1,"ACTIVE GHGE, FARM GATE (kg CO2e/kg)","GHGE, processor gate (kg CO2e/kg)"),INDIRECT($K45)),GETPIVOTDATA(IF($J45=1,"Average of ACTIVE GHGE, FARM GATE (kg CO2e/kg)","Average of GHGE, processor gate (kg CO2e/kg)"),'Pivot Table_GHG'!$A$3,"SUB TYPE",$B45)) -> 0.22093144 | S45: =IF($P45="PROXY",DSTDEV('literature entries'!$D:$AI,IF($J45=1,"ACTIVE GHGE, FARM GATE (kg CO2e/kg)","GHGE, processor gate (kg CO2e/kg)"),INDIRECT($K45)),GETPIVOTDATA(IF($J45=1,"StdDev of ACTIVE GHGE, FARM GATE (kg CO2e/kg)","StdDev of GHGE, processor gate (kg CO2e/kg)"),'Pivot Table_GHG'!$A$3,"SUB TYPE",$B45)) -> 0.083542949 | W45: greens | X45: =IF($W45="DIRECT",M45,DCOUNT('literature entries'!$D:$AI,IF($J45=1,"ACTIVE CED, FARM GATE (MJ/kg)","CED, processor gate (MJ/kg)"),INDIRECT($W45))) -> 10 | Y45: =IF($W45="DIRECT","",DAVERAGE('literature entries'!$D:$AI,IF($J45=1,"ACTIVE CED, FARM GATE (MJ/kg)","CED, processor gate (MJ/kg)"),INDIRECT($W45))) -> 2.5657275 | Z45: =IF($W45="DIRECT",$O45,DSTDEV('literature entries'!$D:$AI,IF($J45=1,"ACTIVE CED, FARM GATE (MJ/kg)","CED, processor gate (MJ/kg)"),INDIRECT($W45))) -> 1.5197673 | AA45: =IF($W45="DIRECT",$O45,$Z45/$Y45*$N45) -> 0.91855891 | AB45: greens | AC45: =IF($AB45="DIRECT",Q45,DCOUNT('literature entries'!$D:$AI,IF($J45=1,"ACTIVE GHGE, FARM GATE (kg CO2e/kg)","GHGE, processor gate (kg CO2e/kg)"),INDIRECT($AB45))) -> 22 | AD45: =IF($AB45="DIRECT","",DAVERAGE('literature entries'!$D:$AI,IF($J45=1,"ACTIVE GHGE, FARM GATE (kg CO2e/kg)","GHGE, processor gate (kg CO2e/kg)"),INDIRECT($AB45))) -> 0.18561974 | AE45: =IF($AB45="DIRECT",$S45,DSTDEV('literature entries'!$D:$AI,IF($J45=1,"ACTIVE GHGE, FARM GATE (kg CO2e/kg)","GHGE, processor gate (kg CO2e/kg)"),INDIRECT($AB45))) -> 0.097833632 | AF45: =IF($AB45="DIRECT",$S45,$AE45/$AD45*$R45) -> 0.11644518
A46: 401138000 | B46: Dandelion, leaves | C46: weight of leaves | E46: 5 | F46: =N46*H46+T46 -> 1.06 | G46: =R46*H46+U46 -> 0.055666667 | H46: 1 | I46: None | J46: 1 | K46: Escarole | L46: =IF(ISERROR(GETPIVOTDATA(IF($J46=1,"Count of ACTIVE CED, FARM GATE (MJ/kg)","Count of CED, processor gate (MJ/kg)"),'Pivot Table_CED'!$A$3,"SUB TYPE",$B46)),"PROXY",IF(GETPIVOTDATA(IF($J46=1,"Count of ACTIVE CED, FARM GATE (MJ/kg)","Count of CED, processor gate (MJ/kg)"),'Pivot Table_CED'!$A$3,"SUB TYPE",$B46)=0,"PROXY","DB value")) -> PROXY | M46: =IF($L46="PROXY",DCOUNT('literature entries'!$D:$AI,IF($J46=1,"ACTIVE CED, FARM GATE (MJ/kg)","CED, processor gate (MJ/kg)"),INDIRECT($K46)),GETPIVOTDATA(IF($J46=1,"Count of ACTIVE CED, FARM GATE (MJ/kg)","Count of CED, processor gate (MJ/kg)"),'Pivot Table_CED'!$A$3,"SUB TYPE",$B46)) -> 3 | N46: =IF($L46="PROXY",DAVERAGE('literature entries'!$D:$AI,IF($J46=1,"ACTIVE CED, FARM GATE (MJ/kg)","CED, processor gate (MJ/kg)"),INDIRECT($K46)),GETPIVOTDATA(IF($J46=1,"Average of ACTIVE CED, FARM GATE (MJ/kg)","Average of CED, processor gate (MJ/kg)"),'Pivot Table_CED'!$A$3,"SUB TYPE",$B46)) -> 1.06 | O46: =IF($L46="PROXY",DSTDEV('literature entries'!D:AI,IF($J46=1,"ACTIVE CED, FARM GATE (MJ/kg)","CED, processor gate (MJ/kg)"),INDIRECT($K46)),GETPIVOTDATA(IF($J46=1,"StdDev of ACTIVE CED, FARM GATE (MJ/kg)","StdDev of CED, processor gate (MJ/kg)"),'Pivot Table_CED'!$A$3,"SUB TYPE",$B46)) -> 0.28583212 | P46: =IF(ISERROR(GETPIVOTDATA(IF($J46=1,"Count of ACTIVE GHGE, FARM GATE (kg CO2e/kg)","Count of GHGE, processor gate (kg CO2e/kg)"),'Pivot Table_GHG'!$A$3,"SUB TYPE",$B46)),"PROXY",IF(GETPIVOTDATA(IF($J46=1,"Count of ACTIVE GHGE, FARM GATE (kg CO2e/kg)","Count of GHGE, processor gate (kg CO2e/kg)"),'Pivot Table_GHG'!$A$3,"SUB TYPE",$B46)=0,"PROXY","DB value")) -> PROXY | Q46: =IF($P46="PROXY",DCOUNT('literature entries'!$D:$AI,IF($J46=1,"ACTIVE GHGE, FARM GATE (kg CO2e/kg)","GHGE, processor gate (kg CO2e/kg)"),INDIRECT($K46)),GETPIVOTDATA(IF($J46=1,"ACTIVE GHGE, FARM GATE (kg CO2e/kg)","Count of GHGE, processor gate (kg CO2e/kg)"),'Pivot Table_GHG'!$A$3,"SUB TYPE",$B46)) -> 3 | R46: =IF($P46="PROXY",DAVERAGE('literature entries'!$D:$AI,IF($J46=1,"ACTIVE GHGE, FARM GATE (kg CO2e/kg)","GHGE, processor gate (kg CO2e/kg)"),INDIRECT($K46)),GETPIVOTDATA(IF($J46=1,"Average of ACTIVE GHGE, FARM GATE (kg CO2e/kg)","Average of GHGE, processor gate (kg CO2e/kg)"),'Pivot Table_GHG'!$A$3,"SUB TYPE",$B46)) -> 0.055666667 | S46: =IF($P46="PROXY",DSTDEV('literature entries'!$D:$AI,IF($J46=1,"ACTIVE GHGE, FARM GATE (kg CO2e/kg)","GHGE, processor gate (kg CO2e/kg)"),INDIRECT($K46)),GETPIVOTDATA(IF($J46=1,"StdDev of ACTIVE GHGE, FARM GATE (kg CO2e/kg)","StdDev of GHGE, processor gate (kg CO2e/kg)"),'Pivot Table_GHG'!$A$3,"SUB TYPE",$B46)) -> 0.0037287174 | W46: greens | X46: =IF($W46="DIRECT",M46,DCOUNT('literature entries'!$D:$AI,IF($J46=1,"ACTIVE CED, FARM GATE (MJ/kg)","CED, processor gate (MJ/kg)"),INDIRECT($W46))) -> 10 | Y46: =IF($W46="DIRECT","",DAVERAGE('literature entries'!$D:$AI,IF($J46=1,"ACTIVE CED, FARM GATE (MJ/kg)","CED, processor gate (MJ/kg)"),INDIRECT($W46))) -> 2.5657275 | Z46: =IF($W46="DIRECT",$O46,DSTDEV('literature entries'!$D:$AI,IF($J46=1,"ACTIVE CED, FARM GATE (MJ/kg)","CED, processor gate (MJ/kg)"),INDIRECT($W46))) -> 1.5197673 | AA46: =IF($W46="DIRECT",$O46,$Z46/$Y46*$N46) -> 0.62787391 | AB46: greens | AC46: =IF($AB46="DIRECT",Q46,DCOUNT('literature entries'!$D:$AI,IF($J46=1,"ACTIVE GHGE, FARM GATE (kg CO2e/kg)","GHGE, processor gate (kg CO2e/kg)"),INDIRECT($AB46))) -> 22 | AD46: =IF($AB46="DIRECT","",DAVERAGE('literature entries'!$D:$AI,IF($J46=1,"ACTIVE GHGE, FARM GATE (kg CO2e/kg)","GHGE, processor gate (kg CO2e/kg)"),INDIRECT($AB46))) -> 0.18561974 | AE46: =IF($AB46="DIRECT",$S46,DSTDEV('literature entries'!$D:$AI,IF($J46=1,"ACTIVE GHGE, FARM GATE (kg CO2e/kg)","GHGE, processor gate (kg CO2e/kg)"),INDIRECT($AB46))) -> 0.097833632 | AF46: =IF($AB46="DIRECT",$S46,$AE46/$AD46*$R46) -> 0.029339941
A47: 401144000 | B47: Dillweed | C47: weight of leaves | E47: 4937 | F47: =N47*H47+T47 -> 1.5507452 | G47: =R47*H47+U47 -> 0.22093144 | H47: 1 | I47: None | J47: 1 | K47: spinach | L47: =IF(ISERROR(GETPIVOTDATA(IF($J47=1,"Count of ACTIVE CED, FARM GATE (MJ/kg)","Count of CED, processor gate (MJ/kg)"),'Pivot Table_CED'!$A$3,"SUB TYPE",$B47)),"PROXY",IF(GETPIVOTDATA(IF($J47=1,"Count of ACTIVE CED, FARM GATE (MJ/kg)","Count of CED, processor gate (MJ/kg)"),'Pivot Table_CED'!$A$3,"SUB TYPE",$B47)=0,"PROXY","DB value")) -> PROXY | M47: =IF($L47="PROXY",DCOUNT('literature entries'!$D:$AI,IF($J47=1,"ACTIVE CED, FARM GATE (MJ/kg)","CED, processor gate (MJ/kg)"),INDIRECT($K47)),GETPIVOTDATA(IF($J47=1,"Count of ACTIVE CED, FARM GATE (MJ/kg)","Count of CED, processor gate (MJ/kg)"),'Pivot Table_CED'!$A$3,"SUB TYPE",$B47)) -> 3 | N47: =IF($L47="PROXY",DAVERAGE('literature entries'!$D:$AI,IF($J47=1,"ACTIVE CED, FARM GATE (MJ/kg)","CED, processor gate (MJ/kg)"),INDIRECT($K47)),GETPIVOTDATA(IF($J47=1,"Average of ACTIVE CED, FARM GATE (MJ/kg)","Average of CED, processor gate (MJ/kg)"),'Pivot Table_CED'!$A$3,"SUB TYPE",$B47)) -> 1.5507452 | O47: =IF($L47="PROXY",DSTDEV('literature entries'!D:AI,IF($J47=1,"ACTIVE CED, FARM GATE (MJ/kg)","CED, processor gate (MJ/kg)"),INDIRECT($K47)),GETPIVOTDATA(IF($J47=1,"StdDev of ACTIVE CED, FARM GATE (MJ/kg)","StdDev of CED, processor gate (MJ/kg)"),'Pivot Table_CED'!$A$3,"SUB TYPE",$B47)) -> 1.5455737 | P47: =IF(ISERROR(GETPIVOTDATA(IF($J47=1,"Count of ACTIVE GHGE, FARM GATE (kg CO2e/kg)","Count of GHGE, processor gate (kg CO2e/kg)"),'Pivot Table_GHG'!$A$3,"SUB TYPE",$B47)),"PROXY",IF(GETPIVOTDATA(IF($J47=1,"Count of ACTIVE GHGE, FARM GATE (kg CO2e/kg)","Count of GHGE, processor gate (kg CO2e/kg)"),'Pivot Table_GHG'!$A$3,"SUB TYPE",$B47)=0,"PROXY","DB value")) -> PROXY | Q47: =IF($P47="PROXY",DCOUNT('literature entries'!$D:$AI,IF($J47=1,"ACTIVE GHGE, FARM GATE (kg CO2e/kg)","GHGE, processor gate (kg CO2e/kg)"),INDIRECT($K47)),GETPIVOTDATA(IF($J47=1,"ACTIVE GHGE, FARM GATE (kg CO2e/kg)","Count of GHGE, processor gate (kg CO2e/kg)"),'Pivot Table_GHG'!$A$3,"SUB TYPE",$B47)) -> 3 | R47: =IF($P47="PROXY",DAVERAGE('literature entries'!$D:$AI,IF($J47=1,"ACTIVE GHGE, FARM GATE (kg CO2e/kg)","GHGE, processor gate (kg CO2e/kg)"),INDIRECT($K47)),GETPIVOTDATA(IF($J47=1,"Average of ACTIVE GHGE, FARM GATE (kg CO2e/kg)","Average of GHGE, processor gate (kg CO2e/kg)"),'Pivot Table_GHG'!$A$3,"SUB TYPE",$B47)) -> 0.22093144 | S47: =IF($P47="PROXY",DSTDEV('literature entries'!$D:$AI,IF($J47=1,"ACTIVE GHGE, FARM GATE (kg CO2e/kg)","GHGE, processor gate (kg CO2e/kg)"),INDIRECT($K47)),GETPIVOTDATA(IF($J47=1,"StdDev of ACTIVE GHGE, FARM GATE (kg CO2e/kg)","StdDev of GHGE, processor gate (kg CO2e/kg)"),'Pivot Table_GHG'!$A$3,"SUB TYPE",$B47)) -> 0.083542949 | W47: greens | X47: =IF($W47="DIRECT",M47,DCOUNT('literature entries'!$D:$AI,IF($J47=1,"ACTIVE CED, FARM GATE (MJ/kg)","CED, processor gate (MJ/kg)"),INDIRECT($W47))) -> 10 | Y47: =IF($W47="DIRECT","",DAVERAGE('literature entries'!$D:$AI,IF($J47=1,"ACTIVE CED, FARM GATE (MJ/kg)","CED, processor gate (MJ/kg)"),INDIRECT($W47))) -> 2.5657275 | Z47: =IF($W47="DIRECT",$O47,DSTDEV('literature entries'!$D:$AI,IF($J47=1,"ACTIVE CED, FARM GATE (MJ/kg)","CED, processor gate (MJ/kg)"),INDIRECT($W47))) -> 1.5197673 | AA47: =IF($W47="DIRECT",$O47,$Z47/$Y47*$N47) -> 0.91855891 | AB47: greens | AC47: =IF($AB47="DIRECT",Q47,DCOUNT('literature entries'!$D:$AI,IF($J47=1,"ACTIVE GHGE, FARM GATE (kg CO2e/kg)","GHGE, processor gate (kg CO2e/kg)"),INDIRECT($AB47))) -> 22 | AD47: =IF($AB47="DIRECT","",DAVERAGE('literature entries'!$D:$AI,IF($J47=1,"ACTIVE GHGE, FARM GATE (kg CO2e/kg)","GHGE, processor gate (kg CO2e/kg)"),INDIRECT($AB47))) -> 0.18561974 | AE47: =IF($AB47="DIRECT",$S47,DSTDEV('literature entries'!$D:$AI,IF($J47=1,"ACTIVE GHGE, FARM GATE (kg CO2e/kg)","GHGE, processor gate (kg CO2e/kg)"),INDIRECT($AB47))) -> 0.097833632 | AF47: =IF($AB47="DIRECT",$S47,$AE47/$AD47*$R47) -> 0.11644518
A48: 401150000 | B48: Endive | C48: weight of leaves | D48: Includes escarole. | E48: 1566 | F48: =N48*H48+T48 -> 1.2296 | G48: =R48*H48+U48 -> 0.064573333 | H48: 1.16 | I48: FICRCD | J48: 1 | K48: Escarole | L48: =IF(ISERROR(GETPIVOTDATA(IF($J48=1,"Count of ACTIVE CED, FARM GATE (MJ/kg)","Count of CED, processor gate (MJ/kg)"),'Pivot Table_CED'!$A$3,"SUB TYPE",$B48)),"PROXY",IF(GETPIVOTDATA(IF($J48=1,"Count of ACTIVE CED, FARM GATE (MJ/kg)","Count of CED, processor gate (MJ/kg)"),'Pivot Table_CED'!$A$3,"SUB TYPE",$B48)=0,"PROXY","DB value")) -> PROXY | M48: =IF($L48="PROXY",DCOUNT('literature entries'!$D:$AI,IF($J48=1,"ACTIVE CED, FARM GATE (MJ/kg)","CED, processor gate (MJ/kg)"),INDIRECT($K48)),GETPIVOTDATA(IF($J48=1,"Count of ACTIVE CED, FARM GATE (MJ/kg)","Count of CED, processor gate (MJ/kg)"),'Pivot Table_CED'!$A$3,"SUB TYPE",$B48)) -> 3 | N48: =IF($L48="PROXY",DAVERAGE('literature entries'!$D:$AI,IF($J48=1,"ACTIVE CED, FARM GATE (MJ/kg)","CED, processor gate (MJ/kg)"),INDIRECT($K48)),GETPIVOTDATA(IF($J48=1,"Average of ACTIVE CED, FARM GATE (MJ/kg)","Average of CED, processor gate (MJ/kg)"),'Pivot Table_CED'!$A$3,"SUB TYPE",$B48)) -> 1.06 | O48: =IF($L48="PROXY",DSTDEV('literature entries'!D:AI,IF($J48=1,"ACTIVE CED, FARM GATE (MJ/kg)","CED, processor gate (MJ/kg)"),INDIRECT($K48)),GETPIVOTDATA(IF($J48=1,"StdDev of ACTIVE CED, FARM GATE (MJ/kg)","StdDev of CED, processor gate (MJ/kg)"),'Pivot Table_CED'!$A$3,"SUB TYPE",$B48)) -> 0.28583212 | P48: =IF(ISERROR(GETPIVOTDATA(IF($J48=1,"Count of ACTIVE GHGE, FARM GATE (kg CO2e/kg)","Count of GHGE, processor gate (kg CO2e/kg)"),'Pivot Table_GHG'!$A$3,"SUB TYPE",$B48)),"PROXY",IF(GETPIVOTDATA(IF($J48=1,"Count of ACTIVE GHGE, FARM GATE (kg CO2e/kg)","Count of GHGE, processor gate (kg CO2e/kg)"),'Pivot Table_GHG'!$A$3,"SUB TYPE",$B48)=0,"PROXY","DB value")) -> PROXY | Q48: =IF($P48="PROXY",DCOUNT('literature entries'!$D:$AI,IF($J48=1,"ACTIVE GHGE, FARM GATE (kg CO2e/kg)","GHGE, processor gate (kg CO2e/kg)"),INDIRECT($K48)),GETPIVOTDATA(IF($J48=1,"ACTIVE GHGE, FARM GATE (kg CO2e/kg)","Count of GHGE, processor gate (kg CO2e/kg)"),'Pivot Table_GHG'!$A$3,"SUB TYPE",$B48)) -> 3 | R48: =IF($P48="PROXY",DAVERAGE('literature entries'!$D:$AI,IF($J48=1,"ACTIVE GHGE, FARM GATE (kg CO2e/kg)","GHGE, processor gate (kg CO2e/kg)"),INDIRECT($K48)),GETPIVOTDATA(IF($J48=1,"Average of ACTIVE GHGE, FARM GATE (kg CO2e/kg)","Average of GHGE, processor gate (kg CO2e/kg)"),'Pivot Table_GHG'!$A$3,"SUB TYPE",$B48)) -> 0.055666667 | S48: =IF($P48="PROXY",DSTDEV('literature entries'!$D:$AI,IF($J48=1,"ACTIVE GHGE, FARM GATE (kg CO2e/kg)","GHGE, processor gate (kg CO2e/kg)"),INDIRECT($K48)),GETPIVOTDATA(IF($J48=1,"StdDev of ACTIVE GHGE, FARM GATE (kg CO2e/kg)","StdDev of GHGE, processor gate (kg CO2e/kg)"),'Pivot Table_GHG'!$A$3,"SUB TYPE",$B48)) -> 0.0037287174 | W48: greens | X48: =IF($W48="DIRECT",M48,DCOUNT('literature entries'!$D:$AI,IF($J48=1,"ACTIVE CED, FARM GATE (MJ/kg)","CED, processor gate (MJ/kg)"),INDIRECT($W48))) -> 10 | Y48: =IF($W48="DIRECT","",DAVERAGE('literature entries'!$D:$AI,IF($J48=1,"ACTIVE CED, FARM GATE (MJ/kg)","CED, processor gate (MJ/kg)"),INDIRECT($W48))) -> 2.5657275 | Z48: =IF($W48="DIRECT",$O48,DSTDEV('literature entries'!$D:$AI,IF($J48=1,"ACTIVE CED, FARM GATE (MJ/kg)","CED, processor gate (MJ/kg)"),INDIRECT($W48))) -> 1.5197673 | AA48: =IF($W48="DIRECT",$O48,$Z48/$Y48*$N48) -> 0.62787391 | AB48: greens | AC48: =IF($AB48="DIRECT",Q48,DCOUNT('literature entries'!$D:$AI,IF($J48=1,"ACTIVE GHGE, FARM GATE (kg CO2e/kg)","GHGE, processor gate (kg CO2e/kg)"),INDIRECT($AB48))) -> 22 | AD48: =IF($AB48="DIRECT","",DAVERAGE('literature entries'!$D:$AI,IF($J48=1,"ACTIVE GHGE, FARM GATE (kg CO2e/kg)","GHGE, processor gate (kg CO2e/kg)"),INDIRECT($AB48))) -> 0.18561974 | AE48: =IF($AB48="DIRECT",$S48,DSTDEV('literature entries'!$D:$AI,IF($J48=1,"ACTIVE GHGE, FARM GATE (kg CO2e/kg)","GHGE, processor gate (kg CO2e/kg)"),INDIRECT($AB48))) -> 0.097833632 | AF48: =IF($AB48="DIRECT",$S48,$AE48/$AD48*$R48) -> 0.029339941
A49: 401204000 | B49: Lettuce, head | C49: weight of leaves; juice | E49: 15121 | F49: =N49*H49+T49 -> 2.0842911 | G49: =R49*H49+U49 -> 0.1582875 | H49: 1.05 | I49: FICRCD | J49: 1 | L49: =IF(ISERROR(GETPIVOTDATA(IF($J49=1,"Count of ACTIVE CED, FARM GATE (MJ/kg)","Count of CED, processor gate (MJ/kg)"),'Pivot Table_CED'!$A$3,"SUB TYPE",$B49)),"PROXY",IF(GETPIVOTDATA(IF($J49=1,"Count of ACTIVE CED, FARM GATE (MJ/kg)","Count of CED, processor gate (MJ/kg)"),'Pivot Table_CED'!$A$3,"SUB TYPE",$B49)=0,"PROXY","DB value")) -> DB value | M49: =IF($L49="PROXY",DCOUNT('literature entries'!$D:$AI,IF($J49=1,"ACTIVE CED, FARM GATE (MJ/kg)","CED, processor gate (MJ/kg)"),INDIRECT($K49)),GETPIVOTDATA(IF($J49=1,"Count of ACTIVE CED, FARM GATE (MJ/kg)","Count of CED, processor gate (MJ/kg)"),'Pivot Table_CED'!$A$3,"SUB TYPE",$B49)) -> 1 | N49: =IF($L49="PROXY",DAVERAGE('literature entries'!$D:$AI,IF($J49=1,"ACTIVE CED, FARM GATE (MJ/kg)","CED, processor gate (MJ/kg)"),INDIRECT($K49)),GETPIVOTDATA(IF($J49=1,"Average of ACTIVE CED, FARM GATE (MJ/kg)","Average of CED, processor gate (MJ/kg)"),'Pivot Table_CED'!$A$3,"SUB TYPE",$B49)) -> 1.9850392 | O49: =IF($L49="PROXY",DSTDEV('literature entries'!D:AI,IF($J49=1,"ACTIVE CED, FARM GATE (MJ/kg)","CED, processor gate (MJ/kg)"),INDIRECT($K49)),GETPIVOTDATA(IF($J49=1,"StdDev of ACTIVE CED, FARM GATE (MJ/kg)","StdDev of CED, processor gate (MJ/kg)"),'Pivot Table_CED'!$A$3,"SUB TYPE",$B49)) -> 0 | P49: =IF(ISERROR(GETPIVOTDATA(IF($J49=1,"Count of ACTIVE GHGE, FARM GATE (kg CO2e/kg)","Count of GHGE, processor gate (kg CO2e/kg)"),'Pivot Table_GHG'!$A$3,"SUB TYPE",$B49)),"PROXY",IF(GETPIVOTDATA(IF($J49=1,"Count of ACTIVE GHGE, FARM GATE (kg CO2e/kg)","Count of GHGE, processor gate (kg CO2e/kg)"),'Pivot Table_GHG'!$A$3,"SUB TYPE",$B49)=0,"PROXY","DB value")) -> DB value | Q49: =IF($P49="PROXY",DCOUNT('literature entries'!$D:$AI,IF($J49=1,"ACTIVE GHGE, FARM GATE (kg CO2e/kg)","GHGE, processor gate (kg CO2e/kg)"),INDIRECT($K49)),GETPIVOTDATA(IF($J49=1,"ACTIVE GHGE, FARM GATE (kg CO2e/kg)","Count of GHGE, processor gate (kg CO2e/kg)"),'Pivot Table_GHG'!$A$3,"SUB TYPE",$B49)) -> 1 | R49: =IF($P49="PROXY",DAVERAGE('literature entries'!$D:$AI,IF($J49=1,"ACTIVE GHGE, FARM GATE (kg CO2e/kg)","GHGE, processor gate (kg CO2e/kg)"),INDIRECT($K49)),GETPIVOTDATA(IF($J49=1,"Average of ACTIVE GHGE, FARM GATE (kg CO2e/kg)","Average of GHGE, processor gate (kg CO2e/kg)"),'Pivot Table_GHG'!$A$3,"SUB TYPE",$B49)) -> 0.15075 | S49: =IF($P49="PROXY",DSTDEV('literature entries'!$D:$AI,IF($J49=1,"ACTIVE GHGE, FARM GATE (kg CO2e/kg)","GHGE, processor gate (kg CO2e/kg)"),INDIRECT($K49)),GETPIVOTDATA(IF($J49=1,"StdDev of ACTIVE GHGE, FARM GATE (kg CO2e/kg)","StdDev of GHGE, processor gate (kg CO2e/kg)"),'Pivot Table_GHG'!$A$3,"SUB TYPE",$B49)) -> #DIV/0! | W49: greens | X49: =IF($W49="DIRECT",M49,DCOUNT('literature entries'!$D:$AI,IF($J49=1,"ACTIVE CED, FARM GATE (MJ/kg)","CED, processor gate (MJ/kg)"),INDIRECT($W49))) -> 10 | Y49: =IF($W49="DIRECT","",DAVERAGE('literature entries'!$D:$AI,IF($J49=1,"ACTIVE CED, FARM GATE (MJ/kg)","CED, processor gate (MJ/kg)"),INDIRECT($W49))) -> 2.5657275 | Z49: =IF($W49="DIRECT",$O49,DSTDEV('literature entries'!$D:$AI,IF($J49=1,"ACTIVE CED, FARM GATE (MJ/kg)","CED, processor gate (MJ/kg)"),INDIRECT($W49))) -> 1.5197673 | AA49: =IF($W49="DIRECT",$O49,$Z49/$Y49*$N49) -> 1.175806 | AB49: greens | AC49: =IF($AB49="DIRECT",Q49,DCOUNT('literature entries'!$D:$AI,IF($J49=1,"ACTIVE GHGE, FARM GATE (kg CO2e/kg)","GHGE, processor gate (kg CO2e/kg)"),INDIRECT($AB49))) -> 22 | AD49: =IF($AB49="DIRECT","",DAVERAGE('literature entries'!$D:$AI,IF($J49=1,"ACTIVE GHGE, FARM GATE (kg CO2e/kg)","GHGE, processor gate (kg CO2e/kg)"),INDIRECT($AB49))) -> 0.18561974 | AE49: =IF($AB49="DIRECT",$S49,DSTDEV('literature entries'!$D:$AI,IF($J49=1,"ACTIVE GHGE, FARM GATE (kg CO2e/kg)","GHGE, processor gate (kg CO2e/kg)"),INDIRECT($AB49))) -> 0.097833632 | AF49: =IF($AB49="DIRECT",$S49,$AE49/$AD49*$R49) -> 0.079455019
A50: 401205000 | B50: Lettuce, leaf | C50: weight of leaves | D50: Includes romaine. | E50: 1626 | F50: =N50*H50+T50 -> 3.9942 | G50: =R50*H50+U50 -> 0.2289063 | H50: 1.26 | I50: NNDSR28 | J50: 1 | L50: =IF(ISERROR(GETPIVOTDATA(IF($J50=1,"Count of ACTIVE CED, FARM GATE (MJ/kg)","Count of CED, processor gate (MJ/kg)"),'Pivot Table_CED'!$A$3,"SUB TYPE",$B50)),"PROXY",IF(GETPIVOTDATA(IF($J50=1,"Count of ACTIVE CED, FARM GATE (MJ/kg)","Count of CED, processor gate (MJ/kg)"),'Pivot Table_CED'!$A$3,"SUB TYPE",$B50)=0,"PROXY","DB value")) -> DB value | M50: =IF($L50="PROXY",DCOUNT('literature entries'!$D:$AI,IF($J50=1,"ACTIVE CED, FARM GATE (MJ/kg)","CED, processor gate (MJ/kg)"),INDIRECT($K50)),GETPIVOTDATA(IF($J50=1,"Count of ACTIVE CED, FARM GATE (MJ/kg)","Count of CED, processor gate (MJ/kg)"),'Pivot Table_CED'!$A$3,"SUB TYPE",$B50)) -> 6 | N50: =IF($L50="PROXY",DAVERAGE('literature entries'!$D:$AI,IF($J50=1,"ACTIVE CED, FARM GATE (MJ/kg)","CED, processor gate (MJ/kg)"),INDIRECT($K50)),GETPIVOTDATA(IF($J50=1,"Average of ACTIVE CED, FARM GATE (MJ/kg)","Average of CED, processor gate (MJ/kg)"),'Pivot Table_CED'!$A$3,"SUB TYPE",$B50)) -> 3.17 | O50: =IF($L50="PROXY",DSTDEV('literature entries'!D:AI,IF($J50=1,"ACTIVE CED, FARM GATE (MJ/kg)","CED, processor gate (MJ/kg)"),INDIRECT($K50)),GETPIVOTDATA(IF($J50=1,"StdDev of ACTIVE CED, FARM GATE (MJ/kg)","StdDev of CED, processor gate (MJ/kg)"),'Pivot Table_CED'!$A$3,"SUB TYPE",$B50)) -> 1.4415963 | P50: =IF(ISERROR(GETPIVOTDATA(IF($J50=1,"Count of ACTIVE GHGE, FARM GATE (kg CO2e/kg)","Count of GHGE, processor gate (kg CO2e/kg)"),'Pivot Table_GHG'!$A$3,"SUB TYPE",$B50)),"PROXY",IF(GETPIVOTDATA(IF($J50=1,"Count of ACTIVE GHGE, FARM GATE (kg CO2e/kg)","Count of GHGE, processor gate (kg CO2e/kg)"),'Pivot Table_GHG'!$A$3,"SUB TYPE",$B50)=0,"PROXY","DB value")) -> DB value | Q50: =IF($P50="PROXY",DCOUNT('literature entries'!$D:$AI,IF($J50=1,"ACTIVE GHGE, FARM GATE (kg CO2e/kg)","GHGE, processor gate (kg CO2e/kg)"),INDIRECT($K50)),GETPIVOTDATA(IF($J50=1,"ACTIVE GHGE, FARM GATE (kg CO2e/kg)","Count of GHGE, processor gate (kg CO2e/kg)"),'Pivot Table_GHG'!$A$3,"SUB TYPE",$B50)) -> 18 | R50: =IF($P50="PROXY",DAVERAGE('literature entries'!$D:$AI,IF($J50=1,"ACTIVE GHGE, FARM GATE (kg CO2e/kg)","GHGE, processor gate (kg CO2e/kg)"),INDIRECT($K50)),GETPIVOTDATA(IF($J50=1,"Average of ACTIVE GHGE, FARM GATE (kg CO2e/kg)","Average of GHGE, processor gate (kg CO2e/kg)"),'Pivot Table_GHG'!$A$3,"SUB TYPE",$B50)) -> 0.18167167 | S50: =IF($P50="PROXY",DSTDEV('literature entries'!$D:$AI,IF($J50=1,"ACTIVE GHGE, FARM GATE (kg CO2e/kg)","GHGE, processor gate (kg CO2e/kg)"),INDIRECT($K50)),GETPIVOTDATA(IF($J50=1,"StdDev of ACTIVE GHGE, FARM GATE (kg CO2e/kg)","StdDev of GHGE, processor gate (kg CO2e/kg)"),'Pivot Table_GHG'!$A$3,"SUB TYPE",$B50)) -> 0.10341343 | W50: =IF(L50="PROXY",IF(M50>=5,K50,"need group"),IF(M50>=5,"DIRECT","need group")) -> DIRECT | X50: =IF($W50="DIRECT",M50,DCOUNT('literature entries'!$D:$AI,IF($J50=1,"ACTIVE CED, FARM GATE (MJ/kg)","CED, processor gate (MJ/kg)"),INDIRECT($W50))) -> 6 | Y50: =IF($W50="DIRECT","",DAVERAGE('literature entries'!$D:$AI,IF($J50=1,"ACTIVE CED, FARM GATE (MJ/kg)","CED, processor gate (MJ/kg)"),INDIRECT($W50))) | Z50: =IF($W50="DIRECT",$O50,DSTDEV('literature entries'!$D:$AI,IF($J50=1,"ACTIVE CED, FARM GATE (MJ/kg)","CED, processor gate (MJ/kg)"),INDIRECT($W50))) -> 1.4415963 | AA50: =IF($W50="DIRECT",$O50,$Z50/$Y50*$N50) -> 1.4415963 | AB50: =IF(P50="PROXY",IF(Q50>=5,K50,"need group"),IF(Q50>=5,"DIRECT","need group")) -> DIRECT | AC50: =IF($AB50="DIRECT",Q50,DCOUNT('literature entries'!$D:$AI,IF($J50=1,"ACTIVE GHGE, FARM GATE (kg CO2e/kg)","GHGE, processor gate (kg CO2e/kg)"),INDIRECT($AB50))) -> 18 | AD50: =IF($AB50="DIRECT","",DAVERAGE('literature entries'!$D:$AI,IF($J50=1,"ACTIVE GHGE, FARM GATE (kg CO2e/kg)","GHGE, processor gate (kg CO2e/kg)"),INDIRECT($AB50))) | AE50: =IF($AB50="DIRECT",$S50,DSTDEV('literature entries'!$D:$AI,IF($J50=1,"ACTIVE GHGE, FARM GATE (kg CO2e/kg)","GHGE, processor gate (kg CO2e/kg)"),INDIRECT($AB50))) -> 0.10341343 | AF50: =IF($AB50="DIRECT",$S50,$AE50/$AD50*$R50) -> 0.10341343
A51: 401248000 | B51: Parsley, leaves | C51: weight of leaves and stems | E51: 2940 | F51: =N51*H51+T51 -> 1.6282824 | G51: =R51*H51+U51 -> 0.23197801 | H51: 1.05 | I51: FICRCD | J51: 1 | K51: spinach | L51: =IF(ISERROR(GETPIVOTDATA(IF($J51=1,"Count of ACTIVE CED, FARM GATE (MJ/kg)","Count of CED, processor gate (MJ/kg)"),'Pivot Table_CED'!$A$3,"SUB TYPE",$B51)),"PROXY",IF(GETPIVOTDATA(IF($J51=1,"Count of ACTIVE CED, FARM GATE (MJ/kg)","Count of CED, processor gate (MJ/kg)"),'Pivot Table_CED'!$A$3,"SUB TYPE",$B51)=0,"PROXY","DB value")) -> PROXY | M51: =IF($L51="PROXY",DCOUNT('literature entries'!$D:$AI,IF($J51=1,"ACTIVE CED, FARM GATE (MJ/kg)","CED, processor gate (MJ/kg)"),INDIRECT($K51)),GETPIVOTDATA(IF($J51=1,"Count of ACTIVE CED, FARM GATE (MJ/kg)","Count of CED, processor gate (MJ/kg)"),'Pivot Table_CED'!$A$3,"SUB TYPE",$B51)) -> 3 | N51: =IF($L51="PROXY",DAVERAGE('literature entries'!$D:$AI,IF($J51=1,"ACTIVE CED, FARM GATE (MJ/kg)","CED, processor gate (MJ/kg)"),INDIRECT($K51)),GETPIVOTDATA(IF($J51=1,"Average of ACTIVE CED, FARM GATE (MJ/kg)","Average of CED, processor gate (MJ/kg)"),'Pivot Table_CED'!$A$3,"SUB TYPE",$B51)) -> 1.5507452 | O51: =IF($L51="PROXY",DSTDEV('literature entries'!D:AI,IF($J51=1,"ACTIVE CED, FARM GATE (MJ/kg)","CED, processor gate (MJ/kg)"),INDIRECT($K51)),GETPIVOTDATA(IF($J51=1,"StdDev of ACTIVE CED, FARM GATE (MJ/kg)","StdDev of CED, processor gate (MJ/kg)"),'Pivot Table_CED'!$A$3,"SUB TYPE",$B51)) -> 1.5455737 | P51: =IF(ISERROR(GETPIVOTDATA(IF($J51=1,"Count of ACTIVE GHGE, FARM GATE (kg CO2e/kg)","Count of GHGE, processor gate (kg CO2e/kg)"),'Pivot Table_GHG'!$A$3,"SUB TYPE",$B51)),"PROXY",IF(GETPIVOTDATA(IF($J51=1,"Count of ACTIVE GHGE, FARM GATE (kg CO2e/kg)","Count of GHGE, processor gate (kg CO2e/kg)"),'Pivot Table_GHG'!$A$3,"SUB TYPE",$B51)=0,"PROXY","DB value")) -> PROXY | Q51: =IF($P51="PROXY",DCOUNT('literature entries'!$D:$AI,IF($J51=1,"ACTIVE GHGE, FARM GATE (kg CO2e/kg)","GHGE, processor gate (kg CO2e/kg)"),INDIRECT($K51)),GETPIVOTDATA(IF($J51=1,"ACTIVE GHGE, FARM GATE (kg CO2e/kg)","Count of GHGE, processor gate (kg CO2e/kg)"),'Pivot Table_GHG'!$A$3,"SUB TYPE",$B51)) -> 3 | R51: =IF($P51="PROXY",DAVERAGE('literature entries'!$D:$AI,IF($J51=1,"ACTIVE GHGE, FARM GATE (kg CO2e/kg)","GHGE, processor gate (kg CO2e/kg)"),INDIRECT($K51)),GETPIVOTDATA(IF($J51=1,"Average of ACTIVE GHGE, FARM GATE (kg CO2e/kg)","Average of GHGE, processor gate (kg CO2e/kg)"),'Pivot Table_GHG'!$A$3,"SUB TYPE",$B51)) -> 0.22093144 | S51: =IF($P51="PROXY",DSTDEV('literature entries'!$D:$AI,IF($J51=1,"ACTIVE GHGE, FARM GATE (kg CO2e/kg)","GHGE, processor gate (kg CO2e/kg)"),INDIRECT($K51)),GETPIVOTDATA(IF($J51=1,"StdDev of ACTIVE GHGE, FARM GATE (kg CO2e/kg)","StdDev of GHGE, processor gate (kg CO2e/kg)"),'Pivot Table_GHG'!$A$3,"SUB TYPE",$B51)) -> 0.083542949 | W51: greens | X51: =IF($W51="DIRECT",M51,DCOUNT('literature entries'!$D:$AI,IF($J51=1,"ACTIVE CED, FARM GATE (MJ/kg)","CED, processor gate (MJ/kg)"),INDIRECT($W51))) -> 10 | Y51: =IF($W51="DIRECT","",DAVERAGE('literature entries'!$D:$AI,IF($J51=1,"ACTIVE CED, FARM GATE (MJ/kg)","CED, processor gate (MJ/kg)"),INDIRECT($W51))) -> 2.5657275 | Z51: =IF($W51="DIRECT",$O51,DSTDEV('literature entries'!$D:$AI,IF($J51=1,"ACTIVE CED, FARM GATE (MJ/kg)","CED, processor gate (MJ/kg)"),INDIRECT($W51))) -> 1.5197673 | AA51: =IF($W51="DIRECT",$O51,$Z51/$Y51*$N51) -> 0.91855891 | AB51: greens | AC51: =IF($AB51="DIRECT",Q51,DCOUNT('literature entries'!$D:$AI,IF($J51=1,"ACTIVE GHGE, FARM GATE (kg CO2e/kg)","GHGE, processor gate (kg CO2e/kg)"),INDIRECT($AB51))) -> 22 | AD51: =IF($AB51="DIRECT","",DAVERAGE('literature entries'!$D:$AI,IF($J51=1,"ACTIVE GHGE, FARM GATE (kg CO2e/kg)","GHGE, processor gate (kg CO2e/kg)"),INDIRECT($AB51))) -> 0.18561974 | AE51: =IF($AB51="DIRECT",$S51,DSTDEV('literature entries'!$D:$AI,IF($J51=1,"ACTIVE GHGE, FARM GATE (kg CO2e/kg)","GHGE, processor gate (kg CO2e/kg)"),INDIRECT($AB51))) -> 0.097833632 | AF51: =IF($AB51="DIRECT",$S51,$AE51/$AD51*$R51) -> 0.11644518
